Workbook

Sheet Cover
B9: Tesla
B10: Company analysis

Sheet Drivers
B1: Drivers
B3: Selected case | C3: 2
B4: Company | C4: Tesla
B5: Currency | C5: USD
B6: Domestic country | C6: United States
B7: 10-year treasury yield ( 08.06.2026) | C7: 0.0455
B8: Market risk premium US | C8: 0.055
B9: Company beta ( 08.06.2026) | C9: 1.18
B10: Tesla share price ( 08.06.2026) | C10: 408.95
B11: Bond Yield (Mar 19 2030) | C11: 0.0545
B12: Corporate tax rate | C12: 0.21
B13: Expected inflation | C13: 0.031
B14: No. of Shares (million) | C14: 3752.43

Sheet Input ->
B14: Input -->

Sheet P&L Input
B1: P&L Input
B3: ($ millions) | C3: 2021 Act | D3: 2022 Act | E3: 2023 Act | F3: 2024 Act | G3: 2025 Act
B4: Automotive revenues | C4: 47232 | D4: 71462 | E4: 82419 | F4: 77070 | G4: 69526
B5: Energy generation and storage | C5: 2789 | D5: 3909 | E5: 6035 | F5: 10086 | G5: 12771
B6: Services and other | C6: 3802 | D6: 6091 | E6: 8319 | F6: 10534 | G6: 12530
B7: Total revenues | C7: =SUM(C4:C6) -> 53823 | D7: =SUM(D4:D6) -> 81462 | E7: =SUM(E4:E6) -> 96773 | F7: =SUM(F4:F6) -> 97690 | G7: =SUM(G4:G6) -> 94827
B8: Automotive cost of revenues | C8: -33393 | D8: -51108 | E8: -66389 | F8: -62873 | G8: -57165
B9: Energy generation and storage cost of revenues | C9: -2918 | D9: -3621 | E9: -4894 | F9: -7446 | G9: -8969
B10: Services and other cost of revenues | C10: -3906 | D10: -5880 | E10: -7830 | F10: -9921 | G10: -11599
B11: Gross profit | C11: =SUM(C7:C10) -> 13606 | D11: =SUM(D7:D10) -> 20853 | E11: =SUM(E7:E10) -> 17660 | F11: =SUM(F7:F10) -> 17450 | G11: =SUM(G7:G10) -> 17094
B12: Research and development | C12: -2593 | D12: -3075 | E12: -3969 | F12: -4540 | G12: -6411
B13: Selling, general and administrative | C13: -4517 | D13: -3946 | E13: -4800 | F13: -5150 | G13: -5834
B14: Restructuring and other | C14: 27 | D14: -176 | F14: -684 | G14: -494
B15: EBIT | C15: =SUM(C11:C14) -> 6523 | D15: =SUM(D11:D14) -> 13656 | E15: =SUM(E11:E14) -> 8891 | F15: =SUM(F11:F14) -> 7076 | G15: =SUM(G11:G14) -> 4355
B16: Interest income | C16: 56 | D16: 297 | E16: 1066 | F16: 1569 | G16: 1680
B17: Interest expense | C17: -371 | D17: -191 | E17: -156 | F17: -350 | G17: -338
B18: Other income (expense), net | C18: 135 | D18: -43 | E18: 172 | F18: 695 | G18: -419
B19: EBT | C19: =SUM(C15:C18) -> 6343 | D19: =SUM(D15:D18) -> 13719 | E19: =SUM(E15:E18) -> 9973 | F19: =SUM(F15:F18) -> 8990 | G19: =SUM(G15:G18) -> 5278
B20: Provision for income taxes | C20: -699 | D20: -1132 | E20: 5001 | F20: -1837 | G20: -1423
B21: Net income incl. minority interests | C21: =SUM(C19:C20) -> 5644 | D21: =SUM(D19:D20) -> 12587 | E21: =SUM(E19:E20) -> 14974 | F21: =SUM(F19:F20) -> 7153 | G21: =SUM(G19:G20) -> 3855
B22: Minority interests | C22: -125 | D22: -31 | E22: 23 | F22: -62 | G22: -61
B23: Net income | C23: =SUM(C21:C22) -> 5519 | D23: =SUM(D21:D22) -> 12556 | E23: =SUM(E21:E22) -> 14997 | F23: =SUM(F21:F22) -> 7091 | G23: =SUM(G21:G22) -> 3794
B25: KPIs
B26: Revenue % automotive y-o-y | D26: =D4/C4-1 -> 0.51299966 | E26: =E4/D4-1 -> 0.15332624 | F26: =F4/E4-1 -> -0.064900084 | G26: =G4/F4-1 -> -0.09788504
B27: Revenue % generation y-o-y | D27: =D5/C5-1 -> 0.40157763 | E27: =E5/D5-1 -> 0.54387311 | F27: =F5/E5-1 -> 0.67125104 | G27: =G5/F5-1 -> 0.26621059
B28: Revenue % services y-o-y | D28: =D6/C6-1 -> 0.60205155 | E28: =E6/D6-1 -> 0.36578559 | F28: =F6/E6-1 -> 0.26625796 | G28: =G6/F6-1 -> 0.18948168
B29: GP% automotive | C29: =(C4+C8)/C4 -> 0.29300051 | D29: =(D4+D8)/D4 -> 0.2848227 | E29: =(E4+E8)/E4 -> 0.19449399 | F29: =(F4+F8)/F4 -> 0.18420916 | G29: =(G4+G8)/G4 -> 0.1777896
B30: GP% energy generation and automotive | C30: =(C5+C9)/C5 -> -0.046253137 | D30: =(D5+D9)/D5 -> 0.073676132 | E30: =(E5+E9)/E5 -> 0.18906379 | F30: =(F5+F9)/F5 -> 0.26174896 | G30: =(G5+G9)/G5 -> 0.29770574
B31: GP% services and other | C31: =(C6+C10)/C6 -> -0.027354024 | D31: =(D6+D10)/D6 -> 0.034641274 | E31: =(E6+E10)/E6 -> 0.058781103 | F31: =(F6+F10)/F6 -> 0.058192519 | G31: =(G6+G10)/G6 -> 0.074301676
B32: Overall GP% | C32: =(SUM(C4:C6)+SUM(C8:C10))/SUM(C4:C6) -> 0.25279156 | D32: =(SUM(D4:D6)+SUM(D8:D10))/SUM(D4:D6) -> 0.25598439 | E32: =(SUM(E4:E6)+SUM(E8:E10))/SUM(E4:E6) -> 0.18248892 | F32: =(SUM(F4:F6)+SUM(F8:F10))/SUM(F4:F6) -> 0.17862627 | G32: =(SUM(G4:G6)+SUM(G8:G10))/SUM(G4:G6) -> 0.18026511
B33: EBIT % | C33: =C15/C7 -> 0.12119354 | D33: =D15/D7 -> 0.16763644 | E33: =E15/E7 -> 0.0918748 | F33: =F15/F7 -> 0.072433207 | G33: =G15/G7 -> 0.045925738
B34: Net loss % | C34: =C23/C7 -> 0.10253981 | D34: =D23/D7 -> 0.15413322 | E34: =E23/E7 -> 0.15497091 | F34: =F23/F7 -> 0.072586754 | G34: =G23/G7 -> 0.040009702
B35: ROA | C35: =C23/'Balance Sheet Input'!C20 -> 0.088828443 | D35: =D23/'Balance Sheet Input'!D20 -> 0.15249338 | E35: =E23/'Balance Sheet Input'!E20 -> 0.14066105 | F35: =F23/'Balance Sheet Input'!F20 -> 0.058089621 | G35: =G23/'Balance Sheet Input'!G20 -> 0.027531457
B36: ROE | C36: =C23/'Balance Sheet Input'!C35 -> 0.18281493 | D36: =D23/'Balance Sheet Input'!D35 -> 0.28086972 | E36: =E23/'Balance Sheet Input'!E35 -> 0.23943864 | F36: =F23/'Balance Sheet Input'!F35 -> 0.09725289 | G36: =G23/'Balance Sheet Input'!G35 -> 0.04619112

Sheet Balance Sheet Input
B1: Balance Sheet Input
B3: ($ millions) | C3: 2021 Act | D3: 2022 Act | E3: 2023 Act | F3: 2024 Act | G3: 2025 Act
B4: Cash and cash equivalents | C4: 17576 | D4: 16253 | E4: 16398 | F4: 16139 | G4: 16513
B5: Accounts receivable, net | C5: 1913 | D5: 2952 | E5: 3508 | F5: 4418 | G5: 4576
B6: Inventory | C6: 5757 | D6: 12839 | E6: 13626 | F6: 12017 | G6: 12392
B7: Prepaid expenses and other current assets | C7: 1723 | D7: 2941 | E7: 3388 | F7: 5362 | G7: 7615
B8: Short-term investments | C8: 131 | D8: 5932 | E8: 12696 | F8: 20424 | G8: 27546
B9: Total current assets | C9: =SUM(C4:C8) -> 27100 | D9: =SUM(D4:D8) -> 40917 | E9: =SUM(E4:E8) -> 49616 | F9: =SUM(F4:F8) -> 58360 | G9: =SUM(G4:G8) -> 68642
B11: Operating lease vehicles, net | C11: 4511 | D11: 5035 | E11: 5989 | F11: 5581 | G11: 4912
B12: Solar energy systems, leased and to be leased, net | C12: 5765 | D12: 5489 | E12: 5229 | F12: 4924 | G12: 4604
B13: Property, plant and equipment, net | C13: 18884 | D13: 23548 | E13: 29725 | F13: 35836 | G13: 40643
B14: Operating lease right-of-use assets | C14: 2016 | D14: 2563 | E14: 4180 | F14: 5160 | G14: 6027
B15: Intangible assets, net | C15: 257 | D15: 215 | E15: 178 | F15: 1076 | G15: 1008
B16: Deferred tax assets | C16: 0 | D16: 328 | E16: 6733 | F16: 6524 | G16: 6925
B17: Good will | C17: 200 | D17: 194 | E17: 253 | F17: 0 | G17: 0
B18: Digital assets,net | C18: 1260 | D18: 184 | E18: 184 | F18: 0 | G18: 0
B19: Other assets | C19: 2138 | D19: 3865 | E19: 4531 | F19: 4609 | G19: 5045
B20: Total assets | C20: =SUM(C9:C19) -> 62131 | D20: =SUM(D9:D19) -> 82338 | E20: =SUM(E9:E19) -> 106618 | F20: =SUM(F9:F19) -> 122070 | G20: =SUM(G9:G19) -> 137806
B22: Accounts payable | C22: 10025 | D22: 15255 | E22: 14431 | F22: 12474 | G22: 13371
B23: Accrued liabilities | C23: 5719 | D23: 8205 | E23: 9080 | F23: 10723 | G23: 13279
B24: Deferred revenue | C24: 1447 | D24: 1747 | E24: 2864 | F24: 3168 | G24: 3424
B25: customer deposite | C25: 925 | D25: 0 | E25: 0 | F25: 0 | G25: 0
B26: Current portion of long-term debt and capital leases | C26: 1589 | D26: 1502 | E26: 2373 | F26: 2456 | G26: 1640
B27: Total current liabilities | C27: =SUM(C22:C26) -> 19705 | D27: =SUM(D22:D26) -> 26709 | E27: =SUM(E22:E26) -> 28748 | F27: =SUM(F22:F26) -> 28821 | G27: =SUM(G22:G26) -> 31714
B29: Long-term debt and capital leases, net of current
B30: portion | C30: 5245 | D30: 1597 | E30: 2857 | F30: 5757 | G30: 6736
B31: Other liabilities | C31: 3546 | D31: 5330 | E31: 8153 | F31: 10495 | G31: 12860
B32: Deferred revenue, net of current portion | C32: 2052 | D32: 2804 | E32: 3251 | F32: 3317 | G32: 3631
B33: Total liabilities | C33: =SUM(C27:C32) -> 30548 | D33: =SUM(D27:D32) -> 36440 | E33: =SUM(E27:E32) -> 43009 | F33: =SUM(F27:F32) -> 48390 | G33: =SUM(G27:G32) -> 54941
B34: Redeemable noncontrolling interests in subsidiaries | C34: 568 | D34: 409 | E34: 242 | F34: 63 | G34: 58
B35: Total stockholders' equity | C35: 30189 | D35: 44704 | E35: 62634 | F35: 72913 | G35: 82137
B36: Noncontrolling interests in subsidiaries | C36: 826 | D36: 785 | E36: 733 | F36: 704 | G36: 670
B37: Total liabilities and equity | C37: =C33+C35+C36+C34 -> 62131 | D37: =D33+D35+D36+D34 -> 82338 | E37: =E33+E35+E36+E34 -> 106618 | F37: =F33+F35+F36+F34 -> 122070 | G37: =G33+G35+G36+G34 -> 137806
B39: KPIs
B40: Liquidity ratios
B41: Quick ratio | C41: =C4/C27 -> 0.89195636 | D41: =D4/D27 -> 0.60852147 | E41: =E4/E27 -> 0.5704049 | F41: =F4/F27 -> 0.55997363 | G41: =G4/G27 -> 0.52068487
B42: Current ratio | C42: =C9/C27 -> 1.3752855 | D42: =D9/D27 -> 1.5319555 | E42: =E9/E27 -> 1.725894 | F42: =F9/F27 -> 2.0249124 | G42: =G9/G27 -> 2.1644069
B43: DSO | C43: =C5/'P&L Input'!C7*360 -> 12.795273 | D43: =D5/'P&L Input'!D7*360 -> 13.045592 | E43: =E5/'P&L Input'!E7*360 -> 13.049921 | F43: =F5/'P&L Input'!F7*360 -> 16.280889 | G43: =G5/'P&L Input'!G7*360 -> 17.372267
B44: DIO | C44: =-C6/SUM('P&L Input'!C8:C10)*360 -> 51.533431 | D44: =-D6/SUM('P&L Input'!D8:D10)*360 -> 76.259961 | E44: =-E6/SUM('P&L Input'!E8:E10)*360 -> 62.004475 | F44: =-F6/SUM('P&L Input'!F8:F10)*360 -> 53.914756 | G44: =-G6/SUM('P&L Input'!G8:G10)*360 -> 57.390298
B45: DPO | C45: =-C22/SUM('P&L Input'!C8:C10)*360 -> 89.73817 | D45: =-D22/SUM('P&L Input'!D8:D10)*360 -> 90.610305 | E45: =-E22/SUM('P&L Input'!E8:E10)*360 -> 65.667589 | F45: =-F22/SUM('P&L Input'!F8:F10)*360 -> 55.965105 | G45: =-G22/SUM('P&L Input'!G8:G10)*360 -> 61.924279
B46: Net Trading Cycle | C46: =C43+C44-C45 -> -25.409466 | D46: =D43+D44-D45 -> -1.3047522 | E46: =E43+E44-E45 -> 9.3868062 | F46: =F43+F44-F45 -> 14.23054 | G46: =G43+G44-G45 -> 12.838286
B47: Solvency ratios
B48: Debt ratio | C48: =C33/C20 -> 0.49167082 | D48: =D33/D20 -> 0.44256601 | E48: =E33/E20 -> 0.40339342 | F48: =F33/F20 -> 0.39641189 | G48: =G33/G20 -> 0.39868366
B49: Interest coverage | C49: <0 | D49: <0 | E49: <0 | F49: <0 | G49: <0

Sheet Workings ->
B14: Workings -->

Sheet Income Statement items
B14: Income Statement items

Sheet Automotive
B14: Automotive

Sheet Deliveries
B1: Deliveries
B3: ($ millions) | C3: Tesla Deliveries
B4: Vehicle | C4: 2021 Act | D4: 2022 Act | E4: 2023 Act | F4: 2024 Act | G4: 2025 Act | H4: 2026 Fcst | I4: 2027 Fcst | J4: 2028 Fcst | K4: 2029 Fcst | L4: 2030 Fcst | M4: 2031 Fcst | N4: 2032 Fcst | O4: 2033 Fcst | P4: 2034 Fcst | Q4: 2035 Fcst
B5: Tesla Model 3 | C5: 500000 | D5: 530000 | E5: 500000 | F5: 480000 | G5: 450000 | H5: =H24 -> 450000 | I5: =I24 -> 450000 | J5: =J24 -> 500000 | K5: =K24 -> 550000 | L5: =L24 -> 600000 | M5: =M24 -> 650000 | N5: =N24 -> 700000 | O5: =O24 -> 750000 | ... Q5: =Q24 -> 850000
B6: Tesla Model S and X | C6: 50000 | D6: 67000 | E6: 69000 | F6: 56000 | G6: 50000 | H6: =H25 -> 40000 | I6: =I25 -> 20000 | J6: =J25 -> 10000 | K6: =K25 -> 0 | L6: =L25 -> 0 | M6: =M25 -> 0 | N6: =N25 -> 0 | O6: =O25 -> 0 | ... Q6: =Q25 -> 0
B7: Tesla Model Y | C7: 411000 | D7: 717000 | E7: 1140000 | F7: 1124000 | G7: 1130000 | H7: =H26 -> 1200000 | I7: =I26 -> 1350000 | J7: =J26 -> 1500000 | K7: =K26 -> 1650000 | L7: =L26 -> 1850000 | M7: =M26 -> 2000000 | N7: =N26 -> 2150000 | O7: =O26 -> 2300000 | ... Q7: =Q26 -> 2600000
B8: Tesla Cybertruck | E8: 900 | F8: 19000 | G8: 50000 | H8: =H27 -> 75000 | I8: =I27 -> 120000 | J8: =J27 -> 180000 | K8: =K27 -> 250000 | L8: =L27 -> 300000 | M8: =M27 -> 350000 | N8: =N27 -> 400000 | O8: =O27 -> 450000 | ... Q8: =Q27 -> 550000
B9: Tesla Semi | C9: 0 | D9: 90 | E9: 180 | F9: 290 | G9: 5000 | H9: =H28 -> 10000 | I9: =I28 -> 20000 | J9: =J28 -> 35000 | K9: =K28 -> 50000 | L9: =L28 -> 75000 | M9: =M28 -> 100000 | N9: =N28 -> 125000 | O9: =O28 -> 150000 | ... Q9: =Q28 -> 200000
B10: Total | C10: =SUM(C5:C9) -> 961000 | D10: =SUM(D5:D9) -> 1314090 | E10: =SUM(E5:E9) -> 1710080 | F10: =SUM(F5:F9) -> 1679290 | G10: =SUM(G5:G9) -> 1685000 | H10: =SUM(H5:H9) -> 1775000 | I10: =SUM(I5:I9) -> 1960000 | J10: =SUM(J5:J9) -> 2225000 | ... Q10: =SUM(Q5:Q9) -> 4200000
B12: y-o-y growth %
B14: Tesla Model 3 | C14: n.a. | D14: =D5/C5-1 -> 0.06 | E14: =E5/D5-1 -> -0.056603774 | F14: =F5/E5-1 -> -0.04 | G14: =G5/F5-1 -> -0.0625 | H14: =H5/G5-1 -> 0 | I14: =I5/H5-1 -> 0 | J14: =J5/I5-1 -> 0.11111111 | K14: =K5/J5-1 -> 0.1 | ... Q14: =Q5/P5-1 -> 0.0625
B15: Tesla Model S and X | C15: n.a. | D15: =D6/C6-1 -> 0.34 | E15: =E6/D6-1 -> 0.029850746 | F15: =F6/E6-1 -> -0.1884058 | G15: =G6/F6-1 -> -0.10714286 | H15: =H6/G6-1 -> -0.2 | I15: =I6/H6-1 -> -0.5 | J15: =J6/I6-1 -> -0.5 | K15: n.a. | L15: n.a. | M15: n.a. | N15: n.a. | O15: n.a. | P15: n.a. | Q15: n.a.
B16: Tesla Model Y | C16: n.a. | D16: =D7/C7-1 -> 0.74452555 | E16: =E7/D7-1 -> 0.58995816 | F16: =F7/E7-1 -> -0.014035088 | G16: =G7/F7-1 -> 0.0053380783 | H16: =H7/G7-1 -> 0.061946903 | I16: =I7/H7-1 -> 0.125 | J16: =J7/I7-1 -> 0.11111111 | K16: =K7/J7-1 -> 0.1 | ... Q16: =Q7/P7-1 -> 0.06122449
B17: Tesla Cybertruck | C17: n.a. | D17: n.a. | E17: n.a. | F17: =F8/E8-1 -> 20.111111 | G17: =G8/F8-1 -> 1.6315789 | H17: =H8/G8-1 -> 0.5 | I17: =I8/H8-1 -> 0.6 | J17: =J8/I8-1 -> 0.5 | K17: =K8/J8-1 -> 0.38888889 | L17: =L8/K8-1 -> 0.2 | M17: =M8/L8-1 -> 0.16666667 | ... Q17: =Q8/P8-1 -> 0.1
B18: Tesla Semi | C18: n.a. | D18: n.a. | E18: =E9/D9-1 -> 1 | F18: =F9/E9-1 -> 0.61111111 | G18: =G9/F9-1 -> 16.241379 | H18: =H9/G9-1 -> 1 | I18: =I9/H9-1 -> 1 | J18: =J9/I9-1 -> 0.75 | K18: =K9/J9-1 -> 0.42857143 | L18: =L9/K9-1 -> 0.5 | ... Q18: =Q9/P9-1 -> 0.14285714
B23: Selected case
B24: Tesla Model 3 | H24: =CHOOSE(Drivers!$C$3,H31,H38,H45) -> 450000 | I24: =CHOOSE(Drivers!$C$3,I31,I38,I45) -> 450000 | J24: =CHOOSE(Drivers!$C$3,J31,J38,J45) -> 500000 | K24: =CHOOSE(Drivers!$C$3,K31,K38,K45) -> 550000 | L24: =CHOOSE(Drivers!$C$3,L31,L38,L45) -> 600000 | M24: =CHOOSE(Drivers!$C$3,M31,M38,M45) -> 650000 | N24: =CHOOSE(Drivers!$C$3,N31,N38,N45) -> 700000 | O24: =CHOOSE(Drivers!$C$3,O31,O38,O45) -> 750000 | ... Q24: =CHOOSE(Drivers!$C$3,Q31,Q38,Q45) -> 850000
B25: Tesla Model S and X | H25: =CHOOSE(Drivers!$C$3,H32,H39,H46) -> 40000 | I25: =CHOOSE(Drivers!$C$3,I32,I39,I46) -> 20000 | J25: =CHOOSE(Drivers!$C$3,J32,J39,J46) -> 10000 | K25: =CHOOSE(Drivers!$C$3,K32,K39,K46) -> 0 | L25: =CHOOSE(Drivers!$C$3,L32,L39,L46) -> 0 | M25: =CHOOSE(Drivers!$C$3,M32,M39,M46) -> 0 | N25: =CHOOSE(Drivers!$C$3,N32,N39,N46) -> 0 | O25: =CHOOSE(Drivers!$C$3,O32,O39,O46) -> 0 | ... Q25: =CHOOSE(Drivers!$C$3,Q32,Q39,Q46) -> 0
B26: Tesla Model Y | H26: =CHOOSE(Drivers!$C$3,H33,H40,H47) -> 1200000 | I26: =CHOOSE(Drivers!$C$3,I33,I40,I47) -> 1350000 | J26: =CHOOSE(Drivers!$C$3,J33,J40,J47) -> 1500000 | K26: =CHOOSE(Drivers!$C$3,K33,K40,K47) -> 1650000 | L26: =CHOOSE(Drivers!$C$3,L33,L40,L47) -> 1850000 | M26: =CHOOSE(Drivers!$C$3,M33,M40,M47) -> 2000000 | N26: =CHOOSE(Drivers!$C$3,N33,N40,N47) -> 2150000 | O26: =CHOOSE(Drivers!$C$3,O33,O40,O47) -> 2300000 | ... Q26: =CHOOSE(Drivers!$C$3,Q33,Q40,Q47) -> 2600000
B27: Tesla Cybertruck | H27: =CHOOSE(Drivers!$C$3,H34,H41,H48) -> 75000 | I27: =CHOOSE(Drivers!$C$3,I34,I41,I48) -> 120000 | J27: =CHOOSE(Drivers!$C$3,J34,J41,J48) -> 180000 | K27: =CHOOSE(Drivers!$C$3,K34,K41,K48) -> 250000 | L27: =CHOOSE(Drivers!$C$3,L34,L41,L48) -> 300000 | M27: =CHOOSE(Drivers!$C$3,M34,M41,M48) -> 350000 | N27: =CHOOSE(Drivers!$C$3,N34,N41,N48) -> 400000 | O27: =CHOOSE(Drivers!$C$3,O34,O41,O48) -> 450000 | ... Q27: =CHOOSE(Drivers!$C$3,Q34,Q41,Q48) -> 550000
B28: Tesla Semi | H28: =CHOOSE(Drivers!$C$3,H35,H42,H49) -> 10000 | I28: =CHOOSE(Drivers!$C$3,I35,I42,I49) -> 20000 | J28: =CHOOSE(Drivers!$C$3,J35,J42,J49) -> 35000 | K28: =CHOOSE(Drivers!$C$3,K35,K42,K49) -> 50000 | L28: =CHOOSE(Drivers!$C$3,L35,L42,L49) -> 75000 | M28: =CHOOSE(Drivers!$C$3,M35,M42,M49) -> 100000 | N28: =CHOOSE(Drivers!$C$3,N35,N42,N49) -> 125000 | O28: =CHOOSE(Drivers!$C$3,O35,O42,O49) -> 150000 | ... Q28: =CHOOSE(Drivers!$C$3,Q35,Q42,Q49) -> 200000
B30: Best case
B31: Tesla Model 3 | H31: =H38*105% -> 472500 | I31: =I38*105% -> 472500 | J31: =J38*105% -> 525000 | K31: =K38*105% -> 577500 | L31: =L38*105% -> 630000 | M31: =M38*105% -> 682500 | N31: =N38*105% -> 735000 | O31: =O38*105% -> 787500 | ... Q31: =Q38*105% -> 892500
B32: Tesla Model S and X | H32: =H39*105% -> 42000 | I32: =I39*105% -> 21000 | J32: =J39*105% -> 10500 | K32: =K39*105% -> 0 | L32: =L39*105% -> 0 | M32: =M39*105% -> 0 | N32: =N39*105% -> 0 | O32: =O39*105% -> 0 | ... Q32: =Q39*105% -> 0
B33: Tesla Model Y | H33: =H40*105% -> 1260000 | I33: =I40*105% -> 1417500 | J33: =J40*105% -> 1575000 | K33: =K40*105% -> 1732500 | L33: =L40*105% -> 1942500 | M33: =M40*105% -> 2100000 | N33: =N40*105% -> 2257500 | O33: =O40*105% -> 2415000 | ... Q33: =Q40*105% -> 2730000
B34: Tesla Cybertruck | H34: =H41*105% -> 78750 | I34: =I41*105% -> 126000 | J34: =J41*105% -> 189000 | K34: =K41*105% -> 262500 | L34: =L41*105% -> 315000 | M34: =M41*105% -> 367500 | N34: =N41*105% -> 420000 | O34: =O41*105% -> 472500 | ... Q34: =Q41*105% -> 577500
B35: Tesla Semi | H35: =H42*105% -> 10500 | I35: =I42*105% -> 21000 | J35: =J42*105% -> 36750 | K35: =K42*105% -> 52500 | L35: =L42*105% -> 78750 | M35: =M42*105% -> 105000 | N35: =N42*105% -> 131250 | O35: =O42*105% -> 157500 | ... Q35: =Q42*105% -> 210000
B37: Base case
B38: Tesla Model 3 | H38: 450000 | I38: 450000 | J38: 500000 | K38: 550000 | L38: 600000 | M38: 650000 | N38: 700000 | O38: 750000 | P38: 800000 | Q38: 850000
B39: Tesla Model S and X | H39: 40000 | I39: 20000 | J39: 10000 | K39: 0 | L39: 0 | M39: 0 | N39: 0 | O39: 0 | P39: 0 | Q39: 0
B40: Tesla Model Y | H40: 1200000 | I40: 1350000 | J40: 1500000 | K40: 1650000 | L40: 1850000 | M40: 2000000 | N40: 2150000 | O40: 2300000 | P40: 2450000 | Q40: 2600000
B41: Tesla Cybertruck | H41: 75000 | I41: 120000 | J41: 180000 | K41: 250000 | L41: 300000 | M41: 350000 | N41: 400000 | O41: 450000 | P41: 500000 | Q41: 550000
B42: Tesla Semi | H42: 10000 | I42: 20000 | J42: 35000 | K42: 50000 | L42: 75000 | M42: 100000 | N42: 125000 | O42: 150000 | P42: 175000 | Q42: 200000
B44: Worst case
B45: Tesla Model 3 | H45: =H38*95% -> 427500 | I45: =I38*95% -> 427500 | J45: =J38*95% -> 475000 | K45: =K38*95% -> 522500 | L45: =L38*95% -> 570000 | M45: =M38*95% -> 617500 | N45: =N38*95% -> 665000 | O45: =O38*95% -> 712500 | ... Q45: =Q38*95% -> 807500
B46: Tesla Model S and X | H46: =H39*95% -> 38000 | I46: =I39*95% -> 19000 | J46: =J39*95% -> 9500 | K46: =K39*95% -> 0 | L46: =L39*95% -> 0 | M46: =M39*95% -> 0 | N46: =N39*95% -> 0 | O46: =O39*95% -> 0 | ... Q46: =Q39*95% -> 0
B47: Tesla Cybertruck | H47: =H40*95% -> 1140000 | I47: =I40*95% -> 1282500 | J47: =J40*95% -> 1425000 | K47: =K40*95% -> 1567500 | L47: =L40*95% -> 1757500 | M47: =M40*95% -> 1900000 | N47: =N40*95% -> 2042500 | O47: =O40*95% -> 2185000 | ... Q47: =Q40*95% -> 2470000
B48: Tesla Pickup | H48: =H41*95% -> 71250 | I48: =I41*95% -> 114000 | J48: =J41*95% -> 171000 | K48: =K41*95% -> 237500 | L48: =L41*95% -> 285000 | M48: =M41*95% -> 332500 | N48: =N41*95% -> 380000 | O48: =O41*95% -> 427500 | ... Q48: =Q41*95% -> 522500
B49: Tesla Semi | H49: =H42*95% -> 9500 | I49: =I42*95% -> 19000 | J49: =J42*95% -> 33250 | K49: =K42*95% -> 47500 | L49: =L42*95% -> 71250 | M49: =M42*95% -> 95000 | N49: =N42*95% -> 118750 | O49: =O42*95% -> 142500 | ... Q49: =Q42*95% -> 190000

Sheet Deliveries development

Sheet Deliveries comparables
B1: Deliveries comparables
B3: Comparables 2021-2025
B6: Vehicle Sales 2021-2025 - average | C6: Average | D6: Adj. Average
B7: BYD (BEV only) | C7: 939000 | D7: =C7 -> 939000
B8: NIO | C8: 128000 | D8: =C8 -> 128000
B9: XPeng | C9: 115000 | D9: =C9 -> 115000
B10: Li Auto | C10: 226000 | D10: =C10 -> 226000
B11: Rivian | C11: 25000 | D11: =C11 -> 25000
B12: Lucid | C12: 4000 | D12: =C12 -> 4000
B13: Toyota | C13: 10100000 | D13: =C13 -> 10100000
B14: Volkswagen Group | C14: 8700000 | D14: =C14 -> 8700000
B15: Hyundai-Kia | C15: 6800000 | D15: =C15 -> 6800000
B16: General Motors | C16: 6100000 | D16: =C16 -> 6100000
B17: Ford | C17: 4300000 | D17: =C17 -> 4300000
B18: BMW | C18: 2300000 | D18: =C18 -> 2300000
B19: Mercedes-Benz | C19: 2100000 | D19: =C19 -> 2100000
B20: Ferrari | C20: n.a. | D20: n.a.
B21: Scania | C21: n.a. | D21: n.a.
B22: MAN | C22: n.a. | D22: n.a.
B23: Paccar | C23: n.a. | D23: n.a.
B24: Average | C24: n.a. | D24: =AVERAGE(D7:D23) -> 3218230.8
B28: Tesla Expected Deliveries
B29: 2026 | D29: =Deliveries!H$10 -> 1775000
B30: 2030 | D30: =Deliveries!L$10 -> 2825000
B31: 2035 | D31: =Deliveries!Q$10 -> 4200000

Sheet Average Prices
B1: Average prices
B3: Model and Version | C3: Range(max) | D3: Base price | E3: Fully loaded | F3: Average Price per Model
B4: Tesla Model 3 | C4: 466 miles | D4: 36990 | E4: 56990 | F4: =AVERAGE(D4:E4) -> 46990
B6: Tesla Model S | C6: 405 miles | D6: 94990 | E6: 111990 | F6: =AVERAGE(D6:E6) -> 103490
B7: Tesla Model X | C7: 348 miles | D7: 101630 | E7: 116990 | F7: =AVERAGE(D7:E7) -> 109310
B8: Tesla Model X & S | F8: =AVERAGE(F6:F7) -> 106400
B10: Tesla Model Y | C10: 357 miles | D10: 39990 | E10: 59990 | F10: =AVERAGE(D10:E10) -> 49990
B12: Tesla Cybertruck | C12: 340 miles | D12: 69990 | E12: 117999 | F12: =AVERAGE(D12:E12) -> 93994.5
B14: Tesla Semi | C14: 805 miles | D14: 260000 | E14: 290000 | F14: =AVERAGE(D14:E14) -> 275000

Sheet Automotive Revenue
B1: Revenue Automotive
C3: Tesla Revenue Automotive (in mln $)
B4: Vehicle | C4: 2021 Act | D4: 2022 Act | E4: 2023 Act | F4: 2024 Act | G4: 2025 Act | H4: 2026 Fcst | I4: 2027 Fcst | J4: 2028 Fcst | K4: 2029 Fcst | L4: 2030 Fcst | M4: 2031 Fcst | N4: 2032 Fcst | O4: 2033 Fcst | P4: 2034 Fcst | Q4: 2035 Fcst | R4: Average Price ($)
B5: Tesla Model 3 | C5: =($R5*Deliveries!C5)/1000000 -> 23495 | D5: =($R5*Deliveries!D5)/1000000 -> 24904.7 | E5: =($R5*Deliveries!E5)/1000000 -> 23495 | F5: =($R5*Deliveries!F5)/1000000 -> 22555.2 | G5: =($R5*Deliveries!G5)/1000000 -> 21145.5 | H5: =($R5*Deliveries!H5)*H15/1000000 -> 21145.5 | I5: =($R5*Deliveries!I5)*I15/1000000 -> 21145.5 | J5: =($R5*Deliveries!J5)*J15/1000000 -> 23495 | K5: =($R5*Deliveries!K5)*K15/1000000 -> 25844.5 | L5: =($R5*Deliveries!L5)*L15/1000000 -> 28194 | M5: =($R5*Deliveries!M5)*M15/1000000 -> 30543.5 | N5: =($R5*Deliveries!N5)*N15/1000000 -> 32893 | O5: =($R5*Deliveries!O5)*O15/1000000 -> 35242.5 | ... Q5: =($R5*Deliveries!Q5)*Q15/1000000 -> 39941.5 | R5: ='Average Prices'!F4 -> 46990
B6: Tesla Model S and X | C6: =($R6*Deliveries!C6)/1000000 -> 5320 | D6: =($R6*Deliveries!D6)/1000000 -> 7128.8 | E6: =($R6*Deliveries!E6)/1000000 -> 7341.6 | F6: =($R6*Deliveries!F6)/1000000 -> 5958.4 | G6: =($R6*Deliveries!G6)/1000000 -> 5320 | H6: =($R6*Deliveries!H6)*H16/1000000 -> 4256 | I6: =($R6*Deliveries!I6)*I16/1000000 -> 2128 | J6: =($R6*Deliveries!J6)*J16/1000000 -> 1064 | K6: =($R6*Deliveries!K6)*K16/1000000 -> 0 | L6: =($R6*Deliveries!L6)*L16/1000000 -> 0 | M6: =($R6*Deliveries!M6)*M16/1000000 -> 0 | N6: =($R6*Deliveries!N6)*N16/1000000 -> 0 | O6: =($R6*Deliveries!O6)*O16/1000000 -> 0 | ... Q6: =($R6*Deliveries!Q6)*Q16/1000000 -> 0 | R6: ='Average Prices'!F8 -> 106400
B7: Tesla Model Y | C7: =($R7*Deliveries!C7)/1000000 -> 20545.89 | D7: =($R7*Deliveries!D7)/1000000 -> 35842.83 | E7: =($R7*Deliveries!E7)/1000000 -> 56988.6 | F7: =($R7*Deliveries!F7)/1000000 -> 56188.76 | G7: =($R7*Deliveries!G7)/1000000 -> 56488.7 | H7: =($R7*Deliveries!H7)*H17/1000000 -> 59988 | I7: =($R7*Deliveries!I7)*I17/1000000 -> 67486.5 | J7: =($R7*Deliveries!J7)*J17/1000000 -> 74985 | K7: =($R7*Deliveries!K7)*K17/1000000 -> 82483.5 | L7: =($R7*Deliveries!L7)*L17/1000000 -> 92481.5 | M7: =($R7*Deliveries!M7)*M17/1000000 -> 99980 | N7: =($R7*Deliveries!N7)*N17/1000000 -> 107478.5 | O7: =($R7*Deliveries!O7)*O17/1000000 -> 114977 | ... Q7: =($R7*Deliveries!Q7)*Q17/1000000 -> 129974 | R7: ='Average Prices'!F10 -> 49990
B8: Tesla Cybertruck | C8: =($R8*Deliveries!C8)/1000000 -> 0 | D8: =($R8*Deliveries!D8)/1000000 -> 0 | E8: =($R8*Deliveries!E8)/1000000 -> 84.59505 | F8: =($R8*Deliveries!F8)/1000000 -> 1785.8955 | G8: =($R8*Deliveries!G8)/1000000 -> 4699.725 | H8: =($R8*Deliveries!H8)*H18/1000000 -> 7049.5875 | I8: =($R8*Deliveries!I8)*I18/1000000 -> 11279.34 | J8: =($R8*Deliveries!J8)*J18/1000000 -> 16919.01 | K8: =($R8*Deliveries!K8)*K18/1000000 -> 23498.625 | L8: =($R8*Deliveries!L8)*L18/1000000 -> 28198.35 | M8: =($R8*Deliveries!M8)*M18/1000000 -> 32898.075 | N8: =($R8*Deliveries!N8)*N18/1000000 -> 37597.8 | O8: =($R8*Deliveries!O8)*O18/1000000 -> 42297.525 | ... Q8: =($R8*Deliveries!Q8)*Q18/1000000 -> 51696.975 | R8: ='Average Prices'!F12 -> 93994.5
B9: Tesla Semi | C9: =($R9*Deliveries!C9)/1000000 -> 0 | D9: =($R9*Deliveries!D9)/1000000 -> 24.75 | E9: =($R9*Deliveries!E9)/1000000 -> 49.5 | F9: =($R9*Deliveries!F9)/1000000 -> 79.75 | G9: =($R9*Deliveries!G9)/1000000 -> 1375 | H9: =($R9*Deliveries!H9)*H19/1000000 -> 2750 | I9: =($R9*Deliveries!I9)*I19/1000000 -> 5500 | J9: =($R9*Deliveries!J9)*J19/1000000 -> 9625 | K9: =($R9*Deliveries!K9)*K19/1000000 -> 13750 | L9: =($R9*Deliveries!L9)*L19/1000000 -> 20625 | M9: =($R9*Deliveries!M9)*M19/1000000 -> 27500 | N9: =($R9*Deliveries!N9)*N19/1000000 -> 34375 | O9: =($R9*Deliveries!O9)*O19/1000000 -> 41250 | ... Q9: =($R9*Deliveries!Q9)*Q19/1000000 -> 55000 | R9: ='Average Prices'!F14 -> 275000
B10: Total | C10: ='P&L Input'!C4 -> 47232 | D10: ='P&L Input'!D4 -> 71462 | E10: ='P&L Input'!E4 -> 82419 | F10: ='P&L Input'!F4 -> 77070 | G10: ='P&L Input'!G4 -> 69526 | H10: =SUM(H5:H9) -> 95189.087 | I10: =SUM(I5:I9) -> 107539.34 | J10: =SUM(J5:J9) -> 126088.01 | K10: =SUM(K5:K9) -> 145576.62 | L10: =SUM(L5:L9) -> 169498.85 | M10: =SUM(M5:M9) -> 190921.58 | N10: =SUM(N5:N9) -> 212344.3 | O10: =SUM(O5:O9) -> 233767.02 | ... Q10: =SUM(Q5:Q9) -> 276612.47
B14: Selected case
B15: Tesla Model 3 | H15: =CHOOSE(Drivers!$C$3,'Automotive Revenue'!H22,'Automotive Revenue'!H29,'Automotive Revenue'!H36) -> 1 | I15: =CHOOSE(Drivers!$C$3,'Automotive Revenue'!I22,'Automotive Revenue'!I29,'Automotive Revenue'!I36) -> 1 | J15: =CHOOSE(Drivers!$C$3,'Automotive Revenue'!J22,'Automotive Revenue'!J29,'Automotive Revenue'!J36) -> 1 | K15: =CHOOSE(Drivers!$C$3,'Automotive Revenue'!K22,'Automotive Revenue'!K29,'Automotive Revenue'!K36) -> 1 | L15: =CHOOSE(Drivers!$C$3,'Automotive Revenue'!L22,'Automotive Revenue'!L29,'Automotive Revenue'!L36) -> 1 | M15: =CHOOSE(Drivers!$C$3,'Automotive Revenue'!M22,'Automotive Revenue'!M29,'Automotive Revenue'!M36) -> 1 | N15: =CHOOSE(Drivers!$C$3,'Automotive Revenue'!N22,'Automotive Revenue'!N29,'Automotive Revenue'!N36) -> 1 | O15: =CHOOSE(Drivers!$C$3,'Automotive Revenue'!O22,'Automotive Revenue'!O29,'Automotive Revenue'!O36) -> 1 | ... Q15: =CHOOSE(Drivers!$C$3,'Automotive Revenue'!Q22,'Automotive Revenue'!Q29,'Automotive Revenue'!Q36) -> 1
B16: Tesla Model S and X | H16: =CHOOSE(Drivers!$C$3,'Automotive Revenue'!H23,'Automotive Revenue'!H30,'Automotive Revenue'!H37) -> 1 | I16: =CHOOSE(Drivers!$C$3,'Automotive Revenue'!I23,'Automotive Revenue'!I30,'Automotive Revenue'!I37) -> 1 | J16: =CHOOSE(Drivers!$C$3,'Automotive Revenue'!J23,'Automotive Revenue'!J30,'Automotive Revenue'!J37) -> 1 | K16: =CHOOSE(Drivers!$C$3,'Automotive Revenue'!K23,'Automotive Revenue'!K30,'Automotive Revenue'!K37) -> 1 | L16: =CHOOSE(Drivers!$C$3,'Automotive Revenue'!L23,'Automotive Revenue'!L30,'Automotive Revenue'!L37) -> 1 | M16: =CHOOSE(Drivers!$C$3,'Automotive Revenue'!M23,'Automotive Revenue'!M30,'Automotive Revenue'!M37) -> 1 | N16: =CHOOSE(Drivers!$C$3,'Automotive Revenue'!N23,'Automotive Revenue'!N30,'Automotive Revenue'!N37) -> 1 | O16: =CHOOSE(Drivers!$C$3,'Automotive Revenue'!O23,'Automotive Revenue'!O30,'Automotive Revenue'!O37) -> 1 | ... Q16: =CHOOSE(Drivers!$C$3,'Automotive Revenue'!Q23,'Automotive Revenue'!Q30,'Automotive Revenue'!Q37) -> 1
B17: Tesla Model Y | H17: =CHOOSE(Drivers!$C$3,'Automotive Revenue'!H24,'Automotive Revenue'!H31,'Automotive Revenue'!H38) -> 1 | I17: =CHOOSE(Drivers!$C$3,'Automotive Revenue'!I24,'Automotive Revenue'!I31,'Automotive Revenue'!I38) -> 1 | J17: =CHOOSE(Drivers!$C$3,'Automotive Revenue'!J24,'Automotive Revenue'!J31,'Automotive Revenue'!J38) -> 1 | K17: =CHOOSE(Drivers!$C$3,'Automotive Revenue'!K24,'Automotive Revenue'!K31,'Automotive Revenue'!K38) -> 1 | L17: =CHOOSE(Drivers!$C$3,'Automotive Revenue'!L24,'Automotive Revenue'!L31,'Automotive Revenue'!L38) -> 1 | M17: =CHOOSE(Drivers!$C$3,'Automotive Revenue'!M24,'Automotive Revenue'!M31,'Automotive Revenue'!M38) -> 1 | N17: =CHOOSE(Drivers!$C$3,'Automotive Revenue'!N24,'Automotive Revenue'!N31,'Automotive Revenue'!N38) -> 1 | O17: =CHOOSE(Drivers!$C$3,'Automotive Revenue'!O24,'Automotive Revenue'!O31,'Automotive Revenue'!O38) -> 1 | ... Q17: =CHOOSE(Drivers!$C$3,'Automotive Revenue'!Q24,'Automotive Revenue'!Q31,'Automotive Revenue'!Q38) -> 1
B18: Tesla Cybertruck | H18: =CHOOSE(Drivers!$C$3,'Automotive Revenue'!H25,'Automotive Revenue'!H32,'Automotive Revenue'!H39) -> 1 | I18: =CHOOSE(Drivers!$C$3,'Automotive Revenue'!I25,'Automotive Revenue'!I32,'Automotive Revenue'!I39) -> 1 | J18: =CHOOSE(Drivers!$C$3,'Automotive Revenue'!J25,'Automotive Revenue'!J32,'Automotive Revenue'!J39) -> 1 | K18: =CHOOSE(Drivers!$C$3,'Automotive Revenue'!K25,'Automotive Revenue'!K32,'Automotive Revenue'!K39) -> 1 | L18: =CHOOSE(Drivers!$C$3,'Automotive Revenue'!L25,'Automotive Revenue'!L32,'Automotive Revenue'!L39) -> 1 | M18: =CHOOSE(Drivers!$C$3,'Automotive Revenue'!M25,'Automotive Revenue'!M32,'Automotive Revenue'!M39) -> 1 | N18: =CHOOSE(Drivers!$C$3,'Automotive Revenue'!N25,'Automotive Revenue'!N32,'Automotive Revenue'!N39) -> 1 | O18: =CHOOSE(Drivers!$C$3,'Automotive Revenue'!O25,'Automotive Revenue'!O32,'Automotive Revenue'!O39) -> 1 | ... Q18: =CHOOSE(Drivers!$C$3,'Automotive Revenue'!Q25,'Automotive Revenue'!Q32,'Automotive Revenue'!Q39) -> 1
B19: Tesla Semi | H19: =CHOOSE(Drivers!$C$3,'Automotive Revenue'!H26,'Automotive Revenue'!H33,'Automotive Revenue'!H40) -> 1 | I19: =CHOOSE(Drivers!$C$3,'Automotive Revenue'!I26,'Automotive Revenue'!I33,'Automotive Revenue'!I40) -> 1 | J19: =CHOOSE(Drivers!$C$3,'Automotive Revenue'!J26,'Automotive Revenue'!J33,'Automotive Revenue'!J40) -> 1 | K19: =CHOOSE(Drivers!$C$3,'Automotive Revenue'!K26,'Automotive Revenue'!K33,'Automotive Revenue'!K40) -> 1 | L19: =CHOOSE(Drivers!$C$3,'Automotive Revenue'!L26,'Automotive Revenue'!L33,'Automotive Revenue'!L40) -> 1 | M19: =CHOOSE(Drivers!$C$3,'Automotive Revenue'!M26,'Automotive Revenue'!M33,'Automotive Revenue'!M40) -> 1 | N19: =CHOOSE(Drivers!$C$3,'Automotive Revenue'!N26,'Automotive Revenue'!N33,'Automotive Revenue'!N40) -> 1 | O19: =CHOOSE(Drivers!$C$3,'Automotive Revenue'!O26,'Automotive Revenue'!O33,'Automotive Revenue'!O40) -> 1 | ... Q19: =CHOOSE(Drivers!$C$3,'Automotive Revenue'!Q26,'Automotive Revenue'!Q33,'Automotive Revenue'!Q40) -> 1
B21: Best case
B22: Tesla Model 3 | H22: 1.02 | I22: 1.02 | J22: 1.02 | K22: 1.02 | L22: 1.02 | M22: 1.02 | N22: 1.02 | O22: 1.02 | P22: 1.02 | Q22: 1.02
B23: Tesla Model S and X | H23: 1.02 | I23: 1.02 | J23: 1.02 | K23: 1.02 | L23: 1.02 | M23: 1.02 | N23: 1.02 | O23: 1.02 | P23: 1.02 | Q23: 1.02
B24: Tesla Model Y | H24: 1.02 | I24: 1.02 | J24: 1.02 | K24: 1.02 | L24: 1.02 | M24: 1.02 | N24: 1.02 | O24: 1.02 | P24: 1.02 | Q24: 1.02
B25: Tesla Cybertruck | H25: 1.02 | I25: 1.02 | J25: 1.02 | K25: 1.02 | L25: 1.02 | M25: 1.02 | N25: 1.02 | O25: 1.02 | P25: 1.02 | Q25: 1.02
B26: Tesla Semi | H26: 1.02 | I26: 1.02 | J26: 1.02 | K26: 1.02 | L26: 1.02 | M26: 1.02 | N26: 1.02 | O26: 1.02 | P26: 1.02 | Q26: 1.02
B28: Base case
B29: Tesla Model 3 | H29: 1 | I29: 1 | J29: 1 | K29: 1 | L29: 1 | M29: 1 | N29: 1 | O29: 1 | P29: 1 | Q29: 1
B30: Tesla Model S and X | H30: 1 | I30: 1 | J30: 1 | K30: 1 | L30: 1 | M30: 1 | N30: 1 | O30: 1 | P30: 1 | Q30: 1
B31: Tesla Model Y | H31: 1 | I31: 1 | J31: 1 | K31: 1 | L31: 1 | M31: 1 | N31: 1 | O31: 1 | P31: 1 | Q31: 1
B32: Tesla Cybertruck | H32: 1 | I32: 1 | J32: 1 | K32: 1 | L32: 1 | M32: 1 | N32: 1 | O32: 1 | P32: 1 | Q32: 1
B33: Tesla Semi | H33: 1 | I33: 1 | J33: 1 | K33: 1 | L33: 1 | M33: 1 | N33: 1 | O33: 1 | P33: 1 | Q33: 1
B35: Worst case
B36: Tesla Model 3 | H36: 0.98 | I36: 0.98 | J36: 0.98 | K36: 0.98 | L36: 0.98 | M36: 0.98 | N36: 0.98 | O36: 0.98 | P36: 0.98 | Q36: 0.98
B37: Tesla Model S and X | H37: 0.98 | I37: 0.98 | J37: 0.98 | K37: 0.98 | L37: 0.98 | M37: 0.98 | N37: 0.98 | O37: 0.98 | P37: 0.98 | Q37: 0.98
B38: Tesla Model Y | H38: 0.98 | I38: 0.98 | J38: 0.98 | K38: 0.98 | L38: 0.98 | M38: 0.98 | N38: 0.98 | O38: 0.98 | P38: 0.98 | Q38: 0.98
B39: Tesla Cybertruck | H39: 0.98 | I39: 0.98 | J39: 0.98 | K39: 0.98 | L39: 0.98 | M39: 0.98 | N39: 0.98 | O39: 0.98 | P39: 0.98 | Q39: 0.98
B40: Tesla Semi | H40: 0.98 | I40: 0.98 | J40: 0.98 | K40: 0.98 | L40: 0.98 | M40: 0.98 | N40: 0.98 | O40: 0.98 | P40: 0.98 | Q40: 0.98

Sheet Automotive Gross Margin
B1: GP %
B3: Comparables 2019
B5: Vehicle | C5: Comparable companies | D5: GP % Comp. 1 | E5: GP % Comp. 2 | F5: GP % Comp. 3 | H5: Average
B6: Tesla Model 3 | C6: GM, Ford, Fiat Chrysler | D6: 0.18 | E6: =(((155900-134693)/155900)+((160338-136269)/160338))/2 -> 0.14307182 | F6: =(((108187-93164)/108187)+((110412-95011)/110412))/2 -> 0.13917403 | H6: =C15 -> 0.18 | I6: Historic
B7: Tesla Model S and X | C7: BMW, Mercedes Cars, Volkswagen | D7: 0.19 | E7: =((33067/167362)+(29165/172745))/2 -> 0.18320519 | F7: 0.172 | H7: =C16 -> 0.19 | I7: Historic
B8: Tesla Model Y | C8: GM, Ford, Fiat Chrysler | D8: 0.13 | E8: =(((155900-134693)/155900)+((160338-136269)/160338))/2 -> 0.14307182 | F8: =(((108187-93164)/108187)+((110412-95011)/110412))/2 -> 0.13917403 | H8: =C17 -> 0.2 | I8: Historic
B9: Tesla Pickup | C9: GM, Ford, Fiat Chrysler | D9: 0.14 | E9: =(((155900-134693)/155900)+((160338-136269)/160338))/2 -> 0.14307182 | F9: =F6 -> 0.13917403 | H9: =C18 -> 0.12 | I9: Historic
B10: Tesla Semi | C10: Scania, MAN, Paccar | D10: 0.15 | E10: =E7 -> 0.18320519 | F10: =(((24120-20556)/24120)+((22139-18925)/22139))/2 -> 0.14646743 | H10: =C19 -> 0.15 | I10: Historic
B12: Historical
B14: Vehicle | C14: Historic Average GP%
B15: Tesla Model 3 | C15: 0.18
B16: Tesla Model S and X | C16: 0.19
B17: Tesla Model Y | C17: 0.2
B18: Tesla Pickup | C18: 0.12
B19: Tesla Semi | C19: 0.15

Sheet Automotive Gross Profit
B1: Gross Profit
B3: ($ millions) | C3: Tesla Gross Profit (in mln $)
B4: Vehicle | C4: 2021 Act | D4: 2022 Act | E4: 2023 Act | F4: 2024 Act | G4: 2025 Act | H4: 2026 Fcst | I4: 2027 Fcst | J4: 2028 Fcst | K4: 2029 Fcst | L4: 2030 Fcst | M4: 2031 Fcst | N4: 2032 Fcst | O4: 2033 Fcst | P4: 2034 Fcst | Q4: 2035 Fcst
B5: Tesla Model 3 | C5: n.a. | D5: n.a. | E5: n.a. | F5: n.a. | G5: n.a. | H5: =H13*'Automotive Revenue'!H5 -> 3806.19 | I5: =I13*'Automotive Revenue'!I5 -> 3806.19 | J5: =J13*'Automotive Revenue'!J5 -> 4229.1 | K5: =K13*'Automotive Revenue'!K5 -> 4652.01 | L5: =L13*'Automotive Revenue'!L5 -> 5074.92 | M5: =M13*'Automotive Revenue'!M5 -> 5497.83 | N5: =N13*'Automotive Revenue'!N5 -> 5920.74 | O5: =O13*'Automotive Revenue'!O5 -> 6343.65 | ... Q5: =Q13*'Automotive Revenue'!Q5 -> 7189.47
B6: Tesla Model S and X | C6: n.a. | D6: n.a. | E6: n.a. | F6: n.a. | G6: n.a. | H6: =H14*'Automotive Revenue'!H6 -> 808.64 | I6: =I14*'Automotive Revenue'!I6 -> 404.32 | J6: =J14*'Automotive Revenue'!J6 -> 202.16 | K6: =K14*'Automotive Revenue'!K6 -> 0 | L6: =L14*'Automotive Revenue'!L6 -> 0 | M6: =M14*'Automotive Revenue'!M6 -> 0 | N6: =N14*'Automotive Revenue'!N6 -> 0 | O6: =O14*'Automotive Revenue'!O6 -> 0 | ... Q6: =Q14*'Automotive Revenue'!Q6 -> 0
B7: Tesla Model Y | C7: n.a. | D7: n.a. | E7: n.a. | F7: n.a. | G7: n.a. | H7: =H15*'Automotive Revenue'!H7 -> 11997.6 | I7: =I15*'Automotive Revenue'!I7 -> 13497.3 | J7: =J15*'Automotive Revenue'!J7 -> 14997 | K7: =K15*'Automotive Revenue'!K7 -> 16496.7 | L7: =L15*'Automotive Revenue'!L7 -> 18496.3 | M7: =M15*'Automotive Revenue'!M7 -> 19996 | N7: =N15*'Automotive Revenue'!N7 -> 21495.7 | O7: =O15*'Automotive Revenue'!O7 -> 22995.4 | ... Q7: =Q15*'Automotive Revenue'!Q7 -> 25994.8
B8: Tesla Pickup | C8: 0 | D8: 0 | E8: n.a. | F8: n.a. | G8: n.a. | H8: =H16*'Automotive Revenue'!H8 -> 845.9505 | I8: =I16*'Automotive Revenue'!I8 -> 1353.5208 | J8: =J16*'Automotive Revenue'!J8 -> 2030.2812 | K8: =K16*'Automotive Revenue'!K8 -> 2819.835 | L8: =L16*'Automotive Revenue'!L8 -> 3383.802 | M8: =M16*'Automotive Revenue'!M8 -> 3947.769 | N8: =N16*'Automotive Revenue'!N8 -> 4511.736 | O8: =O16*'Automotive Revenue'!O8 -> 5075.703 | ... Q8: =Q16*'Automotive Revenue'!Q8 -> 6203.637
B9: Tesla Semi | C9: 0 | D9: n.a. | E9: n.a. | F9: n.a. | G9: n.a. | H9: =H17*'Automotive Revenue'!H9 -> 412.5 | I9: =I17*'Automotive Revenue'!I9 -> 825 | J9: =J17*'Automotive Revenue'!J9 -> 1443.75 | K9: =K17*'Automotive Revenue'!K9 -> 2062.5 | L9: =L17*'Automotive Revenue'!L9 -> 3093.75 | M9: =M17*'Automotive Revenue'!M9 -> 4125 | N9: =N17*'Automotive Revenue'!N9 -> 5156.25 | O9: =O17*'Automotive Revenue'!O9 -> 6187.5 | ... Q9: =Q17*'Automotive Revenue'!Q9 -> 8250
B10: Total | C10: =('P&L Input'!C4+'P&L Input'!C8) -> 13839 | D10: =('P&L Input'!D4+'P&L Input'!D8) -> 20354 | E10: =('P&L Input'!E4+'P&L Input'!E8) -> 16030 | F10: =('P&L Input'!F4+'P&L Input'!F8) -> 14197 | G10: =('P&L Input'!G4+'P&L Input'!G8) -> 12361 | H10: =SUM(H5:H9) -> 17870.88 | I10: =SUM(I5:I9) -> 19886.331 | J10: =SUM(J5:J9) -> 22902.291 | K10: =SUM(K5:K9) -> 26031.045 | L10: =SUM(L5:L9) -> 30048.772 | M10: =SUM(M5:M9) -> 33566.599 | N10: =SUM(N5:N9) -> 37084.426 | O10: =SUM(O5:O9) -> 40602.253 | ... Q10: =SUM(Q5:Q9) -> 47637.907
B12: Selected case
B13: Tesla Model 3 | G13: =CHOOSE(Drivers!$C$3,'Automotive Gross Profit'!G20,'Automotive Gross Profit'!G27,'Automotive Gross Profit'!G34) -> 0.18 | H13: =CHOOSE(Drivers!$C$3,'Automotive Gross Profit'!H20,'Automotive Gross Profit'!H27,'Automotive Gross Profit'!H34) -> 0.18 | I13: =CHOOSE(Drivers!$C$3,'Automotive Gross Profit'!I20,'Automotive Gross Profit'!I27,'Automotive Gross Profit'!I34) -> 0.18 | J13: =CHOOSE(Drivers!$C$3,'Automotive Gross Profit'!J20,'Automotive Gross Profit'!J27,'Automotive Gross Profit'!J34) -> 0.18 | K13: =CHOOSE(Drivers!$C$3,'Automotive Gross Profit'!K20,'Automotive Gross Profit'!K27,'Automotive Gross Profit'!K34) -> 0.18 | L13: =CHOOSE(Drivers!$C$3,'Automotive Gross Profit'!L20,'Automotive Gross Profit'!L27,'Automotive Gross Profit'!L34) -> 0.18 | M13: =CHOOSE(Drivers!$C$3,'Automotive Gross Profit'!M20,'Automotive Gross Profit'!M27,'Automotive Gross Profit'!M34) -> 0.18 | N13: =CHOOSE(Drivers!$C$3,'Automotive Gross Profit'!N20,'Automotive Gross Profit'!N27,'Automotive Gross Profit'!N34) -> 0.18 | ... Q13: =CHOOSE(Drivers!$C$3,'Automotive Gross Profit'!Q20,'Automotive Gross Profit'!Q27,'Automotive Gross Profit'!Q34) -> 0.18
B14: Tesla Model S and X | G14: =CHOOSE(Drivers!$C$3,'Automotive Gross Profit'!G21,'Automotive Gross Profit'!G28,'Automotive Gross Profit'!G35) -> 0.19 | H14: =CHOOSE(Drivers!$C$3,'Automotive Gross Profit'!H21,'Automotive Gross Profit'!H28,'Automotive Gross Profit'!H35) -> 0.19 | I14: =CHOOSE(Drivers!$C$3,'Automotive Gross Profit'!I21,'Automotive Gross Profit'!I28,'Automotive Gross Profit'!I35) -> 0.19 | J14: =CHOOSE(Drivers!$C$3,'Automotive Gross Profit'!J21,'Automotive Gross Profit'!J28,'Automotive Gross Profit'!J35) -> 0.19 | K14: =CHOOSE(Drivers!$C$3,'Automotive Gross Profit'!K21,'Automotive Gross Profit'!K28,'Automotive Gross Profit'!K35) -> 0.19 | L14: =CHOOSE(Drivers!$C$3,'Automotive Gross Profit'!L21,'Automotive Gross Profit'!L28,'Automotive Gross Profit'!L35) -> 0.19 | M14: =CHOOSE(Drivers!$C$3,'Automotive Gross Profit'!M21,'Automotive Gross Profit'!M28,'Automotive Gross Profit'!M35) -> 0.19 | N14: =CHOOSE(Drivers!$C$3,'Automotive Gross Profit'!N21,'Automotive Gross Profit'!N28,'Automotive Gross Profit'!N35) -> 0.19 | ... Q14: =CHOOSE(Drivers!$C$3,'Automotive Gross Profit'!Q21,'Automotive Gross Profit'!Q28,'Automotive Gross Profit'!Q35) -> 0.19
B15: Tesla Model Y | G15: =CHOOSE(Drivers!$C$3,'Automotive Gross Profit'!G22,'Automotive Gross Profit'!G29,'Automotive Gross Profit'!G36) -> 0.2 | H15: =CHOOSE(Drivers!$C$3,'Automotive Gross Profit'!H22,'Automotive Gross Profit'!H29,'Automotive Gross Profit'!H36) -> 0.2 | I15: =CHOOSE(Drivers!$C$3,'Automotive Gross Profit'!I22,'Automotive Gross Profit'!I29,'Automotive Gross Profit'!I36) -> 0.2 | J15: =CHOOSE(Drivers!$C$3,'Automotive Gross Profit'!J22,'Automotive Gross Profit'!J29,'Automotive Gross Profit'!J36) -> 0.2 | K15: =CHOOSE(Drivers!$C$3,'Automotive Gross Profit'!K22,'Automotive Gross Profit'!K29,'Automotive Gross Profit'!K36) -> 0.2 | L15: =CHOOSE(Drivers!$C$3,'Automotive Gross Profit'!L22,'Automotive Gross Profit'!L29,'Automotive Gross Profit'!L36) -> 0.2 | M15: =CHOOSE(Drivers!$C$3,'Automotive Gross Profit'!M22,'Automotive Gross Profit'!M29,'Automotive Gross Profit'!M36) -> 0.2 | N15: =CHOOSE(Drivers!$C$3,'Automotive Gross Profit'!N22,'Automotive Gross Profit'!N29,'Automotive Gross Profit'!N36) -> 0.2 | ... Q15: =CHOOSE(Drivers!$C$3,'Automotive Gross Profit'!Q22,'Automotive Gross Profit'!Q29,'Automotive Gross Profit'!Q36) -> 0.2
B16: Tesla Pickup | G16: =CHOOSE(Drivers!$C$3,'Automotive Gross Profit'!G23,'Automotive Gross Profit'!G30,'Automotive Gross Profit'!G37) -> 0.12 | H16: =CHOOSE(Drivers!$C$3,'Automotive Gross Profit'!H23,'Automotive Gross Profit'!H30,'Automotive Gross Profit'!H37) -> 0.12 | I16: =CHOOSE(Drivers!$C$3,'Automotive Gross Profit'!I23,'Automotive Gross Profit'!I30,'Automotive Gross Profit'!I37) -> 0.12 | J16: =CHOOSE(Drivers!$C$3,'Automotive Gross Profit'!J23,'Automotive Gross Profit'!J30,'Automotive Gross Profit'!J37) -> 0.12 | K16: =CHOOSE(Drivers!$C$3,'Automotive Gross Profit'!K23,'Automotive Gross Profit'!K30,'Automotive Gross Profit'!K37) -> 0.12 | L16: =CHOOSE(Drivers!$C$3,'Automotive Gross Profit'!L23,'Automotive Gross Profit'!L30,'Automotive Gross Profit'!L37) -> 0.12 | M16: =CHOOSE(Drivers!$C$3,'Automotive Gross Profit'!M23,'Automotive Gross Profit'!M30,'Automotive Gross Profit'!M37) -> 0.12 | N16: =CHOOSE(Drivers!$C$3,'Automotive Gross Profit'!N23,'Automotive Gross Profit'!N30,'Automotive Gross Profit'!N37) -> 0.12 | ... Q16: =CHOOSE(Drivers!$C$3,'Automotive Gross Profit'!Q23,'Automotive Gross Profit'!Q30,'Automotive Gross Profit'!Q37) -> 0.12
B17: Tesla Semi | G17: =CHOOSE(Drivers!$C$3,'Automotive Gross Profit'!G24,'Automotive Gross Profit'!G31,'Automotive Gross Profit'!G38) -> 0.15 | H17: =CHOOSE(Drivers!$C$3,'Automotive Gross Profit'!H24,'Automotive Gross Profit'!H31,'Automotive Gross Profit'!H38) -> 0.15 | I17: =CHOOSE(Drivers!$C$3,'Automotive Gross Profit'!I24,'Automotive Gross Profit'!I31,'Automotive Gross Profit'!I38) -> 0.15 | J17: =CHOOSE(Drivers!$C$3,'Automotive Gross Profit'!J24,'Automotive Gross Profit'!J31,'Automotive Gross Profit'!J38) -> 0.15 | K17: =CHOOSE(Drivers!$C$3,'Automotive Gross Profit'!K24,'Automotive Gross Profit'!K31,'Automotive Gross Profit'!K38) -> 0.15 | L17: =CHOOSE(Drivers!$C$3,'Automotive Gross Profit'!L24,'Automotive Gross Profit'!L31,'Automotive Gross Profit'!L38) -> 0.15 | M17: =CHOOSE(Drivers!$C$3,'Automotive Gross Profit'!M24,'Automotive Gross Profit'!M31,'Automotive Gross Profit'!M38) -> 0.15 | N17: =CHOOSE(Drivers!$C$3,'Automotive Gross Profit'!N24,'Automotive Gross Profit'!N31,'Automotive Gross Profit'!N38) -> 0.15 | ... Q17: =CHOOSE(Drivers!$C$3,'Automotive Gross Profit'!Q24,'Automotive Gross Profit'!Q31,'Automotive Gross Profit'!Q38) -> 0.15
B19: Best case
B20: Tesla Model 3 | G20: =G27+1.5% -> 0.195 | H20: =H27+1.5% -> 0.195 | I20: =I27+1.5% -> 0.195 | J20: =J27+1.5% -> 0.195 | K20: =K27+1.5% -> 0.195 | L20: =L27+1.5% -> 0.195 | M20: =M27+1.5% -> 0.195 | N20: =N27+1.5% -> 0.195 | ... Q20: =Q27+1.5% -> 0.195
B21: Tesla Model S and X | G21: =G28+1.5% -> 0.205 | H21: =H28+1.5% -> 0.205 | I21: =I28+1.5% -> 0.205 | J21: =J28+1.5% -> 0.205 | K21: =K28+1.5% -> 0.205 | L21: =L28+1.5% -> 0.205 | M21: =M28+1.5% -> 0.205 | N21: =N28+1.5% -> 0.205 | ... Q21: =Q28+1.5% -> 0.205
B22: Tesla Model Y | G22: =G29+1.5% -> 0.215 | H22: =H29+1.5% -> 0.215 | I22: =I29+1.5% -> 0.215 | J22: =J29+1.5% -> 0.215 | K22: =K29+1.5% -> 0.215 | L22: =L29+1.5% -> 0.215 | M22: =M29+1.5% -> 0.215 | N22: =N29+1.5% -> 0.215 | ... Q22: =Q29+1.5% -> 0.215
B23: Tesla Pickup | G23: =G30+1.5% -> 0.135 | H23: =H30+1.5% -> 0.135 | I23: =I30+1.5% -> 0.135 | J23: =J30+1.5% -> 0.135 | K23: =K30+1.5% -> 0.135 | L23: =L30+1.5% -> 0.135 | M23: =M30+1.5% -> 0.135 | N23: =N30+1.5% -> 0.135 | ... Q23: =Q30+1.5% -> 0.135
B24: Tesla Semi | G24: =G31+1.5% -> 0.165 | H24: =H31+1.5% -> 0.165 | I24: =I31+1.5% -> 0.165 | J24: =J31+1.5% -> 0.165 | K24: =K31+1.5% -> 0.165 | L24: =L31+1.5% -> 0.165 | M24: =M31+1.5% -> 0.165 | N24: =N31+1.5% -> 0.165 | ... Q24: =Q31+1.5% -> 0.165
B26: Base case
B27: Tesla Model 3 | G27: ='Automotive Gross Margin'!$H6 -> 0.18 | H27: ='Automotive Gross Margin'!$H6 -> 0.18 | I27: ='Automotive Gross Margin'!$H6 -> 0.18 | J27: ='Automotive Gross Margin'!$H6 -> 0.18 | K27: ='Automotive Gross Margin'!$H6 -> 0.18 | L27: ='Automotive Gross Margin'!$H6 -> 0.18 | M27: ='Automotive Gross Margin'!$H6 -> 0.18 | N27: ='Automotive Gross Margin'!$H6 -> 0.18 | ... Q27: ='Automotive Gross Margin'!$H6 -> 0.18
B28: Tesla Model S and X | G28: ='Automotive Gross Margin'!$H7 -> 0.19 | H28: ='Automotive Gross Margin'!$H7 -> 0.19 | I28: ='Automotive Gross Margin'!$H7 -> 0.19 | J28: ='Automotive Gross Margin'!$H7 -> 0.19 | K28: ='Automotive Gross Margin'!$H7 -> 0.19 | L28: ='Automotive Gross Margin'!$H7 -> 0.19 | M28: ='Automotive Gross Margin'!$H7 -> 0.19 | N28: ='Automotive Gross Margin'!$H7 -> 0.19 | ... Q28: ='Automotive Gross Margin'!$H7 -> 0.19
B29: Tesla Model Y | G29: ='Automotive Gross Margin'!$H8 -> 0.2 | H29: ='Automotive Gross Margin'!$H8 -> 0.2 | I29: ='Automotive Gross Margin'!$H8 -> 0.2 | J29: ='Automotive Gross Margin'!$H8 -> 0.2 | K29: ='Automotive Gross Margin'!$H8 -> 0.2 | L29: ='Automotive Gross Margin'!$H8 -> 0.2 | M29: ='Automotive Gross Margin'!$H8 -> 0.2 | N29: ='Automotive Gross Margin'!$H8 -> 0.2 | ... Q29: ='Automotive Gross Margin'!$H8 -> 0.2
B30: Tesla Pickup | G30: ='Automotive Gross Margin'!$H9 -> 0.12 | H30: ='Automotive Gross Margin'!$H9 -> 0.12 | I30: ='Automotive Gross Margin'!$H9 -> 0.12 | J30: ='Automotive Gross Margin'!$H9 -> 0.12 | K30: ='Automotive Gross Margin'!$H9 -> 0.12 | L30: ='Automotive Gross Margin'!$H9 -> 0.12 | M30: ='Automotive Gross Margin'!$H9 -> 0.12 | N30: ='Automotive Gross Margin'!$H9 -> 0.12 | ... Q30: ='Automotive Gross Margin'!$H9 -> 0.12
B31: Tesla Semi | G31: ='Automotive Gross Margin'!$H10 -> 0.15 | H31: ='Automotive Gross Margin'!$H10 -> 0.15 | I31: ='Automotive Gross Margin'!$H10 -> 0.15 | J31: ='Automotive Gross Margin'!$H10 -> 0.15 | K31: ='Automotive Gross Margin'!$H10 -> 0.15 | L31: ='Automotive Gross Margin'!$H10 -> 0.15 | M31: ='Automotive Gross Margin'!$H10 -> 0.15 | N31: ='Automotive Gross Margin'!$H10 -> 0.15 | ... Q31: ='Automotive Gross Margin'!$H10 -> 0.15
B33: Worst case
B34: Tesla Model 3 | G34: =G27-1.5% -> 0.165 | H34: =H27-1.5% -> 0.165 | I34: =I27-1.5% -> 0.165 | J34: =J27-1.5% -> 0.165 | K34: =K27-1.5% -> 0.165 | L34: =L27-1.5% -> 0.165 | M34: =M27-1.5% -> 0.165 | N34: =N27-1.5% -> 0.165 | ... Q34: =Q27-1.5% -> 0.165
B35: Tesla Model S and X | G35: =G28-1.5% -> 0.175 | H35: =H28-1.5% -> 0.175 | I35: =I28-1.5% -> 0.175 | J35: =J28-1.5% -> 0.175 | K35: =K28-1.5% -> 0.175 | L35: =L28-1.5% -> 0.175 | M35: =M28-1.5% -> 0.175 | N35: =N28-1.5% -> 0.175 | ... Q35: =Q28-1.5% -> 0.175
B36: Tesla Model Y | G36: =G29-1.5% -> 0.185 | H36: =H29-1.5% -> 0.185 | I36: =I29-1.5% -> 0.185 | J36: =J29-1.5% -> 0.185 | K36: =K29-1.5% -> 0.185 | L36: =L29-1.5% -> 0.185 | M36: =M29-1.5% -> 0.185 | N36: =N29-1.5% -> 0.185 | ... Q36: =Q29-1.5% -> 0.185
B37: Tesla Pickup | G37: =G30-1.5% -> 0.105 | H37: =H30-1.5% -> 0.105 | I37: =I30-1.5% -> 0.105 | J37: =J30-1.5% -> 0.105 | K37: =K30-1.5% -> 0.105 | L37: =L30-1.5% -> 0.105 | M37: =M30-1.5% -> 0.105 | N37: =N30-1.5% -> 0.105 | ... Q37: =Q30-1.5% -> 0.105
B38: Tesla Semi | G38: =G31-1.5% -> 0.135 | H38: =H31-1.5% -> 0.135 | I38: =I31-1.5% -> 0.135 | J38: =J31-1.5% -> 0.135 | K38: =K31-1.5% -> 0.135 | L38: =L31-1.5% -> 0.135 | M38: =M31-1.5% -> 0.135 | N38: =N31-1.5% -> 0.135 | ... Q38: =Q31-1.5% -> 0.135

Sheet Cost of sales automotive
B1: Cost of sales automotive
B3: ($ millions) | C3: Tesla Cost of sales (in mln $)
B4: Vehicle | C4: 2021 Act | D4: 2022 Act | E4: 2023 Act | F4: 2024 Act | G4: 2025 Act | H4: 2026 Fcst | I4: 2027 Fcst | J4: 2028 Fcst | K4: 2029 Fcst | L4: 2030 Fcst | M4: 2031 Fcst | N4: 2032 Fcst | O4: 2033 Fcst | P4: 2034 Fcst | Q4: 2035 Fcst
B5: Tesla Model 3 | C5: n.a. | D5: n.a. | E5: n.a. | F5: n.a. | G5: n.a. | H5: =-('Automotive Revenue'!H5-'Automotive Gross Profit'!H5) -> -17339.31 | I5: =-('Automotive Revenue'!I5-'Automotive Gross Profit'!I5) -> -17339.31 | J5: =-('Automotive Revenue'!J5-'Automotive Gross Profit'!J5) -> -19265.9 | K5: =-('Automotive Revenue'!K5-'Automotive Gross Profit'!K5) -> -21192.49 | L5: =-('Automotive Revenue'!L5-'Automotive Gross Profit'!L5) -> -23119.08 | M5: =-('Automotive Revenue'!M5-'Automotive Gross Profit'!M5) -> -25045.67 | N5: =-('Automotive Revenue'!N5-'Automotive Gross Profit'!N5) -> -26972.26 | O5: =-('Automotive Revenue'!O5-'Automotive Gross Profit'!O5) -> -28898.85 | ... Q5: =-('Automotive Revenue'!Q5-'Automotive Gross Profit'!Q5) -> -32752.03
B6: Tesla Model S and X | C6: n.a. | D6: n.a. | E6: n.a. | F6: n.a. | G6: n.a. | H6: =-('Automotive Revenue'!H6-'Automotive Gross Profit'!H6) -> -3447.36 | I6: =-('Automotive Revenue'!I6-'Automotive Gross Profit'!I6) -> -1723.68 | J6: =-('Automotive Revenue'!J6-'Automotive Gross Profit'!J6) -> -861.84 | K6: =-('Automotive Revenue'!K6-'Automotive Gross Profit'!K6) -> 0 | L6: =-('Automotive Revenue'!L6-'Automotive Gross Profit'!L6) -> 0 | M6: =-('Automotive Revenue'!M6-'Automotive Gross Profit'!M6) -> 0 | N6: =-('Automotive Revenue'!N6-'Automotive Gross Profit'!N6) -> 0 | O6: =-('Automotive Revenue'!O6-'Automotive Gross Profit'!O6) -> 0 | ... Q6: =-('Automotive Revenue'!Q6-'Automotive Gross Profit'!Q6) -> 0
B7: Tesla Model Y | C7: n.a. | D7: n.a. | E7: n.a. | F7: n.a. | G7: n.a. | H7: =-('Automotive Revenue'!H7-'Automotive Gross Profit'!H7) -> -47990.4 | I7: =-('Automotive Revenue'!I7-'Automotive Gross Profit'!I7) -> -53989.2 | J7: =-('Automotive Revenue'!J7-'Automotive Gross Profit'!J7) -> -59988 | K7: =-('Automotive Revenue'!K7-'Automotive Gross Profit'!K7) -> -65986.8 | L7: =-('Automotive Revenue'!L7-'Automotive Gross Profit'!L7) -> -73985.2 | M7: =-('Automotive Revenue'!M7-'Automotive Gross Profit'!M7) -> -79984 | N7: =-('Automotive Revenue'!N7-'Automotive Gross Profit'!N7) -> -85982.8 | O7: =-('Automotive Revenue'!O7-'Automotive Gross Profit'!O7) -> -91981.6 | ... Q7: =-('Automotive Revenue'!Q7-'Automotive Gross Profit'!Q7) -> -103979.2
B8: Tesla Pickup | C8: 0 | D8: 0 | E8: n.a. | F8: n.a. | G8: n.a. | H8: =-('Automotive Revenue'!H8-'Automotive Gross Profit'!H8) -> -6203.637 | I8: =-('Automotive Revenue'!I8-'Automotive Gross Profit'!I8) -> -9925.8192 | J8: =-('Automotive Revenue'!J8-'Automotive Gross Profit'!J8) -> -14888.729 | K8: =-('Automotive Revenue'!K8-'Automotive Gross Profit'!K8) -> -20678.79 | L8: =-('Automotive Revenue'!L8-'Automotive Gross Profit'!L8) -> -24814.548 | M8: =-('Automotive Revenue'!M8-'Automotive Gross Profit'!M8) -> -28950.306 | N8: =-('Automotive Revenue'!N8-'Automotive Gross Profit'!N8) -> -33086.064 | O8: =-('Automotive Revenue'!O8-'Automotive Gross Profit'!O8) -> -37221.822 | ... Q8: =-('Automotive Revenue'!Q8-'Automotive Gross Profit'!Q8) -> -45493.338
B9: Tesla Semi | C9: 0 | D9: n.a. | E9: n.a. | F9: n.a. | G9: n.a. | H9: =-('Automotive Revenue'!H9-'Automotive Gross Profit'!H9) -> -2337.5 | I9: =-('Automotive Revenue'!I9-'Automotive Gross Profit'!I9) -> -4675 | J9: =-('Automotive Revenue'!J9-'Automotive Gross Profit'!J9) -> -8181.25 | K9: =-('Automotive Revenue'!K9-'Automotive Gross Profit'!K9) -> -11687.5 | L9: =-('Automotive Revenue'!L9-'Automotive Gross Profit'!L9) -> -17531.25 | M9: =-('Automotive Revenue'!M9-'Automotive Gross Profit'!M9) -> -23375 | N9: =-('Automotive Revenue'!N9-'Automotive Gross Profit'!N9) -> -29218.75 | O9: =-('Automotive Revenue'!O9-'Automotive Gross Profit'!O9) -> -35062.5 | ... Q9: =-('Automotive Revenue'!Q9-'Automotive Gross Profit'!Q9) -> -46750
B10: Total | C10: =-('Automotive Revenue'!C10-'Automotive Gross Profit'!C10) -> -33393 | D10: =-('Automotive Revenue'!D10-'Automotive Gross Profit'!D10) -> -51108 | E10: =-('Automotive Revenue'!E10-'Automotive Gross Profit'!E10) -> -66389 | F10: =-('Automotive Revenue'!F10-'Automotive Gross Profit'!F10) -> -62873 | G10: =-('Automotive Revenue'!G10-'Automotive Gross Profit'!G10) -> -57165 | H10: =SUM(H5:H9) -> -77318.207 | I10: =SUM(I5:I9) -> -87653.009 | J10: =SUM(J5:J9) -> -103185.72 | K10: =SUM(K5:K9) -> -119545.58 | L10: =SUM(L5:L9) -> -139450.08 | M10: =SUM(M5:M9) -> -157354.98 | N10: =SUM(N5:N9) -> -175259.87 | O10: =SUM(O5:O9) -> -193164.77 | ... Q10: =SUM(Q5:Q9) -> -228974.57

Sheet Automotive Revenue and GP 
B1: Revenue and Gross Profit automotive
B2: ($ millions)
B3: Vehicle | C3: 2021 Act | D3: 2022 Act | E3: 2023 Act | F3: 2024 Act | G3: 2025 Act | H3: 2026 Fcst | I3: 2027 Fcst | J3: 2028 Fcst | K3: 2029 Fcst | L3: 2030 Fcst | M3: 2031 Fcst | N3: 2032 Fcst | O3: 2033 Fcst | P3: 2034 Fcst | Q3: 2035 Fcst
B4: Revenue automotive | C4: ='Automotive Revenue'!C10 -> 47232 | D4: ='Automotive Revenue'!D10 -> 71462 | E4: ='Automotive Revenue'!E10 -> 82419 | F4: ='Automotive Revenue'!F10 -> 77070 | G4: ='Automotive Revenue'!G10 -> 69526 | H4: ='Automotive Revenue'!H10 -> 95189.087 | I4: ='Automotive Revenue'!I10 -> 107539.34 | J4: ='Automotive Revenue'!J10 -> 126088.01 | ... Q4: ='Automotive Revenue'!Q10 -> 276612.47
B5: Gross Profit automotive | C5: ='Automotive Gross Profit'!C10 -> 13839 | D5: ='Automotive Gross Profit'!D10 -> 20354 | E5: ='Automotive Gross Profit'!E10 -> 16030 | F5: ='Automotive Gross Profit'!F10 -> 14197 | G5: ='Automotive Gross Profit'!G10 -> 12361 | H5: ='Automotive Gross Profit'!H10 -> 17870.88 | I5: ='Automotive Gross Profit'!I10 -> 19886.331 | J5: ='Automotive Gross Profit'!J10 -> 22902.291 | ... Q5: ='Automotive Gross Profit'!Q10 -> 47637.907
B6: GP% | C6: =C5/C4 -> 0.29300051 | D6: =D5/D4 -> 0.2848227 | E6: =E5/E4 -> 0.19449399 | F6: =F5/F4 -> 0.18420916 | G6: =G5/G4 -> 0.1777896 | H6: =H5/H4 -> 0.18774085 | I6: =I5/I4 -> 0.18492145 | J6: =J5/J4 -> 0.18163734 | ... Q6: =Q5/Q4 -> 0.17221894

Sheet Energy & Other
B14: Energy & Other

Sheet Revenue Energy & Other
B1: Revenue Energy & Other
C3: Tesla Revenue Energy & Other (in mln $)
B4: ($ millions) | C4: 2021 Act | D4: 2022 Act | E4: 2023 Act | F4: 2024 Act | G4: 2025 Act | H4: 2026 Fcst | I4: 2027 Fcst | J4: 2028 Fcst | K4: 2029 Fcst | L4: 2030 Fcst | M4: 2031 Fcst | N4: 2032 Fcst | O4: 2033 Fcst | P4: 2034 Fcst | Q4: 2035 Fcst
B5: Energy generation and storage | C5: ='P&L Input'!C5 -> 2789 | D5: ='P&L Input'!D5 -> 3909 | E5: ='P&L Input'!E5 -> 6035 | F5: ='P&L Input'!F5 -> 10086 | G5: ='P&L Input'!G5 -> 12771 | H5: n.a. | I5: n.a. | J5: n.a. | K5: n.a. | L5: n.a. | M5: n.a. | N5: n.a. | O5: n.a. | P5: n.a. | Q5: n.a.
B6: Services and other | C6: ='P&L Input'!C6 -> 3802 | D6: ='P&L Input'!D6 -> 6091 | E6: ='P&L Input'!E6 -> 8319 | F6: ='P&L Input'!F6 -> 10534 | G6: ='P&L Input'!G6 -> 12530 | H6: n.a. | I6: n.a. | J6: n.a. | K6: n.a. | L6: n.a. | M6: n.a. | N6: n.a. | O6: n.a. | P6: n.a. | Q6: n.a.
B7: Total Energy and Other | C7: =SUM(C5:C6) -> 6591 | D7: =SUM(D5:D6) -> 10000 | E7: =SUM(E5:E6) -> 14354 | F7: =SUM(F5:F6) -> 20620 | G7: =SUM(G5:G6) -> 25301 | H7: =G7*(1+H10) -> 29855.18 | I7: =H7*(1+I10) -> 33437.802 | J7: =I7*(1+J10) -> 36112.826 | K7: =J7*(1+K10) -> 38279.595 | L7: =K7*(1+L10) -> 40576.371 | M7: =L7*(1+M10) -> 43010.953 | N7: =M7*(1+N10) -> 45591.61 | O7: =N7*(1+O10) -> 48327.107 | ... Q7: =P7*(1+Q10) -> 54300.338
B9: Selected case
B10: Total Energy and Other | H10: =CHOOSE(Drivers!$C$3,'Revenue Energy & Other'!H14,'Revenue Energy & Other'!H17,'Revenue Energy & Other'!H20) -> 0.18 | I10: =CHOOSE(Drivers!$C$3,'Revenue Energy & Other'!I14,'Revenue Energy & Other'!I17,'Revenue Energy & Other'!I20) -> 0.12 | J10: =CHOOSE(Drivers!$C$3,'Revenue Energy & Other'!J14,'Revenue Energy & Other'!J17,'Revenue Energy & Other'!J20) -> 0.08 | K10: =CHOOSE(Drivers!$C$3,'Revenue Energy & Other'!K14,'Revenue Energy & Other'!K17,'Revenue Energy & Other'!K20) -> 0.06 | L10: =CHOOSE(Drivers!$C$3,'Revenue Energy & Other'!L14,'Revenue Energy & Other'!L17,'Revenue Energy & Other'!L20) -> 0.06 | M10: =CHOOSE(Drivers!$C$3,'Revenue Energy & Other'!M14,'Revenue Energy & Other'!M17,'Revenue Energy & Other'!M20) -> 0.06 | N10: =CHOOSE(Drivers!$C$3,'Revenue Energy & Other'!N14,'Revenue Energy & Other'!N17,'Revenue Energy & Other'!N20) -> 0.06 | O10: =CHOOSE(Drivers!$C$3,'Revenue Energy & Other'!O14,'Revenue Energy & Other'!O17,'Revenue Energy & Other'!O20) -> 0.06 | ... Q10: =CHOOSE(Drivers!$C$3,'Revenue Energy & Other'!Q14,'Revenue Energy & Other'!Q17,'Revenue Energy & Other'!Q20) -> 0.06
B12: Y-o-Y %
B13: Best case
B14: Total Energy and Other | H14: =H17+Drivers!$C$13 -> 0.211 | I14: =I17+Drivers!$C$13 -> 0.151 | J14: =J17+Drivers!$C$13 -> 0.111 | K14: =K17+Drivers!$C$13 -> 0.091 | L14: =L17+Drivers!$C$13 -> 0.091 | M14: =M17+Drivers!$C$13 -> 0.091 | N14: =N17+Drivers!$C$13 -> 0.091 | O14: =O17+Drivers!$C$13 -> 0.091 | ... Q14: =Q17+Drivers!$C$13 -> 0.091
B16: Base case
B17: Total Energy and Other | D17: =D7/C7-1 -> 0.51722045 | E17: =E7/D7-1 -> 0.4354 | F17: =F7/E7-1 -> 0.43653337 | G17: =G7/F7-1 -> 0.22701261 | H17: 0.18 | I17: 0.12 | J17: 0.08 | K17: 0.06 | L17: 0.06 | M17: 0.06 | N17: 0.06 | O17: 0.06 | P17: 0.06 | Q17: 0.06
B19: Worst case
B20: Total Energy and Other | H20: =H17-Drivers!$C$13 -> 0.149 | I20: =I17-Drivers!$C$13 -> 0.089 | J20: =J17-Drivers!$C$13 -> 0.049 | K20: =K17-Drivers!$C$13 -> 0.029 | L20: =L17-Drivers!$C$13 -> 0.029 | M20: =M17-Drivers!$C$13 -> 0.029 | N20: =N17-Drivers!$C$13 -> 0.029 | O20: =O17-Drivers!$C$13 -> 0.029 | ... Q20: =Q17-Drivers!$C$13 -> 0.029

Sheet Gross Profit Energy & Other
B1: Gross Profit Energy & Other
C3: Tesla GP% Energy and Other (in mln $)
B4: ($ millions) | C4: 2021 Act | D4: 2022 Act | E4: 2023 Act | F4: 2024 Act | G4: 2025 Act | H4: 2026 Fcst | I4: 2027 Fcst | J4: 2028 Fcst | K4: 2029 Fcst | L4: 2030 Fcst | M4: 2031 Fcst | N4: 2032 Fcst | O4: 2033 Fcst | P4: 2034 Fcst | Q4: 2035 Fcst
B5: Energy generation and storage | C5: =('P&L Input'!C5+'P&L Input'!C9) -> -129 | D5: =('P&L Input'!D5+'P&L Input'!D9) -> 288 | E5: =('P&L Input'!E5+'P&L Input'!E9) -> 1141 | F5: =('P&L Input'!F5+'P&L Input'!F9) -> 2640 | G5: =('P&L Input'!G5+'P&L Input'!G9) -> 3802 | H5: n.a. | I5: n.a. | J5: n.a. | K5: n.a. | L5: n.a. | M5: n.a. | N5: n.a. | O5: n.a. | P5: n.a. | Q5: n.a.
B6: Services and other | C6: =('P&L Input'!C6+'P&L Input'!C10) -> -104 | D6: =('P&L Input'!D6+'P&L Input'!D10) -> 211 | E6: =('P&L Input'!E6+'P&L Input'!E10) -> 489 | F6: =('P&L Input'!F6+'P&L Input'!F10) -> 613 | G6: =('P&L Input'!G6+'P&L Input'!G10) -> 931 | H6: n.a. | I6: n.a. | J6: n.a. | K6: n.a. | L6: n.a. | M6: n.a. | N6: n.a. | O6: n.a. | P6: n.a. | Q6: n.a.
B7: Total Energy and Other | C7: =SUM(C5:C6) -> -233 | D7: =SUM(D5:D6) -> 499 | E7: =SUM(E5:E6) -> 1630 | F7: =SUM(F5:F6) -> 3253 | G7: =SUM(G5:G6) -> 4733 | H7: =H11*'Revenue Energy & Other'!H7 -> 3390.2705 | I7: =I11*'Revenue Energy & Other'!I7 -> 3797.103 | J7: =J11*'Revenue Energy & Other'!J7 -> 4100.8713 | K7: =K11*'Revenue Energy & Other'!K7 -> 4346.9235 | L7: =L11*'Revenue Energy & Other'!L7 -> 4607.7389 | M7: =M11*'Revenue Energy & Other'!M7 -> 4884.2033 | N7: =N11*'Revenue Energy & Other'!N7 -> 5177.2555 | O7: =O11*'Revenue Energy & Other'!O7 -> 5487.8908 | ... Q7: =Q11*'Revenue Energy & Other'!Q7 -> 6166.1941
B10: Selected case
B11: Total Energy and Other | H11: =CHOOSE(Drivers!$C$3,'Gross Profit Energy & Other'!H14,'Gross Profit Energy & Other'!H17,'Gross Profit Energy & Other'!H21) -> 0.1135572 | I11: =CHOOSE(Drivers!$C$3,'Gross Profit Energy & Other'!I14,'Gross Profit Energy & Other'!I17,'Gross Profit Energy & Other'!I21) -> 0.1135572 | J11: =CHOOSE(Drivers!$C$3,'Gross Profit Energy & Other'!J14,'Gross Profit Energy & Other'!J17,'Gross Profit Energy & Other'!J21) -> 0.1135572 | K11: =CHOOSE(Drivers!$C$3,'Gross Profit Energy & Other'!K14,'Gross Profit Energy & Other'!K17,'Gross Profit Energy & Other'!K21) -> 0.1135572 | L11: =CHOOSE(Drivers!$C$3,'Gross Profit Energy & Other'!L14,'Gross Profit Energy & Other'!L17,'Gross Profit Energy & Other'!L21) -> 0.1135572 | M11: =CHOOSE(Drivers!$C$3,'Gross Profit Energy & Other'!M14,'Gross Profit Energy & Other'!M17,'Gross Profit Energy & Other'!M21) -> 0.1135572 | N11: =CHOOSE(Drivers!$C$3,'Gross Profit Energy & Other'!N14,'Gross Profit Energy & Other'!N17,'Gross Profit Energy & Other'!N21) -> 0.1135572 | O11: =CHOOSE(Drivers!$C$3,'Gross Profit Energy & Other'!O14,'Gross Profit Energy & Other'!O17,'Gross Profit Energy & Other'!O21) -> 0.1135572 | ... Q11: =CHOOSE(Drivers!$C$3,'Gross Profit Energy & Other'!Q14,'Gross Profit Energy & Other'!Q17,'Gross Profit Energy & Other'!Q21) -> 0.1135572
B13: GP%
B14: Best case | H14: =H17+Drivers!$C$13 -> 0.1445572 | I14: =I17+Drivers!$C$13 -> 0.1445572 | J14: =J17+Drivers!$C$13 -> 0.1445572 | K14: =K17+Drivers!$C$13 -> 0.1445572 | L14: =L17+Drivers!$C$13 -> 0.1445572 | M14: =M17+Drivers!$C$13 -> 0.1445572 | N14: =N17+Drivers!$C$13 -> 0.1445572 | O14: =O17+Drivers!$C$13 -> 0.1445572 | ... Q14: =Q17+Drivers!$C$13 -> 0.1445572
B15: Total Energy and Other
B17: Base case(Historical Median) | C17: =C7/'Revenue Energy & Other'!C7 -> -0.035351237 | D17: =D7/'Revenue Energy & Other'!D7 -> 0.0499 | E17: =E7/'Revenue Energy & Other'!E7 -> 0.1135572 | F17: =F7/'Revenue Energy & Other'!F7 -> 0.15775946 | G17: =G7/'Revenue Energy & Other'!G7 -> 0.1870677 | H17: =MEDIAN(C17:G17) -> 0.1135572 | I17: =$H$17 -> 0.1135572 | J17: =$H$17 -> 0.1135572 | K17: =$H$17 -> 0.1135572 | L17: =$H$17 -> 0.1135572 | M17: =$H$17 -> 0.1135572 | N17: =$H$17 -> 0.1135572 | O17: =$H$17 -> 0.1135572 | P17: =$H$17 -> 0.1135572 | Q17: =$H$17 -> 0.1135572
B18: Total Energy and Other
B20: Worst case
B21: Total Energy and Other | H21: =H17-Drivers!$C$13 -> 0.082557197 | I21: =I17-Drivers!$C$13 -> 0.082557197 | J21: =J17-Drivers!$C$13 -> 0.082557197 | K21: =K17-Drivers!$C$13 -> 0.082557197 | L21: =L17-Drivers!$C$13 -> 0.082557197 | M21: =M17-Drivers!$C$13 -> 0.082557197 | N21: =N17-Drivers!$C$13 -> 0.082557197 | O21: =O17-Drivers!$C$13 -> 0.082557197 | ... Q21: =Q17-Drivers!$C$13 -> 0.082557197

Sheet Cost of sales Energy & Other
B1: Cost of sales Energy & Other
C3: Tesla Cost of sales Energy & Other (in mln $)
B4: ($ millions) | C4: 2021 Act | D4: 2022 Act | E4: 2023 Act | F4: 2024 Act | G4: 2025 Act | H4: 2026 Fcst | I4: 2027 Fcst | J4: 2028 Fcst | K4: 2029 Fcst | L4: 2030 Fcst | M4: 2031 Fcst | N4: 2032 Fcst | O4: 2033 Fcst | P4: 2034 Fcst | Q4: 2035 Fcst
B5: Energy generation and storage | C5: =-('Revenue Energy & Other'!C5-'Gross Profit Energy & Other'!C5) -> -2918 | D5: =-('Revenue Energy & Other'!D5-'Gross Profit Energy & Other'!D5) -> -3621 | E5: =-('Revenue Energy & Other'!E5-'Gross Profit Energy & Other'!E5) -> -4894 | F5: =-('Revenue Energy & Other'!F5-'Gross Profit Energy & Other'!F5) -> -7446 | G5: =-('Revenue Energy & Other'!G5-'Gross Profit Energy & Other'!G5) -> -8969 | H5: n.a. | I5: n.a. | J5: n.a. | K5: n.a. | L5: n.a. | M5: n.a. | N5: n.a. | O5: n.a. | P5: n.a. | Q5: n.a.
B6: Services and other | C6: =-('Revenue Energy & Other'!C6-'Gross Profit Energy & Other'!C6) -> -3906 | D6: =-('Revenue Energy & Other'!D6-'Gross Profit Energy & Other'!D6) -> -5880 | E6: =-('Revenue Energy & Other'!E6-'Gross Profit Energy & Other'!E6) -> -7830 | F6: =-('Revenue Energy & Other'!F6-'Gross Profit Energy & Other'!F6) -> -9921 | G6: =-('Revenue Energy & Other'!G6-'Gross Profit Energy & Other'!G6) -> -11599 | H6: n.a. | I6: n.a. | J6: n.a. | K6: n.a. | L6: n.a. | M6: n.a. | N6: n.a. | O6: n.a. | P6: n.a. | Q6: n.a.
B7: Total Energy and Other | C7: =SUM(C5:C6) -> -6824 | D7: =SUM(D5:D6) -> -9501 | E7: =SUM(E5:E6) -> -12724 | F7: =SUM(F5:F6) -> -17367 | G7: =SUM(G5:G6) -> -20568 | H7: =-('Revenue Energy & Other'!H7-'Gross Profit Energy & Other'!H7) -> -26464.909 | I7: =-('Revenue Energy & Other'!I7-'Gross Profit Energy & Other'!I7) -> -29640.699 | J7: =-('Revenue Energy & Other'!J7-'Gross Profit Energy & Other'!J7) -> -32011.954 | K7: =-('Revenue Energy & Other'!K7-'Gross Profit Energy & Other'!K7) -> -33932.672 | L7: =-('Revenue Energy & Other'!L7-'Gross Profit Energy & Other'!L7) -> -35968.632 | M7: =-('Revenue Energy & Other'!M7-'Gross Profit Energy & Other'!M7) -> -38126.75 | N7: =-('Revenue Energy & Other'!N7-'Gross Profit Energy & Other'!N7) -> -40414.355 | O7: =-('Revenue Energy & Other'!O7-'Gross Profit Energy & Other'!O7) -> -42839.216 | ... Q7: =-('Revenue Energy & Other'!Q7-'Gross Profit Energy & Other'!Q7) -> -48134.143

Sheet Operating expenses
B14: Operating expenses

Sheet Opex comparables
B1: Opex comparables
B3: Comparables - 2019
B6: Company | C6: Average | D6: Adj. Average
B7: Tesla | C7: 0.12 | D7: =C7 -> 0.12
B8: GM | C8: 0.152 | D8: =C8 -> 0.152
B9: Ford | C9: 0.13234766 | D9: =C9 -> 0.13234766
B10: Fiat Chrysler | C10: 0.093051845
B11: BMW | C11: 0.099485177 | D11: =C11 -> 0.099485177
B12: Volkswagen | C12: 0.11 | D12: =C12 -> 0.11
B13: Jaguar | C13: 0.37065334
B14: Porsche | C14: 0.30660065
B15: Ferrari | C15: 0.2767445
B16: Scania | C16: 0.15 | D16: =C16 -> 0.15
B17: MAN | C17: 0.15 | D17: =C17 -> 0.15
B18: Paccar | C18: 0.03685738
B19: Average | C19: =AVERAGE(C7:C18) -> 0.16647838 | D19: =AVERAGE(D7:D18) -> 0.13054755

Sheet Opex
B1: Opex
C3: Tesla Opex (in mln $)
B4: ($ millions) | C4: 2021 Act | D4: 2022 Act | E4: 2023 Act | F4: 2024 Act | G4: 2025 Act | H4: 2026 Fcst | I4: 2027 Fcst | J4: 2028 Fcst | K4: 2029 Fcst | L4: 2030 Fcst | M4: 2031 Fcst | N4: 2032 Fcst | O4: 2033 Fcst | P4: 2034 Fcst | Q4: 2035 Fcst
B5: Revenues | C5: ='Revenue Energy & Other'!C7+'Automotive Revenue'!C10 -> 53823 | D5: ='Revenue Energy & Other'!D7+'Automotive Revenue'!D10 -> 81462 | E5: ='Revenue Energy & Other'!E7+'Automotive Revenue'!E10 -> 96773 | F5: ='Revenue Energy & Other'!F7+'Automotive Revenue'!F10 -> 97690 | G5: ='Revenue Energy & Other'!G7+'Automotive Revenue'!G10 -> 94827 | H5: ='Revenue Energy & Other'!H7+'Automotive Revenue'!H10 -> 125044.27 | I5: ='Revenue Energy & Other'!I7+'Automotive Revenue'!I10 -> 140977.14 | J5: ='Revenue Energy & Other'!J7+'Automotive Revenue'!J10 -> 162200.84 | ... Q5: ='Revenue Energy & Other'!Q7+'Automotive Revenue'!Q10 -> 330912.81
B6: Opex as a % of revenues | C6: =C7/C5 -> -0.13159802 | D6: =D7/D5 -> -0.088347941 | E6: =E7/E5 -> -0.090614118 | F6: =F7/F5 -> -0.10619306 | G6: =G7/G5 -> -0.13433938 | H6: =H10 -> -0.13054755 | I6: =I10 -> -0.13054755 | J6: =J10 -> -0.13054755 | K6: =K10 -> -0.13054755 | L6: =L10 -> -0.13054755 | M6: =M10 -> -0.13054755 | N6: =N10 -> -0.13054755 | O6: =O10 -> -0.13054755 | ... Q6: =Q10 -> -0.13054755
B7: Opex | C7: =('P&L Input'!C12+'P&L Input'!C13+'P&L Input'!C14) -> -7083 | D7: =('P&L Input'!D12+'P&L Input'!D13+'P&L Input'!D14) -> -7197 | E7: =('P&L Input'!E12+'P&L Input'!E13+'P&L Input'!E14) -> -8769 | F7: =('P&L Input'!F12+'P&L Input'!F13+'P&L Input'!F14) -> -10374 | G7: =('P&L Input'!G12+'P&L Input'!G13+'P&L Input'!G14) -> -12739 | H7: =H5*H6 -> -16324.223 | I7: =I5*I6 -> -18404.22 | J7: =J5*J6 -> -21174.921 | K7: =K5*K6 -> -24001.979 | L7: =L5*L6 -> -27424.805 | M7: =M5*M6 -> -30539.318 | N7: =N5*N6 -> -33672.901 | O7: =O5*O6 -> -36826.697 | ... Q7: =Q5*Q6 -> -43199.856
B9: Selected case
B10: Opex as a % of revenue | H10: =CHOOSE(Drivers!$C$3,Opex!H14,Opex!H17,Opex!H20) -> -0.13054755 | I10: =CHOOSE(Drivers!$C$3,Opex!I14,Opex!I17,Opex!I20) -> -0.13054755 | J10: =CHOOSE(Drivers!$C$3,Opex!J14,Opex!J17,Opex!J20) -> -0.13054755 | K10: =CHOOSE(Drivers!$C$3,Opex!K14,Opex!K17,Opex!K20) -> -0.13054755 | L10: =CHOOSE(Drivers!$C$3,Opex!L14,Opex!L17,Opex!L20) -> -0.13054755 | M10: =CHOOSE(Drivers!$C$3,Opex!M14,Opex!M17,Opex!M20) -> -0.13054755 | N10: =CHOOSE(Drivers!$C$3,Opex!N14,Opex!N17,Opex!N20) -> -0.13054755 | O10: =CHOOSE(Drivers!$C$3,Opex!O14,Opex!O17,Opex!O20) -> -0.13054755 | ... Q10: =CHOOSE(Drivers!$C$3,Opex!Q14,Opex!Q17,Opex!Q20) -> -0.13054755
B12: Opex %
B13: Best case
B14: Opex as a % of revenue | H14: =H17+2% -> -0.11054755 | I14: =I17+2% -> -0.11054755 | J14: =J17+2% -> -0.11054755 | K14: =K17+2% -> -0.11054755 | L14: =L17+2% -> -0.11054755 | M14: =M17+2% -> -0.11054755 | N14: =N17+2% -> -0.11054755 | O14: =O17+2% -> -0.11054755 | ... Q14: =Q17+2% -> -0.11054755
B16: Base case
B17: Opex as a % of revenue | H17: =-'Opex comparables'!$D$19 -> -0.13054755 | I17: =-'Opex comparables'!$D$19 -> -0.13054755 | J17: =-'Opex comparables'!$D$19 -> -0.13054755 | K17: =-'Opex comparables'!$D$19 -> -0.13054755 | L17: =-'Opex comparables'!$D$19 -> -0.13054755 | M17: =-'Opex comparables'!$D$19 -> -0.13054755 | N17: =-'Opex comparables'!$D$19 -> -0.13054755 | O17: =-'Opex comparables'!$D$19 -> -0.13054755 | ... Q17: =-'Opex comparables'!$D$19 -> -0.13054755
B19: Worst case
B20: Opex as a % of revenue | H20: =H17-2% -> -0.15054755 | I20: =I17-2% -> -0.15054755 | J20: =J17-2% -> -0.15054755 | K20: =K17-2% -> -0.15054755 | L20: =L17-2% -> -0.15054755 | M20: =M17-2% -> -0.15054755 | N20: =N17-2% -> -0.15054755 | O20: =O17-2% -> -0.15054755 | ... Q20: =Q17-2% -> -0.15054755

Sheet Balance Sheet ->
B14: Balance Sheet -->

Sheet PP&E ->
B14: Property, Plant & Equipment

Sheet PP&E
B1: Fixed asset roll forward
B3: ="Selected case:"&CHOOSE(C3," as a % of PPE"," as a % of revenue") -> Selected case: as a % of PPE | C3: 1
C5: Tesla PP&E (in mln $)
B6: ($ millions) | C6: 2021 Act | D6: 2022 Act | E6: 2023 Act | F6: 2024 Act | G6: 2025 Act | H6: 2026 Fcst | I6: 2027 Fcst | J6: 2028 Fcst | K6: 2029 Fcst | L6: 2030 Fcst | M6: 2031 Fcst | N6: 2032 Fcst | O6: 2033 Fcst | P6: 2034 Fcst | Q6: 2035 Fcst
B7: Beginning PP&E | C7: 13923 | D7: =C10 -> 18884 | E7: =D10 -> 23548 | F7: =E10 -> 29725 | G7: =F10 -> 35836 | H7: =G10 -> 40643 | I7: =H10 -> 46820.736 | J7: =I10 -> 53417.257 | K7: =J10 -> 60365.122 | ... Q7: =P10 -> 101315.72
B8: Capex | C8: =C10-C7-C9 -> 7872 | D8: =D10-D7-D9 -> 8411 | E8: =E10-E7-E9 -> 10844 | F8: =F10-F7-F9 -> 11479 | G8: =G10-G7-G9 -> 10955 | H8: =CHOOSE($C$3,H32*H7,H33*Opex!H5) -> 11380.04 | I8: =CHOOSE($C$3,I32*I7,I33*Opex!I5) -> 13109.806 | J8: =CHOOSE($C$3,J32*J7,J33*Opex!J5) -> 14956.832 | K8: =CHOOSE($C$3,K32*K7,K33*Opex!K5) -> 16902.234 | L8: =CHOOSE($C$3,L32*L7,L33*Opex!L5) -> 18919.086 | M8: =CHOOSE($C$3,M32*M7,M33*Opex!M5) -> 20970.922 | N8: =CHOOSE($C$3,N32*N7,N33*Opex!N5) -> 23010.087 | O8: =CHOOSE($C$3,O32*O7,O33*Opex!O5) -> 24975.935 | ... Q8: =CHOOSE($C$3,Q32*Q7,Q33*Opex!Q5) -> 28368.401
B9: D&A | C9: -2911 | D9: -3747 | E9: -4667 | F9: -5368 | G9: -6148 | H9: =H28 -> -5202.304 | I9: =I28 -> -6513.2846 | J9: =J28 -> -8008.9678 | K9: =K28 -> -9699.1912 | L9: =L28 -> -11591.1 | M9: =M28 -> -13688.192 | N9: =N28 -> -15989.201 | O9: =O28 -> -18486.794 | ... Q9: =Q28 -> -24002.924
B10: Ending PP&E | C10: ='Balance Sheet Input'!C13 -> 18884 | D10: ='Balance Sheet Input'!D13 -> 23548 | E10: ='Balance Sheet Input'!E13 -> 29725 | F10: ='Balance Sheet Input'!F13 -> 35836 | G10: ='Balance Sheet Input'!G13 -> 40643 | H10: =SUM(H7:H9) -> 46820.736 | I10: =SUM(I7:I9) -> 53417.257 | J10: =SUM(J7:J9) -> 60365.122 | K10: =SUM(K7:K9) -> 67568.165 | L10: =SUM(L7:L9) -> 74896.151 | M10: =SUM(M7:M9) -> 82178.881 | N10: =SUM(N7:N9) -> 89199.767 | O10: =SUM(O7:O9) -> 95688.908 | ... Q10: =SUM(Q7:Q9) -> 105681.2
B12: Useful life Capex | C12: 10
B13: Useful life historical assets | C13: 10
C15: Tesla D&A (in mln $)
B16: ($ in million) | C16: 2021 Act | D16: 2022 Act | E16: 2023 Act | F16: 2024 Act | G16: 2025 Act | H16: 2026 Fcst | I16: 2027 Fcst | J16: 2028 Fcst | K16: 2029 Fcst | L16: 2030 Fcst | M16: 2031 Fcst | N16: 2032 Fcst | O16: 2033 Fcst | P16: 2034 Fcst | Q16: 2035 Fcst
H17: =-$H$7/$C$12 -> -4064.3 | I17: =-$H$7/$C$12 -> -4064.3 | J17: =-$H$7/$C$12 -> -4064.3 | K17: =-$H$7/$C$12 -> -4064.3 | L17: =-$H$7/$C$12 -> -4064.3 | M17: =-$H$7/$C$12 -> -4064.3 | N17: =-$H$7/$C$12 -> -4064.3 | O17: =-$H$7/$C$12 -> -4064.3 | ... Q17: =-$H$7/$C$12 -> -4064.3
H18: =-$H$8/$C$12 -> -1138.004 | I18: =-$H$8/$C$12 -> -1138.004 | J18: =-$H$8/$C$12 -> -1138.004 | K18: =-$H$8/$C$12 -> -1138.004 | L18: =-$H$8/$C$12 -> -1138.004 | M18: =-$H$8/$C$12 -> -1138.004 | N18: =-$H$8/$C$12 -> -1138.004 | O18: =-$H$8/$C$12 -> -1138.004 | ... Q18: =-$H$8/$C$12 -> -1138.004
I19: =-$I$8/$C$12 -> -1310.9806 | J19: =-$I$8/$C$12 -> -1310.9806 | K19: =-$I$8/$C$12 -> -1310.9806 | L19: =-$I$8/$C$12 -> -1310.9806 | M19: =-$I$8/$C$12 -> -1310.9806 | N19: =-$I$8/$C$12 -> -1310.9806 | O19: =-$I$8/$C$12 -> -1310.9806 | P19: =-$I$8/$C$12 -> -1310.9806 | Q19: =-$I$8/$C$12 -> -1310.9806
J20: =-$J$8/$C$12 -> -1495.6832 | K20: =-$J$8/$C$12 -> -1495.6832 | L20: =-$J$8/$C$12 -> -1495.6832 | M20: =-$J$8/$C$12 -> -1495.6832 | N20: =-$J$8/$C$12 -> -1495.6832 | O20: =-$J$8/$C$12 -> -1495.6832 | P20: =-$J$8/$C$12 -> -1495.6832 | Q20: =-$J$8/$C$12 -> -1495.6832
K21: =-$K$8/$C$12 -> -1690.2234 | L21: =-$K$8/$C$12 -> -1690.2234 | M21: =-$K$8/$C$12 -> -1690.2234 | N21: =-$K$8/$C$12 -> -1690.2234 | O21: =-$K$8/$C$12 -> -1690.2234 | P21: =-$K$8/$C$12 -> -1690.2234 | Q21: =-$K$8/$C$12 -> -1690.2234
L22: =-$L$8/$C$12 -> -1891.9086 | M22: =-$L$8/$C$12 -> -1891.9086 | N22: =-$L$8/$C$12 -> -1891.9086 | O22: =-$L$8/$C$12 -> -1891.9086 | P22: =-$L$8/$C$12 -> -1891.9086 | Q22: =-$L$8/$C$12 -> -1891.9086
M23: =-$M$8/$C$12 -> -2097.0922 | N23: =-$M$8/$C$12 -> -2097.0922 | O23: =-$M$8/$C$12 -> -2097.0922 | P23: =-$M$8/$C$12 -> -2097.0922 | Q23: =-$M$8/$C$12 -> -2097.0922
N24: =-$N$8/$C$12 -> -2301.0087 | O24: =-$N$8/$C$12 -> -2301.0087 | P24: =-$N$8/$C$12 -> -2301.0087 | Q24: =-$N$8/$C$12 -> -2301.0087
O25: =-$O$8/$C$12 -> -2497.5935 | P25: =-$O$8/$C$12 -> -2497.5935 | Q25: =-$O$8/$C$12 -> -2497.5935
P26: =-$P$8/$C$12 -> -2679.2894 | Q26: =-$P$8/$C$12 -> -2679.2894
Q27: =-$Q$8/$C$12 -> -2836.8401
B28: Total D&A | C28: =SUM(C17:C27) -> 0 | D28: =SUM(D17:D27) -> 0 | E28: =SUM(E17:E27) -> 0 | F28: =SUM(F17:F27) -> 0 | G28: =SUM(G17:G27) -> 0 | H28: =SUM(H17:H27) -> -5202.304 | I28: =SUM(I17:I27) -> -6513.2846 | J28: =SUM(J17:J27) -> -8008.9678 | ... Q28: =SUM(Q17:Q27) -> -24002.924
B31: Selected case
B32: Capex as a % of PP&E | H32: =CHOOSE(Drivers!$C$3,H36,H39,H42) -> 0.28 | I32: =CHOOSE(Drivers!$C$3,I36,I39,I42) -> 0.28 | J32: =CHOOSE(Drivers!$C$3,J36,J39,J42) -> 0.28 | K32: =CHOOSE(Drivers!$C$3,K36,K39,K42) -> 0.28 | L32: =CHOOSE(Drivers!$C$3,L36,L39,L42) -> 0.28 | M32: =CHOOSE(Drivers!$C$3,M36,M39,M42) -> 0.28 | N32: =CHOOSE(Drivers!$C$3,N36,N39,N42) -> 0.28 | O32: =CHOOSE(Drivers!$C$3,O36,O39,O42) -> 0.28 | ... Q32: =CHOOSE(Drivers!$C$3,Q36,Q39,Q42) -> 0.28
B33: Capex as a % of revenue | H33: =CHOOSE(Drivers!$C$3,H37,H40,H43) -> 0.11 | I33: =CHOOSE(Drivers!$C$3,I37,I40,I43) -> 0.11 | J33: =CHOOSE(Drivers!$C$3,J37,J40,J43) -> 0.11 | K33: =CHOOSE(Drivers!$C$3,K37,K40,K43) -> 0.11 | L33: =CHOOSE(Drivers!$C$3,L37,L40,L43) -> 0.11 | M33: =CHOOSE(Drivers!$C$3,M37,M40,M43) -> 0.11 | N33: =CHOOSE(Drivers!$C$3,N37,N40,N43) -> 0.11 | O33: =CHOOSE(Drivers!$C$3,O37,O40,O43) -> 0.11 | ... Q33: =CHOOSE(Drivers!$C$3,Q37,Q40,Q43) -> 0.11
B34: Capex %
B35: Best case
B36: Capex as a % of PP&E | H36: =H39-5% -> 0.23 | I36: =I39-5% -> 0.23 | J36: =J39-5% -> 0.23 | K36: =K39-5% -> 0.23 | L36: =L39-5% -> 0.23 | M36: =M39-5% -> 0.23 | N36: =N39-5% -> 0.23 | O36: =O39-5% -> 0.23 | P36: =P39-5% -> 0.23 | Q36: =Q39+5% -> 0.33
B37: =B33 -> Capex as a % of revenue | H37: =H40-3% -> 0.08 | I37: =I40-3% -> 0.08 | J37: =J40-3% -> 0.08 | K37: =K40-3% -> 0.08 | L37: =L40-3% -> 0.08 | M37: =M40-3% -> 0.08 | N37: =N40-3% -> 0.08 | O37: =O40-3% -> 0.08 | P37: =P40-3% -> 0.08 | Q37: =Q40+3% -> 0.14
B38: Base case
B39: Capex as a % of PP&E | C39: =C8/C7 -> 0.56539539 | D39: =D8/D7 -> 0.44540352 | E39: =E8/E7 -> 0.4605062 | F39: =F8/F7 -> 0.38617325 | G39: =G8/G7 -> 0.30569818 | H39: =28% -> 0.28 | I39: =H39 -> 0.28 | J39: =I39 -> 0.28 | K39: =J39 -> 0.28 | L39: =K39 -> 0.28 | M39: =L39 -> 0.28 | N39: =M39 -> 0.28 | O39: =N39 -> 0.28 | P39: =O39 -> 0.28 | Q39: =P39 -> 0.28
B40: =B33 -> Capex as a % of revenue | C40: =C8/'P&L Input'!C7 -> 0.14625718 | D40: =D8/'P&L Input'!D7 -> 0.1032506 | E40: =E8/'P&L Input'!E7 -> 0.11205605 | F40: =F8/'P&L Input'!F7 -> 0.11750435 | G40: =G8/'P&L Input'!G7 -> 0.11552617 | H40: =11% -> 0.11 | I40: =H40 -> 0.11 | J40: =I40 -> 0.11 | K40: =J40 -> 0.11 | L40: =K40 -> 0.11 | M40: =L40 -> 0.11 | N40: =M40 -> 0.11 | O40: =N40 -> 0.11 | P40: =O40 -> 0.11 | Q40: =P40 -> 0.11
B41: Worst case
B42: Capex as a % of PP&E | H42: =H39+5% -> 0.33 | I42: =I39+5% -> 0.33 | J42: =J39+5% -> 0.33 | K42: =K39+5% -> 0.33 | L42: =L39+5% -> 0.33 | M42: =M39+5% -> 0.33 | N42: =N39+5% -> 0.33 | O42: =O39+5% -> 0.33 | P42: =P39+5% -> 0.33 | Q42: =Q39-5% -> 0.23
B43: =B33 -> Capex as a % of revenue | H43: =H40+3% -> 0.14 | I43: =I40+3% -> 0.14 | J43: =J40+3% -> 0.14 | K43: =K40+3% -> 0.14 | L43: =L40+3% -> 0.14 | M43: =M40+3% -> 0.14 | N43: =N40+3% -> 0.14 | O43: =O40+3% -> 0.14 | P43: =P40+3% -> 0.14 | Q43: =Q40-3% -> 0.08

Sheet Working Capital -> 
B14: Working capital

Sheet WC comparables
B1: Working Capital comparables
B3: Comparables - 2019
C5: DSO | F5: DIO | I5: DPO | L5: Net trade cycle
B6: Vehicle | C6: Average | D6: Adj. Average | F6: Average | G6: Adj. Average | I6: Average | J6: Adj. Average | L6: Average | M6: Adj. Average
B7: GM | C7: 19.942786 | D7: =C7 -> 19.942786 | F7: 33.829608 | G7: =F7 -> 33.829608 | I7: 68.381488 | J7: =I7 -> 68.381488 | L7: =C7+F7-I7 -> -14.609093 | M7: =L7 -> -14.609093
B8: Ford | C8: 25.851187 | D8: =C8 -> 25.851187 | F8: 29.988195 | G8: =F8 -> 29.988195 | I8: 57.517466 | J8: =I8 -> 57.517466 | L8: =C8+F8-I8 -> -1.6780836 | M8: =L8 -> -1.6780836
B9: Fiat Chrysler | C9: 22.055145 | D9: =C9 -> 22.055145 | F9: 37.567301 | G9: =F9 -> 37.567301 | I9: 83.527543 | J9: =I9 -> 83.527543 | L9: =C9+F9-I9 -> -23.905097 | M9: =L9 -> -23.905097
B10: BMW | C10: 8.7485003 | D10: =C10 -> 8.7485003 | F10: 66.427199 | G10: =F10 -> 66.427199 | I10: 40.64769 | J10: =I10 -> 40.64769 | L10: =C10+F10-I10 -> 34.528009 | M10: =L10 -> 34.528009
B11: Volkswagen | C11: 25.565882 | D11: =C11 -> 25.565882 | F11: 82.692614 | G11: =F11 -> 82.692614 | I11: 40.238832 | J11: =I11 -> 40.238832 | L11: =C11+F11-I11 -> 68.019664 | M11: =L11 -> 68.019664
B12: Jaguar | C12: 20.249442 | F12: 82.889598 | I12: 162.72368 | L12: =C12+F12-I12 -> -59.584635
B13: Ferrari | C13: 22.081784 | D13: =C13 -> 22.081784 | F13: 83.767313 | G13: =F13 -> 83.767313 | I13: 142.00554 | J13: =I13 -> 142.00554 | L13: =C13+F13-I13 -> -36.156443 | M13: =L13 -> -36.156443
B14: Paccar | C14: 19.492537 | D14: =C14 -> 19.492537 | F14: 20.192644 | G14: =F14 -> 20.192644 | I14: 55.936953 | J14: =I14 -> 55.936953 | L14: =C14+F14-I14 -> -16.251771 | M14: =D14+G14-J14 -> -16.251771
B15: Average | C15: =AVERAGE(C7:C14) -> 20.498408 | D15: =AVERAGE(D7:D14) -> 20.533975 | F15: =AVERAGE(F7:F14) -> 54.669309 | G15: =AVERAGE(G7:G14) -> 50.637839 | I15: =AVERAGE(I7:I14) -> 81.372398 | J15: =AVERAGE(J7:J14) -> 69.750787 | L15: =AVERAGE(L7:L14) -> -6.2046813 | M15: =AVERAGE(M7:M14) -> 1.4210264

Sheet Working capital
B1: Working capital
C3: Tesla Working capital (in mln $)
B4: ($ millions) | C4: 2021 Act | D4: 2022 Act | E4: 2023 Act | F4: 2024 Act | G4: 2025 Act | H4: 2026 Fcst | I4: 2027 Fcst | J4: 2028 Fcst | K4: 2029 Fcst | L4: 2030 Fcst | M4: 2031 Fcst | N4: 2032 Fcst | O4: 2033 Fcst | P4: 2034 Fcst | Q4: 2035 Fcst
B5: Trade receivables | C5: ='Balance Sheet Input'!C5 -> 1913 | D5: ='Balance Sheet Input'!D5 -> 2952 | E5: ='Balance Sheet Input'!E5 -> 3508 | F5: ='Balance Sheet Input'!F5 -> 4418 | G5: ='Balance Sheet Input'!G5 -> 4576 | H5: =H11*('P&L'!H5)/360 -> 5039.5578 | I5: =I11*('P&L'!I5)/360 -> 5681.6876 | J5: =J11*('P&L'!J5)/360 -> 6537.0489 | K5: =K11*('P&L'!K5)/360 -> 7409.8083 | L5: =L11*('P&L'!L5)/360 -> 8466.4915 | M5: =M11*('P&L'!M5)/360 -> 9427.9932 | N5: =N11*('P&L'!N5)/360 -> 10395.382 | O5: =O11*('P&L'!O5)/360 -> 11369.011 | ... Q5: =Q11*('P&L'!Q5)/360 -> 13336.511
B6: Inventory | C6: ='Balance Sheet Input'!C6 -> 5757 | D6: ='Balance Sheet Input'!D6 -> 12839 | E6: ='Balance Sheet Input'!E6 -> 13626 | F6: ='Balance Sheet Input'!F6 -> 12017 | G6: ='Balance Sheet Input'!G6 -> 12392 | H6: =-H12*('P&L'!H$6)/360 -> 17360.777 | I6: =-I12*('P&L'!I$6)/360 -> 19620.821 | J6: =-J12*('P&L'!J$6)/360 -> 22615.786 | K6: =-K12*('P&L'!K$6)/360 -> 25673.75 | L6: =-L12*('P&L'!L$6)/360 -> 29343.937 | M6: =-M12*('P&L'!M$6)/360 -> 32700.066 | N6: =-N12*('P&L'!N$6)/360 -> 36077.856 | O6: =-O12*('P&L'!O$6)/360 -> 39478.606 | ... Q6: =-Q12*('P&L'!Q$6)/360 -> 46354.579
B7: Trade payables | C7: ='Balance Sheet Input'!C22 -> 10025 | D7: ='Balance Sheet Input'!D22 -> 15255 | E7: ='Balance Sheet Input'!E22 -> 14431 | F7: ='Balance Sheet Input'!F22 -> 12474 | G7: ='Balance Sheet Input'!G22 -> 13371 | H7: =-H13*('P&L'!H$6)/360 -> 20981.801 | I7: =-I13*('P&L'!I$6)/360 -> 23713.233 | J7: =-J13*('P&L'!J$6)/360 -> 27332.872 | K7: =-K13*('P&L'!K$6)/360 -> 31028.651 | L7: =-L13*('P&L'!L$6)/360 -> 35464.347 | M7: =-M13*('P&L'!M$6)/360 -> 39520.481 | N7: =-N13*('P&L'!N$6)/360 -> 43602.793 | O7: =-O13*('P&L'!O$6)/360 -> 47712.854 | ... Q7: =-Q13*('P&L'!Q$6)/360 -> 56022.983
B8: Net trade cycle | C8: =C5+C6-C7 -> -2355 | D8: =D5+D6-D7 -> 536 | E8: =E5+E6-E7 -> 2703 | F8: =F5+F6-F7 -> 3961 | G8: =G5+G6-G7 -> 3597 | H8: =H5+H6-H7 -> 1418.5344 | I8: =I5+I6-I7 -> 1589.2756 | J8: =J5+J6-J7 -> 1819.9624 | ... Q8: =Q5+Q6-Q7 -> 3668.1067
B10: Selected case:
B11: DSO | C11: ='Balance Sheet Input'!C43 -> 12.795273 | D11: ='Balance Sheet Input'!D43 -> 13.045592 | E11: ='Balance Sheet Input'!E43 -> 13.049921 | F11: ='Balance Sheet Input'!F43 -> 16.280889 | G11: ='Balance Sheet Input'!G43 -> 17.372267 | H11: =AVERAGE($C11:$G11) -> 14.508788 | I11: =H11 -> 14.508788 | J11: =I11 -> 14.508788 | K11: =J11 -> 14.508788 | L11: =K11 -> 14.508788 | M11: =L11 -> 14.508788 | N11: =M11 -> 14.508788 | O11: =N11 -> 14.508788 | P11: =O11 -> 14.508788 | Q11: =P11 -> 14.508788
B12: DIO | C12: ='Balance Sheet Input'!C44 -> 51.533431 | D12: ='Balance Sheet Input'!D44 -> 76.259961 | E12: ='Balance Sheet Input'!E44 -> 62.004475 | F12: ='Balance Sheet Input'!F44 -> 53.914756 | G12: ='Balance Sheet Input'!G44 -> 57.390298 | H12: =AVERAGE($C12:$G12) -> 60.220584 | I12: =H12 -> 60.220584 | J12: =I12 -> 60.220584 | K12: =J12 -> 60.220584 | L12: =K12 -> 60.220584 | M12: =L12 -> 60.220584 | N12: =M12 -> 60.220584 | O12: =N12 -> 60.220584 | P12: =O12 -> 60.220584 | Q12: =P12 -> 60.220584
B13: DPO | C13: ='Balance Sheet Input'!C45 -> 89.73817 | D13: ='Balance Sheet Input'!D45 -> 90.610305 | E13: ='Balance Sheet Input'!E45 -> 65.667589 | F13: ='Balance Sheet Input'!F45 -> 55.965105 | G13: ='Balance Sheet Input'!G45 -> 61.924279 | H13: =AVERAGE($C13:$G13) -> 72.78109 | I13: =H13 -> 72.78109 | J13: =I13 -> 72.78109 | K13: =J13 -> 72.78109 | L13: =K13 -> 72.78109 | M13: =L13 -> 72.78109 | N13: =M13 -> 72.78109 | O13: =N13 -> 72.78109 | P13: =O13 -> 72.78109 | Q13: =P13 -> 72.78109
B14: Net trade cycle | C14: =C11+C12-C13 -> -25.409466 | D14: =D11+D12-D13 -> -1.3047522 | E14: =E11+E12-E13 -> 9.3868062 | F14: =F11+F12-F13 -> 14.23054 | G14: =G11+G12-G13 -> 12.838286 | H14: =H11+H12-H13 -> 1.9482827 | I14: =I11+I12-I13 -> 1.9482827 | J14: =J11+J12-J13 -> 1.9482827 | ... Q14: =Q11+Q12-Q13 -> 1.9482827

Sheet Financing ->
B14: Financing

Sheet Financing
B1: Financing
B3: Cover negative cash flows with:
B4: Debt | C4: 0.5
B5: Equity | C5: 0.5
B7: =Drivers!B11 -> Bond Yield (Mar 19 2030) | C7: =Drivers!C11 -> 0.0545
C9: Tesla Financing (in mln $)
B10: ($ millions) | C10: 2021 Act | D10: 2022 Act | E10: 2023 Act | F10: 2024 Act | G10: 2025 Act | H10: 2026 Fcst | I10: 2027 Fcst | J10: 2028 Fcst | K10: 2029 Fcst | L10: 2030 Fcst | M10: 2031 Fcst | N10: 2032 Fcst | O10: 2033 Fcst | P10: 2034 Fcst | Q10: 2035 Fcst
B11: Long-term debt and capital leases, net of current | C11: ='Balance Sheet Input'!C30 -> 5245 | D11: ='Balance Sheet Input'!D30 -> 1597 | E11: ='Balance Sheet Input'!E30 -> 2857 | F11: ='Balance Sheet Input'!F30 -> 5757 | G11: ='Balance Sheet Input'!G30 -> 6736 | H11: =G11+G19 -> 6736 | I11: =H11+H19 -> 6736 | J11: =I11+I19 -> 6736 | K11: =J11+J19 -> 6736 | L11: =K11+K19 -> 6736 | M11: =L11+L19 -> 6736 | N11: =M11+M19 -> 6736 | O11: =N11+N19 -> 6736 | ... Q11: =P11+P19 -> 6736
B12: ='P&L Input'!B17 -> Interest expense | C12: ='P&L Input'!C17 -> -371 | D12: ='P&L Input'!D17 -> -191 | E12: ='P&L Input'!E17 -> -156 | F12: ='P&L Input'!F17 -> -350 | G12: ='P&L Input'!G17 -> -338 | H12: =-G11*H13 -> -367.112 | I12: =-H11*I13 -> -367.112 | J12: =-I11*J13 -> -367.112 | K12: =-J11*K13 -> -367.112 | L12: =-K11*L13 -> -367.112 | M12: =-L11*M13 -> -367.112 | N12: =-M11*N13 -> -367.112 | O12: =-N11*O13 -> -367.112 | ... Q12: =-P11*Q13 -> -367.112
B13: Interest rate | C13: =C12/C11 -> -0.070734032 | D13: =D12/D11 -> -0.11959925 | E13: =E12/E11 -> -0.05460273 | F13: =F12/F11 -> -0.060795553 | G13: =G12/G11 -> -0.050178147 | H13: =$C$7 -> 0.0545 | I13: =$C$7 -> 0.0545 | J13: =$C$7 -> 0.0545 | K13: =$C$7 -> 0.0545 | L13: =$C$7 -> 0.0545 | M13: =$C$7 -> 0.0545 | N13: =$C$7 -> 0.0545 | O13: =$C$7 -> 0.0545 | ... Q13: =$C$7 -> 0.0545
C16: Tesla Cash Flow (in mln $)
C17: 2021 Act | D17: 2022 Act | E17: 2023 Act | F17: 2024 Act | G17: 2025 Act | H17: 2026 Fcst | I17: 2027 Fcst | J17: 2028 Fcst | K17: 2029 Fcst | L17: 2030 Fcst | M17: 2031 Fcst | N17: 2032 Fcst | O17: 2033 Fcst | P17: 2034 Fcst | Q17: 2035 Fcst
B18: Unlevered Free Cash Flow | H18: ='Cash Flow'!H20 -> 4254.1293 | I18: ='Cash Flow'!I20 -> 574.39342 | J18: ='Cash Flow'!J20 -> 1649.8545 | K18: ='Cash Flow'!K20 -> 1909.0577 | L18: ='Cash Flow'!L20 -> 3312.1849 | M18: ='Cash Flow'!M20 -> 3454.1013 | N18: ='Cash Flow'!N20 -> 4278.7133 | O18: ='Cash Flow'!O20 -> 5372.8105 | ... Q18: ='Cash Flow'!Q20 -> 8619.8276
B19: Debt | H19: =IF(H$18<0,-H$18*$C4,0) -> 0 | I19: =IF(I$18<0,-I$18*$C4,0) -> 0 | J19: =IF(J$18<0,-J$18*$C4,0) -> 0 | K19: =IF(K$18<0,-K$18*$C4,0) -> 0 | L19: =IF(L$18<0,-L$18*$C4,0) -> 0 | M19: =IF(M$18<0,-M$18*$C4,0) -> 0 | N19: =IF(N$18<0,-N$18*$C4,0) -> 0 | O19: =IF(O$18<0,-O$18*$C4,0) -> 0 | ... Q19: =IF(Q$18<0,-Q$18*$C4,0) -> 0
B20: Equity | H20: =IF(H$18<0,-H$18*$C5,0) -> 0 | I20: =IF(I$18<0,-I$18*$C5,0) -> 0 | J20: =IF(J$18<0,-J$18*$C5,0) -> 0 | K20: =IF(K$18<0,-K$18*$C5,0) -> 0 | L20: =IF(L$18<0,-L$18*$C5,0) -> 0 | M20: =IF(M$18<0,-M$18*$C5,0) -> 0 | N20: =IF(N$18<0,-N$18*$C5,0) -> 0 | O20: =IF(O$18<0,-O$18*$C5,0) -> 0 | ... Q20: =IF(Q$18<0,-Q$18*$C5,0) -> 0
B22: Debt ratio | C22: =-C12/C11 -> 0.070734032 | D22: =-D12/D11 -> 0.11959925 | E22: =-E12/E11 -> 0.05460273 | F22: =-F12/F11 -> 0.060795553 | G22: =-G12/G11 -> 0.050178147 | H22: =-H12/H11 -> 0.0545 | I22: =-I12/I11 -> 0.0545 | J22: =-J12/J11 -> 0.0545 | ... Q22: =-Q12/Q11 -> 0.0545

Sheet Output ->
B14: Output -->

Sheet P&L
B1: P&L
C3: Tesla P&L (in mln $)
B4: ($ millions) | C4: 2021 Act | D4: 2022 Act | E4: 2023 Act | F4: 2024 Act | G4: 2025 Act | H4: 2026 Fcst | I4: 2027 Fcst | J4: 2028 Fcst | K4: 2029 Fcst | L4: 2030 Fcst | M4: 2031 Fcst | N4: 2032 Fcst | O4: 2033 Fcst | P4: 2034 Fcst | Q4: 2035 Fcst
B5: Revenues | C5: ='Automotive Revenue'!C10+'Revenue Energy & Other'!C7 -> 53823 | D5: ='Automotive Revenue'!D10+'Revenue Energy & Other'!D7 -> 81462 | E5: ='Automotive Revenue'!E10+'Revenue Energy & Other'!E7 -> 96773 | F5: ='Automotive Revenue'!F10+'Revenue Energy & Other'!F7 -> 97690 | G5: ='Automotive Revenue'!G10+'Revenue Energy & Other'!G7 -> 94827 | H5: ='Automotive Revenue'!H10+'Revenue Energy & Other'!H7 -> 125044.27 | I5: ='Automotive Revenue'!I10+'Revenue Energy & Other'!I7 -> 140977.14 | J5: ='Automotive Revenue'!J10+'Revenue Energy & Other'!J7 -> 162200.84 | ... Q5: ='Automotive Revenue'!Q10+'Revenue Energy & Other'!Q7 -> 330912.81
B6: Cost of sales | C6: ='Cost of sales Energy & Other'!C7+'Cost of sales automotive'!C10 -> -40217 | D6: ='Cost of sales Energy & Other'!D7+'Cost of sales automotive'!D10 -> -60609 | E6: ='Cost of sales Energy & Other'!E7+'Cost of sales automotive'!E10 -> -79113 | F6: ='Cost of sales Energy & Other'!F7+'Cost of sales automotive'!F10 -> -80240 | G6: ='Cost of sales Energy & Other'!G7+'Cost of sales automotive'!G10 -> -77733 | H6: ='Cost of sales Energy & Other'!H7+'Cost of sales automotive'!H10 -> -103783.12 | I6: ='Cost of sales Energy & Other'!I7+'Cost of sales automotive'!I10 -> -117293.71 | J6: ='Cost of sales Energy & Other'!J7+'Cost of sales automotive'!J10 -> -135197.67 | ... Q6: ='Cost of sales Energy & Other'!Q7+'Cost of sales automotive'!Q10 -> -277108.71
B7: Gross profit | C7: =SUM(C5:C6) -> 13606 | D7: =SUM(D5:D6) -> 20853 | E7: =SUM(E5:E6) -> 17660 | F7: =SUM(F5:F6) -> 17450 | G7: =SUM(G5:G6) -> 17094 | H7: =SUM(H5:H6) -> 21261.151 | I7: =SUM(I5:I6) -> 23683.434 | J7: =SUM(J5:J6) -> 27003.162 | ... Q7: =SUM(Q5:Q6) -> 53804.101
B8: Operating expenses | C8: =Opex!C7 -> -7083 | D8: =Opex!D7 -> -7197 | E8: =Opex!E7 -> -8769 | F8: =Opex!F7 -> -10374 | G8: =Opex!G7 -> -12739 | H8: =Opex!H7 -> -16324.223 | I8: =Opex!I7 -> -18404.22 | J8: =Opex!J7 -> -21174.921 | ... Q8: =Opex!Q7 -> -43199.856
B9: EBIT | C9: =SUM(C7:C8) -> 6523 | D9: =SUM(D7:D8) -> 13656 | E9: =SUM(E7:E8) -> 8891 | F9: =SUM(F7:F8) -> 7076 | G9: =SUM(G7:G8) -> 4355 | H9: =SUM(H7:H8) -> 4936.9285 | I9: =SUM(I7:I8) -> 5279.2137 | J9: =SUM(J7:J8) -> 5828.2411 | ... Q9: =SUM(Q7:Q8) -> 10604.245
B10: Interest expenses/income | C10: =Financing!C12+('P&L Input'!C16+'P&L Input'!C18) -> -180 | D10: =Financing!D12+('P&L Input'!D16+'P&L Input'!D18) -> 63 | E10: =Financing!E12+('P&L Input'!E16+'P&L Input'!E18) -> 1082 | F10: =Financing!F12+('P&L Input'!F16+'P&L Input'!F18) -> 1914 | G10: =Financing!G12+('P&L Input'!G16+'P&L Input'!G18) -> 923 | H10: =Financing!H12 -> -367.112 | I10: =Financing!I12 -> -367.112 | J10: =Financing!J12 -> -367.112 | K10: =Financing!K12 -> -367.112 | L10: =Financing!L12 -> -367.112 | M10: =Financing!M12 -> -367.112 | N10: =Financing!N12 -> -367.112 | O10: =Financing!O12 -> -367.112 | ... Q10: =Financing!Q12 -> -367.112
B11: EBT | C11: =SUM(C9:C10) -> 6343 | D11: =SUM(D9:D10) -> 13719 | E11: =SUM(E9:E10) -> 9973 | F11: =SUM(F9:F10) -> 8990 | G11: =SUM(G9:G10) -> 5278 | H11: =SUM(H9:H10) -> 4569.8165 | I11: =SUM(I9:I10) -> 4912.1017 | J11: =SUM(J9:J10) -> 5461.1291 | ... Q11: =SUM(Q9:Q10) -> 10237.133
B12: Taxes | C12: ='P&L Input'!C20 -> -699 | D12: ='P&L Input'!D20 -> -1132 | E12: ='P&L Input'!E20 -> 5001 | F12: ='P&L Input'!F20 -> -1837 | G12: ='P&L Input'!G20 -> -1423 | H12: =IF(H11>0,-H11*Drivers!$C$12,0) -> -959.66147 | I12: =IF(I11>0,-I11*Drivers!$C$12,0) -> -1031.5413 | J12: =IF(J11>0,-J11*Drivers!$C$12,0) -> -1146.8371 | K12: =IF(K11>0,-K11*Drivers!$C$12,0) -> -1261.8643 | L12: =IF(L11>0,-L11*Drivers!$C$12,0) -> -1441.5647 | M12: =IF(M11>0,-M11*Drivers!$C$12,0) -> -1584.3182 | N12: =IF(N11>0,-N11*Drivers!$C$12,0) -> -1726.5505 | O12: =IF(O11>0,-O11*Drivers!$C$12,0) -> -1868.2303 | ... Q12: =IF(Q11>0,-Q11*Drivers!$C$12,0) -> -2149.7979
B13: Minority interest | C13: ='P&L Input'!C22 -> -125 | D13: ='P&L Input'!D22 -> -31 | E13: ='P&L Input'!E22 -> 23 | F13: ='P&L Input'!F22 -> -62 | G13: ='P&L Input'!G22 -> -61 | H13: 0 | I13: 0 | J13: 0 | K13: 0 | L13: 0 | M13: 0 | N13: 0 | O13: 0 | P13: 0 | Q13: 0
B14: Net Income | C14: =SUM(C11:C13) -> 5519 | D14: =SUM(D11:D13) -> 12556 | E14: =SUM(E11:E13) -> 14997 | F14: =SUM(F11:F13) -> 7091 | G14: =SUM(G11:G13) -> 3794 | H14: =SUM(H11:H13) -> 3610.1551 | I14: =SUM(I11:I13) -> 3880.5603 | J14: =SUM(J11:J13) -> 4314.292 | ... Q14: =SUM(Q11:Q13) -> 8087.3349
B16: Check
B17: Net income | C17: ='P&L Input'!C23 -> 5519 | D17: ='P&L Input'!D23 -> 12556 | E17: ='P&L Input'!E23 -> 14997 | F17: ='P&L Input'!F23 -> 7091 | G17: ='P&L Input'!G23 -> 3794
C18: =C14-C17 -> 0 | D18: =D14-D17 -> 0 | E18: =E14-E17 -> 0 | F18: =F14-F17 -> 0 | G18: =G14-G17 -> 0
B20: Revenue growth rate | D20: =(D5-C5)/C5 -> 0.51351653 | E20: =(E5-D5)/D5 -> 0.18795267 | F20: =(F5-E5)/E5 -> 0.0094757835 | G20: =(G5-F5)/F5 -> -0.029306992 | H20: =(H5-G5)/G5 -> 0.31865679 | I20: =(I5-H5)/H5 -> 0.12741787 | J20: =(J5-I5)/I5 -> 0.15054706 | K20: =(K5-J5)/J5 -> 0.1335097 | ... Q20: =(Q5-P5)/P5 -> 0.079944554

Sheet Balance Sheet
B1: Balance Sheet
C3: Tesla Balance Sheet (in mln $)
B4: ($ millions) | C4: 2021 Act | D4: 2022 Act | E4: 2023 Act | F4: 2024 Act | G4: 2025 Act | H4: 2026 Fcst | I4: 2027 Fcst | J4: 2028 Fcst | K4: 2029 Fcst | L4: 2030 Fcst | M4: 2031 Fcst | N4: 2032 Fcst | O4: 2033 Fcst | P4: 2034 Fcst | Q4: 2035 Fcst | S4: Assumption
B5: Cash | C5: ='Balance Sheet Input'!C4 -> 17576 | D5: =('Balance Sheet Input'!D4) -> 16253 | E5: =('Balance Sheet Input'!E4) -> 16398 | F5: =('Balance Sheet Input'!F4) -> 16139 | G5: =('Balance Sheet Input'!G4) -> 16513 | H5: =G5+'Cash Flow'!H29 -> 20477.111 | I5: =H5+'Cash Flow'!I29 -> 20761.486 | J5: =I5+'Cash Flow'!J29 -> 22121.322 | K5: =J5+'Cash Flow'!K29 -> 23740.361 | L5: =K5+'Cash Flow'!L29 -> 26762.527 | M5: =L5+'Cash Flow'!M29 -> 29926.61 | N5: =M5+'Cash Flow'!N29 -> 33915.305 | O5: =N5+'Cash Flow'!O29 -> 38998.097 | ... Q5: =P5+'Cash Flow'!Q29 -> 53834.939 | S5: Cash flow sheet
B6: Trade receivables | C6: ='Balance Sheet Input'!C5 -> 1913 | D6: =('Balance Sheet Input'!D5) -> 2952 | E6: =('Balance Sheet Input'!E5) -> 3508 | F6: =('Balance Sheet Input'!F5) -> 4418 | G6: =('Balance Sheet Input'!G5) -> 4576 | H6: ='Working capital'!H5 -> 5039.5578 | I6: ='Working capital'!I5 -> 5681.6876 | J6: ='Working capital'!J5 -> 6537.0489 | K6: ='Working capital'!K5 -> 7409.8083 | L6: ='Working capital'!L5 -> 8466.4915 | M6: ='Working capital'!M5 -> 9427.9932 | N6: ='Working capital'!N5 -> 10395.382 | O6: ='Working capital'!O5 -> 11369.011 | ... Q6: ='Working capital'!Q5 -> 13336.511 | S6: Working capital sheet
B7: Inventory | C7: ='Balance Sheet Input'!C6 -> 5757 | D7: =('Balance Sheet Input'!D6) -> 12839 | E7: =('Balance Sheet Input'!E6) -> 13626 | F7: =('Balance Sheet Input'!F6) -> 12017 | G7: =('Balance Sheet Input'!G6) -> 12392 | H7: ='Working capital'!H6 -> 17360.777 | I7: ='Working capital'!I6 -> 19620.821 | J7: ='Working capital'!J6 -> 22615.786 | K7: ='Working capital'!K6 -> 25673.75 | L7: ='Working capital'!L6 -> 29343.937 | M7: ='Working capital'!M6 -> 32700.066 | N7: ='Working capital'!N6 -> 36077.856 | O7: ='Working capital'!O6 -> 39478.606 | ... Q7: ='Working capital'!Q6 -> 46354.579 | S7: Working capital sheet
B8: Short-term investments | C8: ='Balance Sheet Input'!C8 -> 131 | D8: ='Balance Sheet Input'!D8 -> 5932 | E8: ='Balance Sheet Input'!E8 -> 12696 | F8: ='Balance Sheet Input'!F8 -> 20424 | G8: ='Balance Sheet Input'!G8 -> 27546 | H8: =G8 -> 27546 | I8: =H8 -> 27546 | J8: =I8 -> 27546 | K8: =J8 -> 27546 | L8: =K8 -> 27546 | M8: =L8 -> 27546 | N8: =M8 -> 27546 | O8: =N8 -> 27546 | ... Q8: =P8 -> 27546 | S8: Stays flat
B10: Prepaid expenses | C10: ='Balance Sheet Input'!C7 -> 1723 | D10: =('Balance Sheet Input'!D7) -> 2941 | E10: =('Balance Sheet Input'!E7) -> 3388 | F10: =('Balance Sheet Input'!F7) -> 5362 | G10: =('Balance Sheet Input'!G7) -> 7615 | H10: =H11*('P&L'!H$5) -> 8452.495 | I10: =I11*('P&L'!I$5) -> 9529.4939 | J10: =J11*('P&L'!J$5) -> 10964.131 | K10: =K11*('P&L'!K$5) -> 12427.949 | L10: =L11*('P&L'!L$5) -> 14200.249 | M10: =M11*('P&L'!M$5) -> 15812.908 | N10: =N11*('P&L'!N$5) -> 17435.441 | O10: =O11*('P&L'!O$5) -> 19068.441 | ... Q10: =Q11*('P&L'!Q$5) -> 22368.39 | S10: Grows as a % of revenues
B11: as a % of revenues | C11: =C10/('P&L'!C$5) -> 0.032012337 | D11: =D10/('P&L'!D$5) -> 0.036102723 | E11: =E10/('P&L'!E$5) -> 0.035009765 | F11: =F10/('P&L'!F$5) -> 0.054887911 | G11: =G10/('P&L'!G$5) -> 0.080304133 | H11: =AVERAGE($F$11:$G$11) -> 0.067596022 | I11: =AVERAGE($F$11:$G$11) -> 0.067596022 | J11: =AVERAGE($F$11:$G$11) -> 0.067596022 | K11: =AVERAGE($F$11:$G$11) -> 0.067596022 | L11: =AVERAGE($F$11:$G$11) -> 0.067596022 | M11: =AVERAGE($F$11:$G$11) -> 0.067596022 | N11: =AVERAGE($F$11:$G$11) -> 0.067596022 | O11: =AVERAGE($F$11:$G$11) -> 0.067596022 | ... Q11: =AVERAGE($F$11:$G$11) -> 0.067596022
B13: Operating lease vehicles | C13: =('Balance Sheet Input'!C11)+'Balance Sheet Input'!C14 -> 6527 | D13: =('Balance Sheet Input'!D11)+'Balance Sheet Input'!D14 -> 7598 | E13: =('Balance Sheet Input'!E11)+'Balance Sheet Input'!E14 -> 10169 | F13: =('Balance Sheet Input'!F11)+'Balance Sheet Input'!F14 -> 10741 | G13: =('Balance Sheet Input'!G11)+'Balance Sheet Input'!G14 -> 10939 | H13: =G13 -> 10939 | I13: =H13 -> 10939 | J13: =I13 -> 10939 | K13: =J13 -> 10939 | L13: =K13 -> 10939 | M13: =L13 -> 10939 | N13: =M13 -> 10939 | O13: =N13 -> 10939 | ... Q13: =P13 -> 10939 | S13: Stays flat
B14: Solar energy systems leased | C14: =('Balance Sheet Input'!C12) -> 5765 | D14: =('Balance Sheet Input'!D12) -> 5489 | E14: =('Balance Sheet Input'!E12) -> 5229 | F14: =('Balance Sheet Input'!F12) -> 4924 | G14: =('Balance Sheet Input'!G12) -> 4604 | H14: =G14 -> 4604 | I14: =H14 -> 4604 | J14: =I14 -> 4604 | K14: =J14 -> 4604 | L14: =K14 -> 4604 | M14: =L14 -> 4604 | N14: =M14 -> 4604 | O14: =N14 -> 4604 | ... Q14: =P14 -> 4604 | S14: Stays flat
B15: PP&E | C15: =('Balance Sheet Input'!C13) -> 18884 | D15: =('Balance Sheet Input'!D13) -> 23548 | E15: =('Balance Sheet Input'!E13) -> 29725 | F15: =('Balance Sheet Input'!F13) -> 35836 | G15: =('Balance Sheet Input'!G13) -> 40643 | H15: ='PP&E'!H10 -> 46820.736 | I15: ='PP&E'!I10 -> 53417.257 | J15: ='PP&E'!J10 -> 60365.122 | K15: ='PP&E'!K10 -> 67568.165 | L15: ='PP&E'!L10 -> 74896.151 | M15: ='PP&E'!M10 -> 82178.881 | N15: ='PP&E'!N10 -> 89199.767 | O15: ='PP&E'!O10 -> 95688.908 | ... Q15: ='PP&E'!Q10 -> 105681.2 | S15: PP&E sheet
B16: Intangible assets | C16: =('Balance Sheet Input'!C15) -> 257 | D16: =('Balance Sheet Input'!D15) -> 215 | E16: =('Balance Sheet Input'!E15) -> 178 | F16: =('Balance Sheet Input'!F15) -> 1076 | G16: =('Balance Sheet Input'!G15) -> 1008 | H16: =G16 -> 1008 | I16: =H16 -> 1008 | J16: =I16 -> 1008 | K16: =J16 -> 1008 | L16: =K16 -> 1008 | M16: =L16 -> 1008 | N16: =M16 -> 1008 | O16: =N16 -> 1008 | ... Q16: =P16 -> 1008 | S16: Stays flat
B17: Deferred tax assets | C17: ='Balance Sheet Input'!C16 -> 0 | D17: ='Balance Sheet Input'!D16 -> 328 | E17: ='Balance Sheet Input'!E16 -> 6733 | F17: ='Balance Sheet Input'!F16 -> 6524 | G17: ='Balance Sheet Input'!G16 -> 6925 | H17: =G17 -> 6925 | I17: =H17 -> 6925 | J17: =I17 -> 6925 | K17: =J17 -> 6925 | L17: =K17 -> 6925 | M17: =L17 -> 6925 | N17: =M17 -> 6925 | O17: =N17 -> 6925 | ... Q17: =P17 -> 6925 | S17: Stays flat
B18: Good will | C18: ='Balance Sheet Input'!C17 -> 200 | D18: ='Balance Sheet Input'!D17 -> 194 | E18: ='Balance Sheet Input'!E17 -> 253 | F18: ='Balance Sheet Input'!F17 -> 0 | G18: ='Balance Sheet Input'!G17 -> 0 | H18: =G18 -> 0 | I18: =H18 -> 0 | J18: =I18 -> 0 | K18: =J18 -> 0 | L18: =K18 -> 0 | M18: =L18 -> 0 | N18: =M18 -> 0 | O18: =N18 -> 0 | ... Q18: =P18 -> 0 | S18: Stays flat
B19: Digital assets,net | C19: ='Balance Sheet Input'!C18 -> 1260 | D19: ='Balance Sheet Input'!D18 -> 184 | E19: ='Balance Sheet Input'!E18 -> 184 | F19: ='Balance Sheet Input'!F18 -> 0 | G19: ='Balance Sheet Input'!G18 -> 0 | H19: =G19 -> 0 | I19: =H19 -> 0 | J19: =I19 -> 0 | K19: =J19 -> 0 | L19: =K19 -> 0 | M19: =L19 -> 0 | N19: =M19 -> 0 | O19: =N19 -> 0 | ... Q19: =P19 -> 0 | S19: Stays flat
B20: Other assets | C20: ='Balance Sheet Input'!C19 -> 2138 | D20: ='Balance Sheet Input'!D19 -> 3865 | E20: ='Balance Sheet Input'!E19 -> 4531 | F20: ='Balance Sheet Input'!F19 -> 4609 | G20: ='Balance Sheet Input'!G19 -> 5045 | H20: =H21*('P&L'!H$5) -> 6276.0969 | I20: =I21*('P&L'!I$5) -> 7075.7838 | J20: =J21*('P&L'!J$5) -> 8141.0223 | K20: =K21*('P&L'!K$5) -> 9227.9277 | L20: =L21*('P&L'!L$5) -> 10543.886 | M20: =M21*('P&L'!M$5) -> 11741.308 | N20: =N21*('P&L'!N$5) -> 12946.062 | O20: =O21*('P&L'!O$5) -> 14158.587 | ... Q20: =Q21*('P&L'!Q$5) -> 16608.845 | S20: Grows as a % of revenues
B21: as a % of revenues | C21: =C20/('P&L'!C$5) -> 0.039722795 | D21: =D20/('P&L'!D$5) -> 0.047445435 | E21: =E20/('P&L'!E$5) -> 0.046820911 | F21: =F20/('P&L'!F$5) -> 0.047179855 | G21: =G20/('P&L'!G$5) -> 0.053202147 | H21: =AVERAGE($F$21:$G$21) -> 0.050191001 | I21: =AVERAGE($F$21:$G$21) -> 0.050191001 | J21: =AVERAGE($F$21:$G$21) -> 0.050191001 | K21: =AVERAGE($F$21:$G$21) -> 0.050191001 | L21: =AVERAGE($F$21:$G$21) -> 0.050191001 | M21: =AVERAGE($F$21:$G$21) -> 0.050191001 | N21: =AVERAGE($F$21:$G$21) -> 0.050191001 | O21: =AVERAGE($F$21:$G$21) -> 0.050191001 | ... Q21: =AVERAGE($F$21:$G$21) -> 0.050191001
B22: Total assets | C22: =C5+C6+C7+C10+C13+C15+C20+C14+C16+C17+C18+C19+C8 -> 62131 | D22: =D5+D6+D7+D10+D13+D15+D20+D14+D16+D17+D18+D19+D8 -> 82338 | E22: =E5+E6+E7+E10+E13+E15+E20+E14+E16+E17+E18+E19+E8 -> 106618 | F22: =F5+F6+F7+F10+F13+F15+F20+F14+F16+F17+F18+F19+F8 -> 122070 | G22: =G5+G6+G7+G10+G13+G15+G20+G14+G16+G17+G18+G19+G8 -> 137806 | H22: =H5+H6+H7+H10+H13+H15+H20+H14+H16+H17+H18+H19+H8 -> 155448.77 | I22: =I5+I6+I7+I10+I13+I15+I20+I14+I16+I17+I18+I19+I8 -> 167108.53 | J22: =J5+J6+J7+J10+J13+J15+J20+J14+J16+J17+J18+J19+J8 -> 181766.43 | ... Q22: =Q5+Q6+Q7+Q10+Q13+Q15+Q20+Q14+Q16+Q17+Q18+Q19+Q8 -> 309206.46
B24: Accounts payable | C24: ='Balance Sheet Input'!C22 -> 10025 | D24: ='Balance Sheet Input'!D22 -> 15255 | E24: ='Balance Sheet Input'!E22 -> 14431 | F24: ='Balance Sheet Input'!F22 -> 12474 | G24: ='Balance Sheet Input'!G22 -> 13371 | H24: ='Working capital'!H7 -> 20981.801 | I24: ='Working capital'!I7 -> 23713.233 | J24: ='Working capital'!J7 -> 27332.872 | K24: ='Working capital'!K7 -> 31028.651 | L24: ='Working capital'!L7 -> 35464.347 | M24: ='Working capital'!M7 -> 39520.481 | N24: ='Working capital'!N7 -> 43602.793 | O24: ='Working capital'!O7 -> 47712.854 | ... Q24: ='Working capital'!Q7 -> 56022.983 | S24: Working capital sheet
B25: Accrued liabilities | C25: ='Balance Sheet Input'!C23 -> 5719 | D25: ='Balance Sheet Input'!D23 -> 8205 | E25: ='Balance Sheet Input'!E23 -> 9080 | F25: ='Balance Sheet Input'!F23 -> 10723 | G25: ='Balance Sheet Input'!G23 -> 13279 | H25: =H26*('P&L'!H$5) -> 15618 | I25: =I26*('P&L'!I$5) -> 17608.013 | J25: =J26*('P&L'!J$5) -> 20258.847 | K25: =K26*('P&L'!K$5) -> 22963.6 | L25: =L26*('P&L'!L$5) -> 26238.347 | M25: =M26*('P&L'!M$5) -> 29218.119 | N25: =N26*('P&L'!N$5) -> 32216.136 | O25: =O26*('P&L'!O$5) -> 35233.492 | ... Q25: =Q26*('P&L'!Q$5) -> 41330.934 | S25: Grows as a % of revenues
B26: as a % of revenues | C26: =C25/('P&L'!C$5) -> 0.10625569 | D26: =D25/('P&L'!D$5) -> 0.10072181 | E26: =E25/('P&L'!E$5) -> 0.093827824 | F26: =F25/('P&L'!F$5) -> 0.10976559 | G26: =G25/('P&L'!G$5) -> 0.14003396 | H26: =AVERAGE($F$26:$G$26) -> 0.12489977 | I26: =AVERAGE($F$26:$G$26) -> 0.12489977 | J26: =AVERAGE($F$26:$G$26) -> 0.12489977 | K26: =AVERAGE($F$26:$G$26) -> 0.12489977 | L26: =AVERAGE($F$26:$G$26) -> 0.12489977 | M26: =AVERAGE($F$26:$G$26) -> 0.12489977 | N26: =AVERAGE($F$26:$G$26) -> 0.12489977 | O26: =AVERAGE($F$26:$G$26) -> 0.12489977 | ... Q26: =AVERAGE($F$26:$G$26) -> 0.12489977
B28: Deferred revenue | C28: ='Balance Sheet Input'!C24 -> 1447 | D28: ='Balance Sheet Input'!D24 -> 1747 | E28: ='Balance Sheet Input'!E24 -> 2864 | F28: ='Balance Sheet Input'!F24 -> 3168 | G28: ='Balance Sheet Input'!G24 -> 3424 | H28: =H29*('P&L'!H$5) -> 4285.0777 | I28: =I29*('P&L'!I$5) -> 4831.0732 | J28: =J29*('P&L'!J$5) -> 5558.3771 | K28: =K29*('P&L'!K$5) -> 6300.4743 | L28: =L29*('P&L'!L$5) -> 7198.9598 | M28: =M29*('P&L'!M$5) -> 8016.5136 | N28: =N29*('P&L'!N$5) -> 8839.0731 | O28: =O29*('P&L'!O$5) -> 9666.9388 | ... Q28: =Q29*('P&L'!Q$5) -> 11339.881 | S28: Grows as a % of revenues
B29: as a % of revenues | C29: =C28/('P&L'!C$5) -> 0.026884417 | D29: =D28/('P&L'!D$5) -> 0.021445582 | E29: =E28/('P&L'!E$5) -> 0.029595032 | F29: =F28/('P&L'!F$5) -> 0.032429112 | G29: =G28/('P&L'!G$5) -> 0.03610786 | H29: =AVERAGE($F$29:$G$29) -> 0.034268486 | I29: =AVERAGE($F$29:$G$29) -> 0.034268486 | J29: =AVERAGE($F$29:$G$29) -> 0.034268486 | K29: =AVERAGE($F$29:$G$29) -> 0.034268486 | L29: =AVERAGE($F$29:$G$29) -> 0.034268486 | M29: =AVERAGE($F$29:$G$29) -> 0.034268486 | N29: =AVERAGE($F$29:$G$29) -> 0.034268486 | O29: =AVERAGE($F$29:$G$29) -> 0.034268486 | ... Q29: =AVERAGE($F$29:$G$29) -> 0.034268486
B31: Customer deposits | C31: ='Balance Sheet Input'!C25 -> 925 | D31: ='Balance Sheet Input'!D25 -> 0 | E31: ='Balance Sheet Input'!E25 -> 0 | F31: ='Balance Sheet Input'!F25 -> 0 | G31: ='Balance Sheet Input'!G25 -> 0 | H31: =H32*('P&L'!H$5) -> 0 | I31: =I32*('P&L'!I$5) -> 0 | J31: =J32*('P&L'!J$5) -> 0 | K31: =K32*('P&L'!K$5) -> 0 | L31: =L32*('P&L'!L$5) -> 0 | M31: =M32*('P&L'!M$5) -> 0 | N31: =N32*('P&L'!N$5) -> 0 | O31: =O32*('P&L'!O$5) -> 0 | ... Q31: =Q32*('P&L'!Q$5) -> 0 | S31: Grows as a % of revenues
B32: as a % of revenues | C32: =C31/('P&L'!C$5) -> 0.017185961 | D32: =D31/('P&L'!D$5) -> 0 | E32: =E31/('P&L'!E$5) -> 0 | F32: =F31/('P&L'!F$5) -> 0 | G32: =G31/('P&L'!G$5) -> 0 | H32: =AVERAGE($F$32:$G$32) -> 0 | I32: =AVERAGE($F$32:$G$32) -> 0 | J32: =AVERAGE($F$32:$G$32) -> 0 | K32: =AVERAGE($F$32:$G$32) -> 0 | L32: =AVERAGE($F$32:$G$32) -> 0 | M32: =AVERAGE($F$32:$G$32) -> 0 | N32: =AVERAGE($F$32:$G$32) -> 0 | O32: =AVERAGE($F$32:$G$32) -> 0 | ... Q32: =AVERAGE($F$32:$G$32) -> 0
B34: Long-term debt | C34: =('Balance Sheet Input'!C26+'Balance Sheet Input'!C30) -> 6834 | D34: =('Balance Sheet Input'!D26+'Balance Sheet Input'!D30) -> 3099 | E34: =('Balance Sheet Input'!E26+'Balance Sheet Input'!E30) -> 5230 | F34: =('Balance Sheet Input'!F26+'Balance Sheet Input'!F30) -> 8213 | G34: =('Balance Sheet Input'!G26+'Balance Sheet Input'!G30) -> 8376 | H34: =G34+Financing!H19 -> 8376 | I34: =H34+Financing!I19 -> 8376 | J34: =I34+Financing!J19 -> 8376 | K34: =J34+Financing!K19 -> 8376 | L34: =K34+Financing!L19 -> 8376 | M34: =L34+Financing!M19 -> 8376 | N34: =M34+Financing!N19 -> 8376 | O34: =N34+Financing!O19 -> 8376 | ... Q34: =P34+Financing!Q19 -> 8376 | S34: Financing sheet
B35: Other liabilities | C35: =('Balance Sheet Input'!C31+'Balance Sheet Input'!C32) -> 5598 | D35: =('Balance Sheet Input'!D31+'Balance Sheet Input'!D32) -> 8134 | E35: =('Balance Sheet Input'!E31+'Balance Sheet Input'!E32) -> 11404 | F35: =('Balance Sheet Input'!F31+'Balance Sheet Input'!F32) -> 13812 | G35: =('Balance Sheet Input'!G31+'Balance Sheet Input'!G32) -> 16491 | H35: =H36*('P&L'!H$5) -> 19712.74 | I35: =I36*('P&L'!I$5) -> 22224.495 | J35: =J36*('P&L'!J$5) -> 25570.328 | K35: =K36*('P&L'!K$5) -> 28984.215 | L35: =L36*('P&L'!L$5) -> 33117.538 | M35: =M36*('P&L'!M$5) -> 36878.549 | N35: =N36*('P&L'!N$5) -> 40662.588 | O35: =O36*('P&L'!O$5) -> 44471.037 | ... Q35: =Q36*('P&L'!Q$5) -> 52167.112 | S35: Grows as a % of revenues
B36: as a % of revenues | C36: =C35/('P&L'!C$5) -> 0.10400758 | D36: =D35/('P&L'!D$5) -> 0.099850237 | E36: =E35/('P&L'!E$5) -> 0.11784279 | F36: =F35/('P&L'!F$5) -> 0.14138602 | G36: =G35/('P&L'!G$5) -> 0.17390617 | H36: =AVERAGE($F$36:$G$36) -> 0.15764609 | I36: =AVERAGE($F$36:$G$36) -> 0.15764609 | J36: =AVERAGE($F$36:$G$36) -> 0.15764609 | K36: =AVERAGE($F$36:$G$36) -> 0.15764609 | L36: =AVERAGE($F$36:$G$36) -> 0.15764609 | M36: =AVERAGE($F$36:$G$36) -> 0.15764609 | N36: =AVERAGE($F$36:$G$36) -> 0.15764609 | O36: =AVERAGE($F$36:$G$36) -> 0.15764609 | ... Q36: =AVERAGE($F$36:$G$36) -> 0.15764609
B38: Total liabilities | C38: =C24+C25+C28+C31+C34+C35 -> 30548 | D38: =D24+D25+D28+D31+D34+D35 -> 36440 | E38: =E24+E25+E28+E31+E34+E35 -> 43009 | F38: =F24+F25+F28+F31+F34+F35 -> 48390 | G38: =G24+G25+G28+G31+G34+G35 -> 54941 | H38: =H24+H25+H28+H31+H34+H35 -> 68973.619 | I38: =I24+I25+I28+I31+I34+I35 -> 76752.814 | J38: =J24+J25+J28+J31+J34+J35 -> 87096.424 | ... Q38: =Q24+Q25+Q28+Q31+Q34+Q35 -> 169236.91
B39: Redeemable noncontrolling interests in subsidiaries | C39: ='Balance Sheet Input'!C34 -> 568 | D39: ='Balance Sheet Input'!D34 -> 409 | E39: ='Balance Sheet Input'!E34 -> 242 | F39: ='Balance Sheet Input'!F34 -> 63 | G39: ='Balance Sheet Input'!G34 -> 58 | H39: =G39 -> 58 | I39: =H39 -> 58 | J39: =I39 -> 58 | K39: =J39 -> 58 | L39: =K39 -> 58 | M39: =L39 -> 58 | N39: =M39 -> 58 | O39: =N39 -> 58 | ... Q39: =P39 -> 58
B40: Equity | C40: =('Balance Sheet Input'!C36+'Balance Sheet Input'!C35) -> 31015 | D40: =('Balance Sheet Input'!D36+'Balance Sheet Input'!D35) -> 45489 | E40: =('Balance Sheet Input'!E36+'Balance Sheet Input'!E35) -> 63367 | F40: =('Balance Sheet Input'!F36+'Balance Sheet Input'!F35) -> 73617 | G40: =('Balance Sheet Input'!G36+'Balance Sheet Input'!G35) -> 82807 | H40: =G40+'P&L'!H14+Financing!H20 -> 86417.155 | I40: =H40+'P&L'!I14+Financing!I20 -> 90297.715 | J40: =I40+'P&L'!J14+Financing!J20 -> 94612.007 | K40: =J40+'P&L'!K14+Financing!K20 -> 99359.021 | L40: =K40+'P&L'!L14+Financing!L20 -> 104782.05 | M40: =L40+'P&L'!M14+Financing!M20 -> 110742.1 | N40: =M40+'P&L'!N14+Financing!N20 -> 117237.22 | O40: =N40+'P&L'!O14+Financing!O20 -> 124265.33 | ... Q40: =P40+'P&L'!Q14+Financing!Q20 -> 139911.55
B42: Total liabilities & equity | C42: =C38+C40+C39 -> 62131 | D42: =D38+D40+D39 -> 82338 | E42: =E38+E40+E39 -> 106618 | F42: =F38+F40+F39 -> 122070 | G42: =G38+G40+G39 -> 137806 | H42: =H38+H40+H39 -> 155448.77 | I42: =I38+I40+I39 -> 167108.53 | J42: =J38+J40+J39 -> 181766.43 | ... Q42: =Q38+Q40+Q39 -> 309206.46
B44: Check | C44: =C22-C42 -> 0 | D44: =D22-D42 -> 0 | E44: =E22-E42 -> 0 | F44: =F22-F42 -> 0 | G44: =G22-G42 -> 0 | H44: =H22-H42 -> 0 | I44: =I22-I42 -> 0 | J44: =J22-J42 -> 0 | ... Q44: =Q22-Q42 -> 0

Sheet Cash Flow
B1: Cash Flow
C3: Tesla Cash Flow (in mln $)
B4: ($ millions) | C4: 2021 Act | D4: 2022 Act | E4: 2023 Act | F4: 2024 Act | G4: 2025 Act | H4: 2026 Fcst | I4: 2027 Fcst | J4: 2028 Fcst | K4: 2029 Fcst | L4: 2030 Fcst | M4: 2031 Fcst | N4: 2032 Fcst | O4: 2033 Fcst | P4: 2034 Fcst | Q4: 2035 Fcst
B5: EBIT | D5: ='P&L'!D9 -> 13656 | E5: ='P&L'!E9 -> 8891 | F5: ='P&L'!F9 -> 7076 | G5: ='P&L'!G9 -> 4355 | H5: ='P&L'!H9 -> 4936.9285 | I5: ='P&L'!I9 -> 5279.2137 | J5: ='P&L'!J9 -> 5828.2411 | K5: ='P&L'!K9 -> 6375.9898 | ... Q5: ='P&L'!Q9 -> 10604.245
B6: =CONCATENATE("Operating taxes (",(Drivers!$C$12*100),"%)") -> Operating taxes (21%) | D6: ='P&L'!D12 -> -1132 | E6: ='P&L'!E12 -> 5001 | F6: ='P&L'!F12 -> -1837 | G6: ='P&L'!G12 -> -1423 | H6: =IF(H5*Drivers!$C$12>0,-H5*Drivers!$C$12,0) -> -1036.755 | I6: =IF(I5*Drivers!$C$12>0,-I5*Drivers!$C$12,0) -> -1108.6349 | J6: =IF(J5*Drivers!$C$12>0,-J5*Drivers!$C$12,0) -> -1223.9306 | K6: =IF(K5*Drivers!$C$12>0,-K5*Drivers!$C$12,0) -> -1338.9579 | L6: =IF(L5*Drivers!$C$12>0,-L5*Drivers!$C$12,0) -> -1518.6582 | M6: =IF(M5*Drivers!$C$12>0,-M5*Drivers!$C$12,0) -> -1661.4117 | N6: =IF(N5*Drivers!$C$12>0,-N5*Drivers!$C$12,0) -> -1803.644 | O6: =IF(O5*Drivers!$C$12>0,-O5*Drivers!$C$12,0) -> -1945.3238 | ... Q6: =IF(Q5*Drivers!$C$12>0,-Q5*Drivers!$C$12,0) -> -2226.8914
B7: NOPAT | D7: =SUM(D5:D6) -> 12524 | E7: =SUM(E5:E6) -> 13892 | F7: =SUM(F5:F6) -> 5239 | G7: =SUM(G5:G6) -> 2932 | H7: =SUM(H5:H6) -> 3900.1735 | I7: =SUM(I5:I6) -> 4170.5788 | J7: =SUM(J5:J6) -> 4604.3104 | K7: =SUM(K5:K6) -> 5037.0319 | ... Q7: =SUM(Q5:Q6) -> 8377.3534
B8: Add-back D&A | D8: =-'PP&E'!D9 -> 3747 | E8: =-'PP&E'!E9 -> 4667 | F8: =-'PP&E'!F9 -> 5368 | G8: =-'PP&E'!G9 -> 6148 | H8: =-'PP&E'!H9 -> 5202.304 | I8: =-'PP&E'!I9 -> 6513.2846 | J8: =-'PP&E'!J9 -> 8008.9678 | K8: =-'PP&E'!K9 -> 9699.1912 | ... Q8: =-'PP&E'!Q9 -> 24002.924
B9: Gross Cash Flow | D9: =SUM(D7:D8) -> 16271 | E9: =SUM(E7:E8) -> 18559 | F9: =SUM(F7:F8) -> 10607 | G9: =SUM(G7:G8) -> 9080 | H9: =SUM(H7:H8) -> 9102.4775 | I9: =SUM(I7:I8) -> 10683.863 | J9: =SUM(J7:J8) -> 12613.278 | K9: =SUM(K7:K8) -> 14736.223 | ... Q9: =SUM(Q7:Q8) -> 32380.277
B11: Trade receivables | D11: =-('Balance Sheet'!D6-'Balance Sheet'!C6) -> -1039 | E11: =-('Balance Sheet'!E6-'Balance Sheet'!D6) -> -556 | F11: =-('Balance Sheet'!F6-'Balance Sheet'!E6) -> -910 | G11: =-('Balance Sheet'!G6-'Balance Sheet'!F6) -> -158 | H11: =-('Balance Sheet'!H6-'Balance Sheet'!G6) -> -463.55783 | I11: =-('Balance Sheet'!I6-'Balance Sheet'!H6) -> -642.12972 | J11: =-('Balance Sheet'!J6-'Balance Sheet'!I6) -> -855.36135 | K11: =-('Balance Sheet'!K6-'Balance Sheet'!J6) -> -872.75942 | ... Q11: =-('Balance Sheet'!Q6-'Balance Sheet'!P6) -> -987.25571
B12: Inventory | D12: =-('Balance Sheet'!D7-'Balance Sheet'!C7) -> -7082 | E12: =-('Balance Sheet'!E7-'Balance Sheet'!D7) -> -787 | F12: =-('Balance Sheet'!F7-'Balance Sheet'!E7) -> 1609 | G12: =-('Balance Sheet'!G7-'Balance Sheet'!F7) -> -375 | H12: =-('Balance Sheet'!H7-'Balance Sheet'!G7) -> -4968.7775 | I12: =-('Balance Sheet'!I7-'Balance Sheet'!H7) -> -2260.0436 | J12: =-('Balance Sheet'!J7-'Balance Sheet'!I7) -> -2994.9646 | K12: =-('Balance Sheet'!K7-'Balance Sheet'!J7) -> -3057.9642 | ... Q12: =-('Balance Sheet'!Q7-'Balance Sheet'!P7) -> -3450.8857
B13: Accounts payable | D13: =('Balance Sheet'!D24-'Balance Sheet'!C24) -> 5230 | E13: =('Balance Sheet'!E24-'Balance Sheet'!D24) -> -824 | F13: =('Balance Sheet'!F24-'Balance Sheet'!E24) -> -1957 | G13: =('Balance Sheet'!G24-'Balance Sheet'!F24) -> 897 | H13: ='Balance Sheet'!H24-'Balance Sheet'!G24 -> 7610.8009 | I13: ='Balance Sheet'!I24-'Balance Sheet'!H24 -> 2731.4321 | J13: ='Balance Sheet'!J24-'Balance Sheet'!I24 -> 3619.6392 | K13: ='Balance Sheet'!K24-'Balance Sheet'!J24 -> 3695.779 | L13: ='Balance Sheet'!L24-'Balance Sheet'!K24 -> 4435.6957 | M13: ='Balance Sheet'!M24-'Balance Sheet'!L24 -> 4056.1338 | N13: ='Balance Sheet'!N24-'Balance Sheet'!M24 -> 4082.3122 | O13: ='Balance Sheet'!O24-'Balance Sheet'!N24 -> 4110.0612 | ... Q13: ='Balance Sheet'!Q24-'Balance Sheet'!P24 -> 4170.6541
B14: Investments in Working Capital | D14: =SUM(D11:D13) -> -2891 | E14: =SUM(E11:E13) -> -2167 | F14: =SUM(F11:F13) -> -1258 | G14: =SUM(G11:G13) -> 364 | H14: =SUM(H11:H13) -> 2178.4656 | I14: =SUM(I11:I13) -> -170.74122 | J14: =SUM(J11:J13) -> -230.68674 | K14: =SUM(K11:K13) -> -234.94467 | ... Q14: =SUM(Q11:Q13) -> -267.48736
B16: Capex | D16: =-'PP&E'!D8 -> -8411 | E16: =-'PP&E'!E8 -> -10844 | F16: =-'PP&E'!F8 -> -11479 | G16: =-'PP&E'!G8 -> -10955 | H16: =-'PP&E'!H8 -> -11380.04 | I16: =-'PP&E'!I8 -> -13109.806 | J16: =-'PP&E'!J8 -> -14956.832 | K16: =-'PP&E'!K8 -> -16902.234 | ... Q16: =-'PP&E'!Q8 -> -28368.401
B17: Other assets | D17: =-('Balance Sheet'!D10-'Balance Sheet'!C10)-('Balance Sheet'!D13-'Balance Sheet'!C13)-('Balance Sheet'!D14-'Balance Sheet'!C14)-('Balance Sheet'!D16-'Balance Sheet'!C16)-('Balance Sheet'!D17-'Balance Sheet'!C17)-('Balance Sheet'!D18-'Balance Sheet'!C18)-('Balance Sheet'!D19-'Balance Sheet'!C19)-('Balance Sheet'!D20-'Balance Sheet'!C20)-('Balance Sheet'!D8-'Balance Sheet'!C8) -> -8745 | E17: =-('Balance Sheet'!E10-'Balance Sheet'!D10)-('Balance Sheet'!E13-'Balance Sheet'!D13)-('Balance Sheet'!E14-'Balance Sheet'!D14)-('Balance Sheet'!E16-'Balance Sheet'!D16)-('Balance Sheet'!E17-'Balance Sheet'!D17)-('Balance Sheet'!E18-'Balance Sheet'!D18)-('Balance Sheet'!E19-'Balance Sheet'!D19)-('Balance Sheet'!E20-'Balance Sheet'!D20)-('Balance Sheet'!E8-'Balance Sheet'!D8) -> -16615 | F17: =-('Balance Sheet'!F10-'Balance Sheet'!E10)-('Balance Sheet'!F13-'Balance Sheet'!E13)-('Balance Sheet'!F14-'Balance Sheet'!E14)-('Balance Sheet'!F16-'Balance Sheet'!E16)-('Balance Sheet'!F17-'Balance Sheet'!E17)-('Balance Sheet'!F18-'Balance Sheet'!E18)-('Balance Sheet'!F19-'Balance Sheet'!E19)-('Balance Sheet'!F20-'Balance Sheet'!E20)-('Balance Sheet'!F8-'Balance Sheet'!E8) -> -10299 | G17: =-('Balance Sheet'!G10-'Balance Sheet'!F10)-('Balance Sheet'!G13-'Balance Sheet'!F13)-('Balance Sheet'!G14-'Balance Sheet'!F14)-('Balance Sheet'!G16-'Balance Sheet'!F16)-('Balance Sheet'!G17-'Balance Sheet'!F17)-('Balance Sheet'!G18-'Balance Sheet'!F18)-('Balance Sheet'!G19-'Balance Sheet'!F19)-('Balance Sheet'!G20-'Balance Sheet'!F20)-('Balance Sheet'!G8-'Balance Sheet'!F8) -> -10022 | H17: =-('Balance Sheet'!H10-'Balance Sheet'!G10)-('Balance Sheet'!H13-'Balance Sheet'!G13)-('Balance Sheet'!H14-'Balance Sheet'!G14)-('Balance Sheet'!H16-'Balance Sheet'!G16)-('Balance Sheet'!H17-'Balance Sheet'!G17)-('Balance Sheet'!H18-'Balance Sheet'!G18)-('Balance Sheet'!H19-'Balance Sheet'!G19)-('Balance Sheet'!H20-'Balance Sheet'!G20)-('Balance Sheet'!H8-'Balance Sheet'!G8) -> -2068.592 | I17: =-('Balance Sheet'!I10-'Balance Sheet'!H10)-('Balance Sheet'!I13-'Balance Sheet'!H13)-('Balance Sheet'!I14-'Balance Sheet'!H14)-('Balance Sheet'!I16-'Balance Sheet'!H16)-('Balance Sheet'!I17-'Balance Sheet'!H17)-('Balance Sheet'!I18-'Balance Sheet'!H18)-('Balance Sheet'!I19-'Balance Sheet'!H19)-('Balance Sheet'!I20-'Balance Sheet'!H20)-('Balance Sheet'!I8-'Balance Sheet'!H8) -> -1876.6858 | J17: =-('Balance Sheet'!J10-'Balance Sheet'!I10)-('Balance Sheet'!J13-'Balance Sheet'!I13)-('Balance Sheet'!J14-'Balance Sheet'!I14)-('Balance Sheet'!J16-'Balance Sheet'!I16)-('Balance Sheet'!J17-'Balance Sheet'!I17)-('Balance Sheet'!J18-'Balance Sheet'!I18)-('Balance Sheet'!J19-'Balance Sheet'!I19)-('Balance Sheet'!J20-'Balance Sheet'!I20)-('Balance Sheet'!J8-'Balance Sheet'!I8) -> -2499.8757 | K17: =-('Balance Sheet'!K10-'Balance Sheet'!J10)-('Balance Sheet'!K13-'Balance Sheet'!J13)-('Balance Sheet'!K14-'Balance Sheet'!J14)-('Balance Sheet'!K16-'Balance Sheet'!J16)-('Balance Sheet'!K17-'Balance Sheet'!J17)-('Balance Sheet'!K18-'Balance Sheet'!J18)-('Balance Sheet'!K19-'Balance Sheet'!J19)-('Balance Sheet'!K20-'Balance Sheet'!J20)-('Balance Sheet'!K8-'Balance Sheet'!J8) -> -2550.7233 | ... Q17: =-('Balance Sheet'!Q10-'Balance Sheet'!P10)-('Balance Sheet'!Q13-'Balance Sheet'!P13)-('Balance Sheet'!Q14-'Balance Sheet'!P14)-('Balance Sheet'!Q16-'Balance Sheet'!P16)-('Balance Sheet'!Q17-'Balance Sheet'!P17)-('Balance Sheet'!Q18-'Balance Sheet'!P18)-('Balance Sheet'!Q19-'Balance Sheet'!P19)-('Balance Sheet'!Q20-'Balance Sheet'!P20)-('Balance Sheet'!Q8-'Balance Sheet'!P8) -> -2885.3497
B18: Other liabilties | D18: =('Balance Sheet'!D25-'Balance Sheet'!C25)+('Balance Sheet'!D28-'Balance Sheet'!C28)+('Balance Sheet'!D31-'Balance Sheet'!C31)+('Balance Sheet'!D35-'Balance Sheet'!C35) -> 4397 | E18: =('Balance Sheet'!E25-'Balance Sheet'!D25)+('Balance Sheet'!E28-'Balance Sheet'!D28)+('Balance Sheet'!E31-'Balance Sheet'!D31)+('Balance Sheet'!E35-'Balance Sheet'!D35) -> 5262 | F18: =('Balance Sheet'!F25-'Balance Sheet'!E25)+('Balance Sheet'!F28-'Balance Sheet'!E28)+('Balance Sheet'!F31-'Balance Sheet'!E31)+('Balance Sheet'!F35-'Balance Sheet'!E35) -> 4355 | G18: =('Balance Sheet'!G25-'Balance Sheet'!F25)+('Balance Sheet'!G28-'Balance Sheet'!F28)+('Balance Sheet'!G31-'Balance Sheet'!F31)+('Balance Sheet'!G35-'Balance Sheet'!F35) -> 5491 | H18: =('Balance Sheet'!H25-'Balance Sheet'!G25)+('Balance Sheet'!H28-'Balance Sheet'!G28)+('Balance Sheet'!H31-'Balance Sheet'!G31)+('Balance Sheet'!H35-'Balance Sheet'!G35) -> 6421.8181 | I18: =('Balance Sheet'!I25-'Balance Sheet'!H25)+('Balance Sheet'!I28-'Balance Sheet'!H28)+('Balance Sheet'!I31-'Balance Sheet'!H31)+('Balance Sheet'!I35-'Balance Sheet'!H35) -> 5047.7631 | J18: =('Balance Sheet'!J25-'Balance Sheet'!I25)+('Balance Sheet'!J28-'Balance Sheet'!I28)+('Balance Sheet'!J31-'Balance Sheet'!I31)+('Balance Sheet'!J35-'Balance Sheet'!I35) -> 6723.9708 | K18: =('Balance Sheet'!K25-'Balance Sheet'!J25)+('Balance Sheet'!K28-'Balance Sheet'!J28)+('Balance Sheet'!K31-'Balance Sheet'!J31)+('Balance Sheet'!K35-'Balance Sheet'!J35) -> 6860.7365 | ... Q18: =('Balance Sheet'!Q25-'Balance Sheet'!P25)+('Balance Sheet'!Q28-'Balance Sheet'!P28)+('Balance Sheet'!Q31-'Balance Sheet'!P31)+('Balance Sheet'!Q35-'Balance Sheet'!P35) -> 7760.7885
B20: Unlevered Free Cash Flow | D20: =D9+D14+D17+D18+D16 -> 621 | E20: =E9+E14+E17+E18+E16 -> -5805 | F20: =F9+F14+F17+F18+F16 -> -8074 | G20: =G9+G14+G17+G18+G16 -> -6042 | H20: =H9+H14+H17+H18+H16 -> 4254.1293 | I20: =I9+I14+I17+I18+I16 -> 574.39342 | J20: =J9+J14+J17+J18+J16 -> 1649.8545 | K20: =K9+K14+K17+K18+K16 -> 1909.0577 | ... Q20: =Q9+Q14+Q17+Q18+Q16 -> 8619.8276
B22: Interest expenses | D22: ='P&L'!D10 -> 63 | E22: ='P&L'!E10 -> 1082 | F22: ='P&L'!F10 -> 1914 | G22: ='P&L'!G10 -> 923 | H22: ='P&L'!H10 -> -367.112 | I22: ='P&L'!I10 -> -367.112 | J22: ='P&L'!J10 -> -367.112 | K22: ='P&L'!K10 -> -367.112 | ... Q22: ='P&L'!Q10 -> -367.112
B23: Delta Financial liabilities | D23: ='Balance Sheet'!D34-'Balance Sheet'!C34 -> -3735 | E23: ='Balance Sheet'!E34-'Balance Sheet'!D34 -> 2131 | F23: ='Balance Sheet'!F34-'Balance Sheet'!E34 -> 2983 | G23: ='Balance Sheet'!G34-'Balance Sheet'!F34 -> 163 | H23: ='Balance Sheet'!H34-'Balance Sheet'!G34 -> 0 | I23: ='Balance Sheet'!I34-'Balance Sheet'!H34 -> 0 | J23: ='Balance Sheet'!J34-'Balance Sheet'!I34 -> 0 | K23: ='Balance Sheet'!K34-'Balance Sheet'!J34 -> 0 | ... Q23: ='Balance Sheet'!Q34-'Balance Sheet'!P34 -> 0
B24: Delta equity/Other equity movements | D24: ='Balance Sheet'!D40-'Balance Sheet'!C40-'P&L'!D14 -> 1918 | E24: ='Balance Sheet'!E40-'Balance Sheet'!D40-'P&L'!E14 -> 2881 | F24: ='Balance Sheet'!F40-'Balance Sheet'!E40-'P&L'!F14 -> 3159 | G24: ='Balance Sheet'!G40-'Balance Sheet'!F40-'P&L'!G14 -> 5396 | H24: ='Balance Sheet'!H40-'Balance Sheet'!G40-'P&L'!H14 -> -7.2759576e-12 | I24: ='Balance Sheet'!I40-'Balance Sheet'!H40-'P&L'!I14 -> -4.5474735e-12 | J24: ='Balance Sheet'!J40-'Balance Sheet'!I40-'P&L'!J14 -> 0 | K24: ='Balance Sheet'!K40-'Balance Sheet'!J40-'P&L'!K14 -> 0 | ... Q24: ='Balance Sheet'!Q40-'Balance Sheet'!P40-'P&L'!Q14 -> -1.3642421e-11
B25: Tax adjustment | D25: ='P&L'!D12-D6 -> 0 | E25: ='P&L'!E12-E6 -> 0 | F25: ='P&L'!F12-F6 -> 0 | G25: ='P&L'!G12-G6 -> 0 | H25: ='P&L'!H12-H6 -> 77.09352 | I25: ='P&L'!I12-I6 -> 77.09352 | J25: ='P&L'!J12-J6 -> 77.09352 | K25: ='P&L'!K12-K6 -> 77.09352 | ... Q25: ='P&L'!Q12-Q6 -> 77.09352
B26: noncontrolling interests in subsidiaries | D26: ='Balance Sheet'!D39-'Balance Sheet'!C39 -> -159 | E26: ='Balance Sheet'!E39-'Balance Sheet'!D39 -> -167 | F26: ='Balance Sheet'!F39-'Balance Sheet'!E39 -> -179 | G26: ='Balance Sheet'!G39-'Balance Sheet'!F39 -> -5 | H26: ='Balance Sheet'!H39-'Balance Sheet'!G39 -> 0 | I26: ='Balance Sheet'!I39-'Balance Sheet'!H39 -> 0 | J26: ='Balance Sheet'!J39-'Balance Sheet'!I39 -> 0 | K26: ='Balance Sheet'!K39-'Balance Sheet'!J39 -> 0 | ... Q26: ='Balance Sheet'!Q39-'Balance Sheet'!P39 -> 0
B27: Minority interest | D27: ='P&L'!D13 -> -31 | E27: ='P&L'!E13 -> 23 | F27: ='P&L'!F13 -> -62 | G27: ='P&L'!G13 -> -61 | H27: ='P&L'!H13 -> 0 | I27: ='P&L'!I13 -> 0 | J27: ='P&L'!J13 -> 0 | K27: ='P&L'!K13 -> 0 | ... Q27: ='P&L'!Q13 -> 0
B29: Net Cash Flow | D29: =SUM(D20:D28) -> -1323 | E29: =SUM(E20:E28) -> 145 | F29: =SUM(F20:F28) -> -259 | G29: =SUM(G20:G28) -> 374 | H29: =SUM(H20:H28) -> 3964.1108 | I29: =SUM(I20:I28) -> 284.37494 | J29: =SUM(J20:J28) -> 1359.836 | K29: =SUM(K20:K28) -> 1619.0392 | ... Q29: =SUM(Q20:Q28) -> 8329.8091
B31: Opening cash | D31: =C33 -> 17576 | E31: =D33 -> 16253 | F31: =E33 -> 16398 | G31: =F33 -> 16139 | H31: =G33 -> 16513 | I31: =H33 -> 20477.111 | J31: =I33 -> 20761.486 | K31: =J33 -> 22121.322 | ... Q31: =P33 -> 45505.13
B32: Net Cash Flow | C32: =C29 -> 0 | D32: =D29 -> -1323 | E32: =E29 -> 145 | F32: =F29 -> -259 | G32: =G29 -> 374 | H32: =H29 -> 3964.1108 | I32: =I29 -> 284.37494 | J32: =J29 -> 1359.836 | ... Q32: =Q29 -> 8329.8091
B33: Closing cash | C33: ='Balance Sheet'!C5 -> 17576 | D33: =D31+D32 -> 16253 | E33: =E31+E32 -> 16398 | F33: =F31+F32 -> 16139 | G33: =G31+G32 -> 16513 | H33: =H31+H32 -> 20477.111 | I33: =I31+I32 -> 20761.486 | J33: =J31+J32 -> 22121.322 | K33: =K31+K32 -> 23740.361 | ... Q33: =Q31+Q32 -> 53834.939
B35: Check | C35: ='Balance Sheet'!C5-C33 -> 0 | D35: ='Balance Sheet'!D5-D33 -> 0 | E35: ='Balance Sheet'!E5-E33 -> 0 | F35: ='Balance Sheet'!F5-F33 -> 0 | G35: ='Balance Sheet'!G5-G33 -> 0 | H35: ='Balance Sheet'!H5-H33 -> 0 | I35: ='Balance Sheet'!I5-I33 -> 0 | J35: ='Balance Sheet'!J5-J33 -> 0 | ... Q35: ='Balance Sheet'!Q5-Q33 -> 0

Sheet WACC
B3: Weighted Average Cost of Capital
B5: ($ millions) | C5: 2021 Act | D5: 2022 Act | E5: 2023 Act | F5: 2024 Act | G5: 2025 Act
B7: Long-term debt | C7: ='Balance Sheet'!C34 -> 6834 | D7: ='Balance Sheet'!D34 -> 3099 | E7: ='Balance Sheet'!E34 -> 5230 | F7: ='Balance Sheet'!F34 -> 8213 | G7: ='Balance Sheet'!G34 -> 8376
B8: Equity | C8: ='Balance Sheet'!C40 -> 31015 | D8: ='Balance Sheet'!D40 -> 45489 | E8: ='Balance Sheet'!E40 -> 63367 | F8: ='Balance Sheet'!F40 -> 73617 | G8: ='Balance Sheet'!G40 -> 82807
B10: Long-term debt weight | C10: =C7/SUM($C$7:$C$8) -> 0.18055959 | D10: =D7/SUM(D7:D8) -> 0.063781181 | E10: =E7/SUM(E7:E8) -> 0.076242401 | F10: =F7/SUM(F7:F8) -> 0.10036661 | G10: =G7/SUM(G7:G8) -> 0.091859228
B11: Equity weight | C11: =C8/SUM(C$7:C$8) -> 0.81944041 | D11: =D8/SUM(D$7:D$8) -> 0.93621882 | E11: =E8/SUM(E$7:E$8) -> 0.9237576 | F11: =F8/SUM(F$7:F$8) -> 0.89963339 | G11: =G8/SUM(G$7:G$8) -> 0.90814077
B13: D/E ratio | C13: =C10/C11 -> 0.22034499 | D13: =D10/D11 -> 0.06812636 | E13: =E10/E11 -> 0.082535073 | F13: =F10/F11 -> 0.11156391 | G13: =G10/G11 -> 0.10115087
B15: unlevered beta | C15: =$N$22/(1+(1-$E$22)*C13) -> 1.0050486 | D15: =$N$22/(1+(1-$E$22)*D13) -> 1.119736 | E15: =$N$22/(1+(1-$E$22)*E13) -> 1.1077704 | F15: =$N$22/(1+(1-$E$22)*F13) -> 1.0844238 | G15: =$N$22/(1+(1-$E$22)*G13) -> 1.0926845
B19: Cost of Debt | I19: Cost of Equity
B21: Pre Tax Cost of Debt | E21: =Drivers!C11 -> 0.0545 | I21: Risk Free Rate | N21: =Drivers!C7 -> 0.0455
B22: Tax | E22: =Drivers!C12 -> 0.21 | I22: Beta( 08.06.2026) | N22: =Drivers!C9 -> 1.18
B23: Post Tax Cost of Debt | E23: =E21*(1-E22) -> 0.043055 | I23: Market risk premium | N23: =Drivers!C8 -> 0.055
I24: Levered Beta 4 | N24: =N32 -> 1.1913358
I25: Cost of Equity | N25: =N21+(N23*N24) -> 0.11102347
B27: Capital Structure
I28: Levered Beta
D29: Current | E29: Target | I29: Unlevered Beta | N29: =G15 -> 1.0926845
B30: Total Debt | C30: =G7 -> 8376 | D30: =C30/C32 -> 0.091859228 | E30: =AVERAGE(C10:G10) -> 0.1025618 | I30: Target Debt/Equity | N30: =E34 -> 0.11428286
B31: Market Capitalization | C31: =G8 -> 82807 | D31: =C31/C32 -> 0.90814077 | E31: =E32-E30 -> 0.8974382 | I31: Tax Rate | N31: =E22 -> 0.21
B32: Total Capital | C32: =C31+C30 -> 91183 | D32: =SUM(D30:D31) -> 1 | E32: =D32 -> 1 | I32: Levered Beta | N32: =N29*(1+(1-N31)*N30) -> 1.1913358
B34: Debt/Equity | D34: =D30/D31 -> 0.10115087 | E34: =E30/E31 -> 0.11428286 | I34: Weighted Average Cost of Capital
M35: Total Cost | N35: Total Weight
I36: Debt | M36: =E23 -> 0.043055 | N36: =E30 -> 0.1025618
I37: Equity | M37: =N25 -> 0.11102347 | N37: =E31 -> 0.8974382
I38: WACC | N38: =SUMPRODUCT(M36:M37,N36:N37) -> 0.1040525

Sheet DCF Valuation
B3: Calculation of ROIC
B4: ($ millions) | F4: 2024 Act | G4: 2025 Act | H4: 2026 Fcst | I4: 2027 Fcst | J4: 2028 Fcst | K4: 2029 Fcst | L4: 2030 Fcst | M4: 2031 Fcst | N4: 2032 Fcst | O4: 2033 Fcst | P4: 2034 Fcst | Q4: 2035 Fcst
B6: Current Assets
B7: Inventories | C7: ='Balance Sheet'!C7 -> 5757 | D7: ='Balance Sheet'!D7 -> 12839 | E7: ='Balance Sheet'!E7 -> 13626 | F7: ='Balance Sheet'!F7 -> 12017 | G7: ='Balance Sheet'!G7 -> 12392 | H7: ='Balance Sheet'!H7 -> 17360.777 | I7: ='Balance Sheet'!I7 -> 19620.821 | J7: ='Balance Sheet'!J7 -> 22615.786 | ... Q7: ='Balance Sheet'!Q7 -> 46354.579
B8: Trade receivables | C8: ='Balance Sheet'!C6 -> 1913 | D8: ='Balance Sheet'!D6 -> 2952 | E8: ='Balance Sheet'!E6 -> 3508 | F8: ='Balance Sheet'!F6 -> 4418 | G8: ='Balance Sheet'!G6 -> 4576 | H8: ='Balance Sheet'!H6 -> 5039.5578 | I8: ='Balance Sheet'!I6 -> 5681.6876 | J8: ='Balance Sheet'!J6 -> 6537.0489 | ... Q8: ='Balance Sheet'!Q6 -> 13336.511
B9: Prepaid Expenses | C9: ='Balance Sheet'!C10 -> 1723 | D9: ='Balance Sheet'!D10 -> 2941 | E9: ='Balance Sheet'!E10 -> 3388 | F9: ='Balance Sheet'!F10 -> 5362 | G9: ='Balance Sheet'!G10 -> 7615 | H9: ='Balance Sheet'!H10 -> 8452.495 | I9: ='Balance Sheet'!I10 -> 9529.4939 | J9: ='Balance Sheet'!J10 -> 10964.131 | ... Q9: ='Balance Sheet'!Q10 -> 22368.39
B10: Short-term investments | C10: ='Balance Sheet'!C8 -> 131 | D10: ='Balance Sheet'!D8 -> 5932 | E10: ='Balance Sheet'!E8 -> 12696 | F10: ='Balance Sheet'!F8 -> 20424 | G10: ='Balance Sheet'!G8 -> 27546 | H10: ='Balance Sheet'!H8 -> 27546 | I10: ='Balance Sheet'!I8 -> 27546 | J10: ='Balance Sheet'!J8 -> 27546 | ... Q10: ='Balance Sheet'!Q8 -> 27546
B11: Total Current Assets | C11: =SUM(C7:C10) -> 9524 | D11: =SUM(D7:D10) -> 24664 | E11: =SUM(E7:E10) -> 33218 | F11: =SUM(F7:F10) -> 42221 | G11: =SUM(G7:G10) -> 52129 | H11: =SUM(H7:H10) -> 58398.83 | I11: =SUM(I7:I10) -> 62378.003 | J11: =SUM(J7:J10) -> 67662.966 | ... Q11: =SUM(Q7:Q10) -> 109605.48
B13: Current Liabilities
B14: Accounts payable | C14: ='Balance Sheet'!C24 -> 10025 | D14: ='Balance Sheet'!D24 -> 15255 | E14: ='Balance Sheet'!E24 -> 14431 | F14: ='Balance Sheet'!F24 -> 12474 | G14: ='Balance Sheet'!G24 -> 13371 | H14: ='Balance Sheet'!H24 -> 20981.801 | I14: ='Balance Sheet'!I24 -> 23713.233 | J14: ='Balance Sheet'!J24 -> 27332.872 | ... Q14: ='Balance Sheet'!Q24 -> 56022.983
B15: Accrued liabilities | C15: ='Balance Sheet'!C25 -> 5719 | D15: ='Balance Sheet'!D25 -> 8205 | E15: ='Balance Sheet'!E25 -> 9080 | F15: ='Balance Sheet'!F25 -> 10723 | G15: ='Balance Sheet'!G25 -> 13279 | H15: ='Balance Sheet'!H25 -> 15618 | I15: ='Balance Sheet'!I25 -> 17608.013 | J15: ='Balance Sheet'!J25 -> 20258.847 | ... Q15: ='Balance Sheet'!Q25 -> 41330.934
B16: Deferred revenue | C16: ='Balance Sheet'!C28 -> 1447 | D16: ='Balance Sheet'!D28 -> 1747 | E16: ='Balance Sheet'!E28 -> 2864 | F16: ='Balance Sheet'!F28 -> 3168 | G16: ='Balance Sheet'!G28 -> 3424 | H16: ='Balance Sheet'!H28 -> 4285.0777 | I16: ='Balance Sheet'!I28 -> 4831.0732 | J16: ='Balance Sheet'!J28 -> 5558.3771 | ... Q16: ='Balance Sheet'!Q28 -> 11339.881
B17: Customer deposits | C17: ='Balance Sheet'!C31 -> 925 | D17: ='Balance Sheet'!D31 -> 0 | E17: ='Balance Sheet'!E31 -> 0 | F17: ='Balance Sheet'!F31 -> 0 | G17: ='Balance Sheet'!G31 -> 0 | H17: ='Balance Sheet'!H31 -> 0 | I17: ='Balance Sheet'!I31 -> 0 | J17: ='Balance Sheet'!J31 -> 0 | ... Q17: ='Balance Sheet'!Q31 -> 0
B18: Total Current Liabilities | C18: =SUM(C14:C17) -> 18116 | D18: =SUM(D14:D17) -> 25207 | E18: =SUM(E14:E17) -> 26375 | F18: =SUM(F14:F17) -> 26365 | G18: =SUM(G14:G17) -> 30074 | H18: =SUM(H14:H17) -> 40884.879 | I18: =SUM(I14:I17) -> 46152.319 | J18: =SUM(J14:J17) -> 53150.097 | ... Q18: =SUM(Q14:Q17) -> 108693.8
B20: Net Working Capital | C20: =C11-C18 -> -8592 | D20: =D11-D18 -> -543 | E20: =E11-E18 -> 6843 | F20: =F11-F18 -> 15856 | G20: =G11-G18 -> 22055 | H20: =H11-H18 -> 17513.951 | I20: =I11-I18 -> 16225.684 | J20: =J11-J18 -> 14512.869 | ... Q20: =Q11-Q18 -> 911.68086
B22: NON Current Assets
B23: Operating lease vehicles | C23: ='Balance Sheet'!C13 -> 6527 | D23: ='Balance Sheet'!D13 -> 7598 | E23: ='Balance Sheet'!E13 -> 10169 | F23: ='Balance Sheet'!F13 -> 10741 | G23: ='Balance Sheet'!G13 -> 10939 | H23: ='Balance Sheet'!H13 -> 10939 | I23: ='Balance Sheet'!I13 -> 10939 | J23: ='Balance Sheet'!J13 -> 10939 | ... Q23: ='Balance Sheet'!Q13 -> 10939
B24: Solar energy systems leased | C24: ='Balance Sheet'!C14 -> 5765 | D24: ='Balance Sheet'!D14 -> 5489 | E24: ='Balance Sheet'!E14 -> 5229 | F24: ='Balance Sheet'!F14 -> 4924 | G24: ='Balance Sheet'!G14 -> 4604 | H24: ='Balance Sheet'!H14 -> 4604 | I24: ='Balance Sheet'!I14 -> 4604 | J24: ='Balance Sheet'!J14 -> 4604 | ... Q24: ='Balance Sheet'!Q14 -> 4604
B25: PP&E | C25: ='Balance Sheet'!C15 -> 18884 | D25: ='Balance Sheet'!D15 -> 23548 | E25: ='Balance Sheet'!E15 -> 29725 | F25: ='Balance Sheet'!F15 -> 35836 | G25: ='Balance Sheet'!G15 -> 40643 | H25: ='Balance Sheet'!H15 -> 46820.736 | I25: ='Balance Sheet'!I15 -> 53417.257 | J25: ='Balance Sheet'!J15 -> 60365.122 | ... Q25: ='Balance Sheet'!Q15 -> 105681.2
B26: Intangible assets | C26: ='Balance Sheet'!C16 -> 257 | D26: ='Balance Sheet'!D16 -> 215 | E26: ='Balance Sheet'!E16 -> 178 | F26: ='Balance Sheet'!F16 -> 1076 | G26: ='Balance Sheet'!G16 -> 1008 | H26: ='Balance Sheet'!H16 -> 1008 | I26: ='Balance Sheet'!I16 -> 1008 | J26: ='Balance Sheet'!J16 -> 1008 | ... Q26: ='Balance Sheet'!Q16 -> 1008
B27: Deferred tax assets | C27: ='Balance Sheet'!C17 -> 0 | D27: ='Balance Sheet'!D17 -> 328 | E27: ='Balance Sheet'!E17 -> 6733 | F27: ='Balance Sheet'!F17 -> 6524 | G27: ='Balance Sheet'!G17 -> 6925 | H27: ='Balance Sheet'!H17 -> 6925 | I27: ='Balance Sheet'!I17 -> 6925 | J27: ='Balance Sheet'!J17 -> 6925 | ... Q27: ='Balance Sheet'!Q17 -> 6925
B28: Good will | C28: ='Balance Sheet'!C18 -> 200 | D28: ='Balance Sheet'!D18 -> 194 | E28: ='Balance Sheet'!E18 -> 253 | F28: ='Balance Sheet'!F18 -> 0 | G28: ='Balance Sheet'!G18 -> 0 | H28: ='Balance Sheet'!H18 -> 0 | I28: ='Balance Sheet'!I18 -> 0 | J28: ='Balance Sheet'!J18 -> 0 | ... Q28: ='Balance Sheet'!Q18 -> 0
B29: Digital assets,net | C29: ='Balance Sheet'!C19 -> 1260 | D29: ='Balance Sheet'!D19 -> 184 | E29: ='Balance Sheet'!E19 -> 184 | F29: ='Balance Sheet'!F19 -> 0 | G29: ='Balance Sheet'!G19 -> 0 | H29: ='Balance Sheet'!H19 -> 0 | I29: ='Balance Sheet'!I19 -> 0 | J29: ='Balance Sheet'!J19 -> 0 | ... Q29: ='Balance Sheet'!Q19 -> 0
B30: Other assets | C30: ='Balance Sheet'!C20 -> 2138 | D30: ='Balance Sheet'!D20 -> 3865 | E30: ='Balance Sheet'!E20 -> 4531 | F30: ='Balance Sheet'!F20 -> 4609 | G30: ='Balance Sheet'!G20 -> 5045 | H30: ='Balance Sheet'!H20 -> 6276.0969 | I30: ='Balance Sheet'!I20 -> 7075.7838 | J30: ='Balance Sheet'!J20 -> 8141.0223 | ... Q30: ='Balance Sheet'!Q20 -> 16608.845
B31: Gross Block | C31: =SUM(C23:C30) -> 35031 | D31: =SUM(D23:D30) -> 41421 | E31: =SUM(E23:E30) -> 57002 | F31: =SUM(F23:F30) -> 63710 | G31: =SUM(G23:G30) -> 69164 | H31: =SUM(H23:H30) -> 76572.833 | I31: =SUM(I23:I30) -> 83969.041 | J31: =SUM(J23:J30) -> 91982.144 | ... Q31: =SUM(Q23:Q30) -> 145766.04
B32: Accumulated Depreciation | C32: =-'Cash Flow'!C8 -> 0 | D32: =-'Cash Flow'!D8 -> -3747 | E32: =-'Cash Flow'!E8 -> -4667 | F32: =-'Cash Flow'!F8 -> -5368 | G32: =-'Cash Flow'!G8 -> -6148 | H32: =-'Cash Flow'!H8 -> -5202.304 | I32: =-'Cash Flow'!I8 -> -6513.2846 | J32: =-'Cash Flow'!J8 -> -8008.9678 | ... Q32: =-'Cash Flow'!Q8 -> -24002.924
B33: NET Non Current Assets | C33: =C31+C32 -> 35031 | D33: =D31+D32 -> 37674 | E33: =E31+E32 -> 52335 | F33: =F31+F32 -> 58342 | G33: =G31+G32 -> 63016 | H33: =H31+H32 -> 71370.529 | I33: =I31+I32 -> 77455.757 | J33: =J31+J32 -> 83973.176 | ... Q33: =Q31+Q32 -> 121763.12
B35: Invested Capital | C35: =C33+C20 -> 26439 | D35: =D33+D20 -> 37131 | E35: =E33+E20 -> 59178 | F35: =F33+F20 -> 74198 | G35: =G33+G20 -> 85071 | H35: =H33+H20 -> 88884.48 | I35: =I33+I20 -> 93681.44 | J35: =J33+J20 -> 98486.046 | ... Q35: =Q33+Q20 -> 122674.8
B36: NOPAT | C36: ='Cash Flow'!C7 -> 0 | D36: ='Cash Flow'!D7 -> 12524 | E36: ='Cash Flow'!E7 -> 13892 | F36: ='Cash Flow'!F7 -> 5239 | G36: ='Cash Flow'!G7 -> 2932 | H36: ='Cash Flow'!H7 -> 3900.1735 | I36: ='Cash Flow'!I7 -> 4170.5788 | J36: ='Cash Flow'!J7 -> 4604.3104 | ... Q36: ='Cash Flow'!Q7 -> 8377.3534
B38: ROIC | C38: =C36/C35 -> 0 | D38: =D36/D35 -> 0.33729229 | E38: =E36/E35 -> 0.2347494 | F38: =F36/F35 -> 0.070608372 | G38: =G36/G35 -> 0.034465329 | H38: =H36/H35 -> 0.043879129 | I38: =I36/I35 -> 0.04451873 | J38: =J36/J35 -> 0.046750892 | ... Q38: =Q36/Q35 -> 0.068289115
B40: ROE | C40: ='P&L'!C14/'Balance Sheet'!C40 -> 0.17794616 | D40: ='P&L'!D14/'Balance Sheet'!D40 -> 0.27602277 | E40: ='P&L'!E14/'Balance Sheet'!E40 -> 0.23666893 | F40: ='P&L'!F14/'Balance Sheet'!F40 -> 0.09632286 | G40: ='P&L'!G14/'Balance Sheet'!G40 -> 0.045817383 | H40: ='P&L'!H14/'Balance Sheet'!H40 -> 0.041775907 | I40: ='P&L'!I14/'Balance Sheet'!I40 -> 0.042975177 | J40: ='P&L'!J14/'Balance Sheet'!J40 -> 0.045599835 | ... Q40: ='P&L'!Q14/'Balance Sheet'!Q40 -> 0.057803198
B42: Calculation of Reinvestment Rate
B44: Net Capex | D44: ='Balance Sheet'!D15-'Balance Sheet'!C15 -> 4664 | E44: ='Balance Sheet'!E15-'Balance Sheet'!D15 -> 6177 | F44: ='Balance Sheet'!F15-'Balance Sheet'!E15 -> 6111 | G44: ='Balance Sheet'!G15-'Balance Sheet'!F15 -> 4807 | H44: ='Balance Sheet'!H15-'Balance Sheet'!G15 -> 6177.736 | I44: ='Balance Sheet'!I15-'Balance Sheet'!H15 -> 6596.5215 | J44: ='Balance Sheet'!J15-'Balance Sheet'!I15 -> 6947.8643 | K44: ='Balance Sheet'!K15-'Balance Sheet'!J15 -> 7203.0429 | ... Q44: ='Balance Sheet'!Q15-'Balance Sheet'!P15 -> 4365.4773
B45: Change in Working Capital (NON Cash) | D45: =D20-C20 -> 8049 | E45: =E20-D20 -> 7386 | F45: =F20-E20 -> 9013 | G45: =G20-F20 -> 6199 | H45: =H20-G20 -> -4541.0486 | I45: =I20-H20 -> -1288.2677 | J45: =J20-I20 -> -1712.8144 | K45: =K20-J20 -> -1748.0873 | ... Q45: =Q20-P20 -> -1975.6962
B46: Reinvestment | D46: =SUM(D44:D45) -> 12713 | E46: =SUM(E44:E45) -> 13563 | F46: =SUM(F44:F45) -> 15124 | G46: =SUM(G44:G45) -> 11006 | H46: =SUM(H44:H45) -> 1636.6874 | I46: =SUM(I44:I45) -> 5308.2538 | J46: =SUM(J44:J45) -> 5235.0499 | K46: =SUM(K44:K45) -> 5454.9556 | ... Q46: =SUM(Q44:Q45) -> 2389.7811
B48: EBIT | D48: ='Cash Flow'!D5 -> 13656 | E48: ='Cash Flow'!E5 -> 8891 | F48: ='Cash Flow'!F5 -> 7076 | G48: ='Cash Flow'!G5 -> 4355 | H48: ='Cash Flow'!H5 -> 4936.9285 | I48: ='Cash Flow'!I5 -> 5279.2137 | J48: ='Cash Flow'!J5 -> 5828.2411 | K48: ='Cash Flow'!K5 -> 6375.9898 | ... Q48: ='Cash Flow'!Q5 -> 10604.245
B49: Marginal Tax | D49: ='Cash Flow'!D6 -> -1132 | E49: ='Cash Flow'!E6 -> 5001 | F49: ='Cash Flow'!F6 -> -1837 | G49: ='Cash Flow'!G6 -> -1423 | H49: ='Cash Flow'!H6 -> -1036.755 | I49: ='Cash Flow'!I6 -> -1108.6349 | J49: ='Cash Flow'!J6 -> -1223.9306 | K49: ='Cash Flow'!K6 -> -1338.9579 | ... Q49: ='Cash Flow'!Q6 -> -2226.8914
B50: EBIT (1-tax) (NOPAT) | D50: ='Cash Flow'!D7 -> 12524 | E50: ='Cash Flow'!E7 -> 13892 | F50: ='Cash Flow'!F7 -> 5239 | G50: ='Cash Flow'!G7 -> 2932 | H50: ='Cash Flow'!H7 -> 3900.1735 | I50: ='Cash Flow'!I7 -> 4170.5788 | J50: ='Cash Flow'!J7 -> 4604.3104 | K50: ='Cash Flow'!K7 -> 5037.0319 | ... Q50: ='Cash Flow'!Q7 -> 8377.3534
B52: Reinvestment Rate | D52: =D46/D50 -> 1.015091 | E52: =E46/E50 -> 0.9763173 | F52: =F46/F50 -> 2.8868105 | G52: =G46/G50 -> 3.7537517 | H52: =H46/H50 -> 0.41964475 | I52: =I46/I50 -> 1.2727859 | J52: =J46/J50 -> 1.1369889 | K52: =K46/K50 -> 1.0829702 | ... Q52: =Q46/Q50 -> 0.28526684
B54: Intrinsic growth rate | D54: =D52*D38 -> 0.34238238 | E54: =E52*E38 -> 0.2291899 | F54: =F52*F38 -> 0.20383299 | G54: =G52*G38 -> 0.12937429 | H54: =H52*H38 -> 0.018413646 | I54: =I52*I38 -> 0.056662812 | J54: =J52*J38 -> 0.053155245 | K54: =K52*K38 -> 0.052787671 | ... Q54: =Q52*Q38 -> 0.01948062
B57: DCF Valuation
B59: Free cash flow to Firm (FCFF) | G59: ='Cash Flow'!G20 -> -6042 | H59: ='Cash Flow'!H20 -> 4254.1293 | I59: ='Cash Flow'!I20 -> 574.39342 | J59: ='Cash Flow'!J20 -> 1649.8545 | K59: ='Cash Flow'!K20 -> 1909.0577 | L59: ='Cash Flow'!L20 -> 3312.1849 | M59: ='Cash Flow'!M20 -> 3454.1013 | N59: ='Cash Flow'!N20 -> 4278.7133 | ... Q59: ='Cash Flow'!Q20 -> 8619.8276
B61: Mid Year Convention | H61: 0.5 | I61: 1.5 | J61: 2.5 | K61: 3.5 | L61: 4.5 | M61: 5.5 | N61: 6.5 | O61: 7.5 | P61: 8.5 | Q61: 9.5
B62: Discounting Factor | H62: =1/(1+H63)^H61 -> 0.95171111 | I62: =1/(1+I63)^I61 -> 0.86201617 | J62: =1/(1+J63)^J61 -> 0.78077462 | K62: =1/(1+K63)^K61 -> 0.70718975 | L62: =1/(1+L63)^L61 -> 0.64053997 | M62: =1/(1+M63)^M61 -> 0.58017166 | N62: =1/(1+N63)^N61 -> 0.52549282 | O62: =1/(1+O63)^O61 -> 0.47596723 | ... Q62: =1/(1+Q63)^Q61 -> 0.39047893
B63: WACC | H63: =WACC!$N$38 -> 0.1040525 | I63: =WACC!$N$38 -> 0.1040525 | J63: =WACC!$N$38 -> 0.1040525 | K63: =WACC!$N$38 -> 0.1040525 | L63: =WACC!$N$38 -> 0.1040525 | M63: =WACC!$N$38 -> 0.1040525 | N63: =WACC!$N$38 -> 0.1040525 | O63: =WACC!$N$38 -> 0.1040525 | ... Q63: =WACC!$N$38 -> 0.1040525
B65: PV of FCFF | H65: =H59*H62 -> 4048.7021 | I65: =I59*I62 -> 495.13641 | J65: =J59*J62 -> 1288.1645 | K65: =K59*K62 -> 1350.066 | L65: =L59*L62 -> 2121.5868 | M65: =M59*M62 -> 2003.9717 | N65: =N59*N62 -> 2248.4331 | O65: =O59*O62 -> 2557.2818 | ... Q65: =Q59*Q62 -> 3365.8611
B67: Expected Growth | D67: =MEDIAN(D54:Q54) -> 0.050556781
B68: Terminal Growth | D68: =Drivers!C7 -> 0.0455
B69: WACC | D69: =WACC!$N$38 -> 0.1040525
B71: Calculation of Terminal Value | G71: Sensitivity Analysis
B73: FCFF(n+1) | D73: =Q59*(1+D67) -> 9055.6183 | G73: =D77 -> 154658.1 | H73: =I73-0.01 -> 0.0355 | I73: =D68 -> 0.0455 | J73: =I73+0.01 -> 0.0555 | K73: =J73+0.01 -> 0.0655 | L73: =K73+0.01 -> 0.0755
B74: WACC | D74: =D69 -> 0.1040525 | G74: =G75-0.02 -> 0.084052501 | H74: =$D$73/($G74-H$73) -> 186511.88 | I74: =$D$73/($G74-I$73) -> 234890.56 | J74: =$D$73/($G74-J$73) -> 317156.75 | K74: =$D$73/($G74-K$73) -> 488107.7 | L74: =$D$73/($G74-L$73) -> 1058827
B75: Terminal growth Rate | D75: =D68 -> 0.0455 | G75: =D74 -> 0.1040525 | H75: =$D$73/($G75-H$73) -> 132097.56 | I75: =$D$73/($G75-I$73) -> 154658.1 | J75: =$D$73/($G75-J$73) -> 186511.88 | K75: =$D$73/($G75-K$73) -> 234890.56 | L75: =$D$73/($G75-L$73) -> 317156.75
G76: =G75+0.02 -> 0.1240525 | H76: =$D$73/($G76-H$73) -> 102262.71 | I76: =$D$73/($G76-I$73) -> 115281.1 | J76: =$D$73/($G76-J$73) -> 132097.56 | K76: =$D$73/($G76-K$73) -> 154658.1 | L76: =$D$73/($G76-L$73) -> 186511.88
B77: Terminal Value | D77: =D73/(D74-D75) -> 154658.1 | G77: =G76+0.02 -> 0.1440525 | H77: =$D$73/($G77-H$73) -> 83421.554 | I77: =$D$73/($G77-I$73) -> 91886.236 | J77: =$D$73/($G77-J$73) -> 102262.71 | K77: =$D$73/($G77-K$73) -> 115281.1 | L77: =$D$73/($G77-L$73) -> 132097.56
G78: =G77+0.02 -> 0.1640525 | H78: =$D$73/($G78-H$73) -> 70442.957 | I78: =$D$73/($G78-I$73) -> 76384.878 | J78: =$D$73/($G78-J$73) -> 83421.554 | K78: =$D$73/($G78-K$73) -> 91886.236 | L78: =$D$73/($G78-L$73) -> 102262.71
B79: Calculation of Enterprise Value | G79: =G78+0.02 -> 0.1840525 | H79: =$D$73/($G79-H$73) -> 60959.043 | I79: =$D$73/($G79-I$73) -> 65358.75 | J79: =$D$73/($G79-J$73) -> 70442.957 | K79: =$D$73/($G79-K$73) -> 76384.878 | L79: =$D$73/($G79-L$73) -> 83421.554
B81: PV of FCFF | D81: =SUM(H65:Q65) -> 22409.475
B82: PV of Terminal Value | D82: =D77*Q62 -> 60390.728
B83: Value of Operating Asset | D83: =SUM(D81:D82) -> 82800.203
B85: Add: Cash | D85: ='Balance Sheet'!G5 -> 16513
B86: Less: Debt | D86: ='Balance Sheet'!G34 -> 8376
B87: Value of Equity | D87: =D83+D85-D86 -> 90937.203
B88: No. of Shares | D88: =Drivers!C14 -> 3752.43
B89: Value per Share | D89: =D87/D88 -> 24.234217
B91: Current Market Value per Share | D91: =Drivers!C10 -> 408.95
B93: implied premium/discount multiple | D93: =D91/D89 -> 16.8749
